Workbook
Name Aljibe: '05.- PU Clave'!$D$21
Name Arena: '05.- PU Clave'!$D$26
Name Ayudante: '05.- PU Clave'!$D$6
Name Base100: '05.- PU Clave'!$D$24
Name Base50: '05.- PU Clave'!$D$25
Name Bolones: '05.- PU Clave'!$D$29
Name Cerámista: '05.- PU Clave'!$D$8
Name CuboDren: '05.- PU Clave'!$D$44
Name Enf: '05.- PU Clave'!$D$10
Name Excavadora: '05.- PU Clave'!$D$16
Name GasfArtef: '05.- PU Clave'!#REF!
Name GasfGrif: '05.- PU Clave'!#REF!
Name Grava: '05.- PU Clave'!$D$28
Name Gravilla: '05.- PU Clave'!$D$27
Name H: '03.- Cubicaciones'!#REF!
Name H: '03.- Cubicaciones'!#REF!
Name HormG15: '05.- PU Clave'!$D$34
Name HormG20: '05.- PU Clave'!$D$33
Name HormG25: '05.- PU Clave'!$D$32
Name HormG5: '05.- PU Clave'!$D$35
Name Jornal: '05.- PU Clave'!$D$7
Name Maestro: '05.- PU Clave'!$D$5
Name Met: '05.- PU Clave'!$D$11
Name Motoniveladora: '05.- PU Clave'!$D$18
Name Pintor: '05.- PU Clave'!$D$9
Name Retroexcavadora: '05.- PU Clave'!$D$17
Name Rodillo: '05.- PU Clave'!$D$19
Name SCAcmafor: '05.- PU Clave'!$D$39
Name SCArtElé: '05.- PU Clave'!#REF!
Name SCBulldog: '05.- PU Clave'!$D$38
Name SCHidrosembrado: '05.- PU Clave'!$D$40
Name SCHoj: '05.- PU Clave'!$D$41
Name SCPV4: '05.- PU Clave'!#REF!
Name SCSan: '05.- PU Clave'!$D$42
Name SoldadorA: '05.- PU Clave'!$D$13
Name SoldadorM: '05.- PU Clave'!$D$12
Name Tolva: '05.- PU Clave'!$D$20
Name UF: '05.- PU Clave'!$J$4

Sheet 01.- Presupuesto
H2: Fecha: | I2: 45847 | S2: Materiales | T2: =SUM(M15:M192) -> 1.8947404e+08
H3: Revisión | I3: 0 | S3: Mano de Obra | T3: =SUM(N15:N192) -> 13405164
B4: PRESUPUESTO ESTIMATIVO N° 208 | S4: Subcontratos | T4: =SUM(O15:O192) -> 1.3801322e+08
B5: OBRAS CIVILES CENTRAL LOICA | S5: Servios &Arr | T5: =SUM(P15:P192) -> 93257515
T6: =SUM(T2:T5) -> 4.3414995e+08 | V6: =I195-T6 -> 0.003372848
C7: TIPO | D7: Industrial
C8: CLIENTE | D8: Potencia Sur SpA
C9: DIRECCIÓN | D9: Avenida Providencia 329, Piso 6
C10: COMUNA | D10: Providencia, RM
B12: ITEM | C12: DESCRIPCION | F12: UNIDAD | G12: CANTIDAD | H12: P. UNITARIO | I12: P. TOTAL | M12: Materiales | N12: Mano de Obra | O12: Subcontratos | P12: Servios &Arr | Q12: Total
C14: Movimiento de Tierra | I14: =SUM(I15:I36) -> 1.7009047e+08 | Q14: =SUM(Q15:Q36) -> 1.7009047e+08
B15: 1 | C15: Desbroce | S15: =I15-Q15 -> 0
B16: 1.1 | C16: Desbroce | F16: gl | G16: ='03.- Cubicaciones'!C5 -> 1 | H16: ='1.1'!$G$4 -> 19164000 | I16: =IF(G16="","",G16*H16) -> 19164000 | M16: ='1.1'!$M$4 -> 0 | N16: ='1.1'!$N$4 -> 0 | O16: ='1.1'!$O$4 -> 0 | P16: ='1.1'!$P$4 -> 19164000 | Q16: =SUM(M16:P16) -> 19164000 | S16: =I16-Q16 -> 0
B17: 2 | C17: Demoliciones y Retiros de Escombros
B18: 2.1 | C18: Excavación, carguió sobre camión y traslado a botadero, e = variable | F18: m3 | G18: ='03.- Cubicaciones'!C7 -> 890 | H18: ='2.1'!$G$4 -> 25500 | I18: =IF(G18="","",G18*H18) -> 22695000 | M18: ='2.1'!$M$4 -> 0 | N18: ='2.1'!$N$4 -> 0 | O18: ='2.1'!$O$4 -> 0 | P18: ='2.1'!$P$4 -> 22695000 | Q18: =SUM(M18:P18) -> 22695000 | S18: =I18-Q18 -> 0
B19: 2.2 | C19: Retiro y reposición zanja para ducto malla de puesta a tierra | F19: m3 | G19: ='03.- Cubicaciones'!C8 -> 400 | H19: ='2.2'!$G$4 -> 34101.438 | I19: =IF(G19="","",G19*H19) -> 13640575 | M19: ='2.2'!$M$4 -> 10400000 | N19: ='2.2'!$N$4 -> 1153555.6 | O19: ='2.2'!$O$4 -> 0 | P19: ='2.2'!$P$4 -> 2087019.6 | Q19: =SUM(M19:P19) -> 13640575 | S19: =I19-Q19 -> 0
B20: 2.3 | C20: Formación y compactación de plataforma e= variable. Relleno e= 20cm | F20: m3 | G20: ='03.- Cubicaciones'!C9 -> 754 | H20: ='2.3'!$G$4 -> 67330.534 | I20: =IF(G20="","",G20*H20) -> 50767223 | M20: ='2.3'!$M$4 -> 42295257 | N20: ='2.3'!$N$4 -> 1961044.4 | O20: ='2.3'!$O$4 -> 0 | P20: ='2.3'!$P$4 -> 6510921.2 | Q20: =SUM(M20:P20) -> 50767223 | S20: =I20-Q20 -> 0.0062984005
B21: 2.4 | C21: Tratamiento de taludes de corte con hidrosiembra según manual de carreteras | F21: gl | G21: ='03.- Cubicaciones'!C10 -> 1 | H21: ='2.4'!$G$4 -> 42742 | I21: =IF(G21="","",G21*H21) -> 42742 | M21: ='2.4'!$M$4 -> 0 | N21: ='2.4'!$N$4 -> 0 | O21: ='2.4'!$O$4 -> 42742 | P21: ='2.4'!$P$4 -> 0 | Q21: =SUM(M21:P21) -> 42742 | S21: =I21-Q21 -> 0
B22: 3 | C22: Movimiento de Tierra Camino Acceso
B23: 3.1 | C23: Sobrexcavación para caminos interiores, carguio sobre camión y traslado | F23: m3 | G23: ='03.- Cubicaciones'!C12 -> 760 | H23: ='3.1'!$G$4 -> 25500 | I23: =IF(G23="","",G23*H23) -> 19380000 | M23: ='3.1'!$M$4 -> 0 | N23: ='3.1'!$N$4 -> 0 | O23: ='3.1'!$O$4 -> 0 | P23: ='3.1'!$P$4 -> 19380000 | Q23: =SUM(M23:P23) -> 19380000 | S23: =I23-Q23 -> 0
B24: 3.2 | C24: Suministro y colocación Base Granular CBR >100% e=26cm | F24: m3 | G24: ='03.- Cubicaciones'!C13 -> 234 | H24: ='3.2'!$G$4 -> 37444.098 | I24: =IF(G24="","",G24*H24) -> 8761918.9 | M24: ='3.2'!$M$4 -> 6692400 | N24: ='3.2'!$N$4 -> 0 | O24: ='3.2'!$O$4 -> 0 | P24: ='3.2'!$P$4 -> 2069518.9 | Q24: =SUM(M24:P24) -> 8761918.9 | S24: =I24-Q24 -> 0
B25: 3.3 | C25: Suministro y colocación Sub-Base granular CBR > 50% e=20cm | F25: m3 | G25: ='03.- Cubicaciones'!C14 -> 180 | H25: ='3.3'!$G$4 -> 35161.255 | I25: =IF(G25="","",G25*H25) -> 6329025.9 | M25: ='3.3'!$M$4 -> 4680000 | N25: ='3.3'!$N$4 -> 0 | O25: ='3.3'!$O$4 -> 0 | P25: ='3.3'!$P$4 -> 1649025.9 | Q25: =SUM(M25:P25) -> 6329025.9 | S25: =I25-Q25 -> 0
B26: 3.4 | C26: Suministro y colocación de bolones para estabilización de suelos e=30cm | F26: m3 | G26: ='03.- Cubicaciones'!C15 -> 270 | H26: ='3.4'!$G$4 -> 49700 | I26: =IF(G26="","",G26*H26) -> 13419000 | M26: ='3.4'!$M$4 -> 12987000 | N26: ='3.4'!$N$4 -> 0 | O26: ='3.4'!$O$4 -> 0 | P26: ='3.4'!$P$4 -> 432000 | Q26: =SUM(M26:P26) -> 13419000 | S26: =I26-Q26 -> 0
B27: 3.5 | C27: Suministro e Instalación de Geotextil bajo la Sub-Base | F27: m2 | G27: ='03.- Cubicaciones'!C16 -> 900 | H27: ='3.5'!$G$4 -> 1623.533 | I27: =IF(G27="","",G27*H27) -> 1461179.7 | M27: ='3.5'!$M$4 -> 1188000 | N27: ='3.5'!$N$4 -> 227649.6 | O27: ='3.5'!$O$4 -> 0 | P27: ='3.5'!$P$4 -> 45530.1 | Q27: =SUM(M27:P27) -> 1461179.7 | S27: =I27-Q27 -> 0
B28: 4 | C28: Sistema Drenajes
B29: 4.1 | C29: Suministro de materiales y construcción de zanja de infiltración, incluye cubo dren | F29: m | G29: ='03.- Cubicaciones'!C18 -> 6.3 | H29: ='4.1'!$G$4 -> 315982.17 | I29: =IF(G29="","",G29*H29) -> 1990687.6 | M29: ='4.1'!$M$4 -> 680431.52 | N29: ='4.1'!$N$4 -> 241535.93 | O29: ='4.1'!$O$4 -> 767550 | P29: ='4.1'!$P$4 -> 301170.2 | Q29: =SUM(M29:P29) -> 1990687.6 | S29: =I29-Q29 -> -0.0029256162
B30: 4.2 | C30: Suministro de materiales y construcción cámaras de filtración y decantación | F30: un | G30: ='03.- Cubicaciones'!C19 -> 1 | H30: ='4.2'!$G$4 -> 650632.39 | I30: =IF(G30="","",G30*H30) -> 650632.39 | M30: ='4.2'!$M$4 -> 424713.73 | N30: ='4.2'!$N$4 -> 144355.56 | O30: ='4.2'!$O$4 -> 37692 | P30: ='4.2'!$P$4 -> 43871.111 | Q30: =SUM(M30:P30) -> 650632.39 | S30: =I30-Q30 -> 0
B31: 5 | C31: Cierre Perimetral Exterior
B32: 5.1 | C32: Suministro e instalación cierre perimetral tipo Bulldog | F32: m | G32: ='03.- Cubicaciones'!C21 -> 50 | H32: ='5.1'!$G$4 -> 30000 | I32: =IF(G32="","",G32*H32) -> 1500000 | M32: ='5.1'!$M$4 -> 0 | N32: ='5.1'!$N$4 -> 0 | O32: ='5.1'!$O$4 -> 1500000 | P32: ='5.1'!$P$4 -> 0 | Q32: =SUM(M32:P32) -> 1500000 | S32: =I32-Q32 -> 0
B33: 5.2 | C33: Suministro e instalación cierre perimetral tipo Acmafor | F33: m | G33: ='03.- Cubicaciones'!C22 -> 280 | H33: ='5.2'!$G$4 -> 30550 | I33: =IF(G33="","",G33*H33) -> 8554000 | M33: ='5.2'!$M$4 -> 0 | N33: ='5.2'!$N$4 -> 0 | O33: ='5.2'!$O$4 -> 8554000 | P33: ='5.2'!$P$4 -> 0 | Q33: =SUM(M33:P33) -> 8554000 | S33: =I33-Q33 -> 0
B34: 5.3 | C34: Suministro e instalación portón metálico vehicular 5m | F34: un | G34: ='03.- Cubicaciones'!C23 -> 1 | H34: ='5.3'!$G$4 -> 1214017 | I34: =IF(G34="","",G34*H34) -> 1214017 | M34: ='5.3'!$M$4 -> 0 | N34: ='5.3'!$N$4 -> 0 | O34: ='5.3'!$O$4 -> 1214017 | P34: ='5.3'!$P$4 -> 0 | Q34: =SUM(M34:P34) -> 1214017 | S34: =I34-Q34 -> 0
B35: 5.4 | C35: Suministro e instalación portón metálico peatonal 1m | F35: un | G35: ='03.- Cubicaciones'!C24 -> 1 | H35: ='5.4'!$G$4 -> 520466 | I35: =IF(G35="","",G35*H35) -> 520466 | M35: ='5.4'!$M$4 -> 0 | N35: ='5.4'!$N$4 -> 0 | O35: ='5.4'!$O$4 -> 520466 | P35: ='5.4'!$P$4 -> 0 | Q35: =SUM(M35:P35) -> 520466 | S35: =I35-Q35 -> 0
I36: =IF(G36="","",G36*H36)
C37: Fundación Equipos | I37: =SUM(I38:I112) -> 53573139 | Q37: =SUM(Q38:Q112) -> 53573139
B38: 6 | C38: Fundación Grupo Generador a gas GLP, 05 unidades.
B39: 6.1 | C39: Suministro e Instalación Hormigón G25(10)20-8 | F39: m3 | G39: ='03.- Cubicaciones'!C28 -> 36.75 | H39: ='6.1'!$G$4 -> 141504.27 | I39: =IF(G39="","",G39*H39) -> 5200281.8 | M39: ='6.1'!$M$4 -> 4568100.2 | N39: ='6.1'!$N$4 -> 353276.39 | O39: ='6.1'!$O$4 -> 0 | P39: ='6.1'!$P$4 -> 278905.27 | Q39: =SUM(M39:P39) -> 5200281.8 | S39: =I39-Q39 -> 0
B40: 6.2 | C40: Suministro e instalación emplantillado hormigón G5 | F40: m3 | G40: ='03.- Cubicaciones'!C29 -> 5.25 | H40: ='6.2'!$G$4 -> 120719.81 | I40: =IF(G40="","",G40*H40) -> 633778.98 | M40: ='6.2'!$M$4 -> 573217.31 | N40: ='6.2'!$N$4 -> 50468.056 | O40: ='6.2'!$O$4 -> 0 | P40: ='6.2'!$P$4 -> 10093.613 | Q40: =SUM(M40:P40) -> 633778.98 | S40: =I40-Q40 -> 0
B41: 6.3 | C41: Suministro e Instalación relleno estructural compactado al 95% DMSC | F41: m3 | G41: ='03.- Cubicaciones'!C30 -> 199.5 | H41: ='6.3'!$G$4 -> 31578.854 | I41: =IF(G41="","",G41*H41) -> 6299981.4 | M41: ='6.3'!$M$4 -> 5187000 | N41: ='6.3'!$N$4 -> 287667.83 | O41: ='6.3'!$O$4 -> 0 | P41: ='6.3'!$P$4 -> 825313.54 | Q41: =SUM(M41:P41) -> 6299981.4 | S41: =I41-Q41 -> 0
B42: 6.4 | C42: Excavación maquinaría local y traslado a botadero, hasta 20 Km | F42: m3 | G42: ='03.- Cubicaciones'!C31 -> 246.75 | H42: ='6.4'!$G$4 -> 25500 | I42: =IF(G42="","",G42*H42) -> 6292125 | M42: ='6.4'!$M$4 -> 0 | N42: ='6.4'!$N$4 -> 0 | O42: ='6.4'!$O$4 -> 0 | P42: ='6.4'!$P$4 -> 6292125 | Q42: =SUM(M42:P42) -> 6292125 | S42: =I42-Q42 -> 0
B43: 6.5 | C43: Suministro y construcción moldajes de madera o metálicos | F43: m2 | G43: ='03.- Cubicaciones'!C32 -> 35 | H43: ='6.5'!$G$4 -> 16475.796 | I43: =IF(G43="","",G43*H43) -> 576652.86 | M43: ='6.5'!$M$4 -> 414252.86 | N43: ='6.5'!$N$4 -> 135333.35 | O43: ='6.5'!$O$4 -> 0 | P43: ='6.5'!$P$4 -> 27066.655 | Q43: =SUM(M43:P43) -> 576652.86 | S43: =I43-Q43 -> 0
B44: 6.6 | C44: Suministro e instalación armadura A630-420H, diámetro 12mm | F44: kg | G44: ='03.- Cubicaciones'!C33 -> 1963.785 | H44: ='6.6'!$G$4 -> 1644.333 | I44: =IF(G44="","",G44*H44) -> 3229116.5 | M44: ='6.6'!$M$4 -> 2050845.5 | N44: ='6.6'!$N$4 -> 0 | O44: ='6.6'!$O$4 -> 1178271 | P44: ='6.6'!$P$4 -> 0 | Q44: =SUM(M44:P44) -> 3229116.5 | S44: =I44-Q44 -> 0
B45: 6.7 | C45: Suministro e instalación de pernos de anclaje químico | F45: un | G45: ='03.- Cubicaciones'!C34 -> 280 | H45: ='6.7'!$G$4 -> 11342.214 | I45: =IF(G45="","",G45*H45) -> 3175819.9 | M45: ='6.7'!$M$4 -> 2769819.9 | N45: ='6.7'!$N$4 -> 338333.24 | O45: ='6.7'!$O$4 -> 0 | P45: ='6.7'!$P$4 -> 67666.76 | Q45: =SUM(M45:P45) -> 3175819.9 | S45: =I45-Q45 -> 0
B46: 7 | C46: Fundación Transformador 2,0 MVA, 05 unidades
B47: 7.1 | C47: Suministro e Instalación Hormigón G20(10)20-8 | F47: m3 | G47: ='03.- Cubicaciones'!C36 -> 20 | H47: ='7.1'!$G$4 -> 137616.83 | I47: =IF(G47="","",G47*H47) -> 2752336.7 | M47: ='7.1'!$M$4 -> 2408292.2 | N47: ='7.1'!$N$4 -> 192259.26 | O47: ='7.1'!$O$4 -> 0 | P47: ='7.1'!$P$4 -> 151785.18 | Q47: =SUM(M47:P47) -> 2752336.7 | S47: =I47-Q47 -> 0
B48: 7.2 | C48: Suministro e instalación emplantillado hormigón G5 | F48: m3 | G48: ='03.- Cubicaciones'!C37 -> 2.5 | H48: ='7.2'!$G$4 -> 120719.81 | I48: =IF(G48="","",G48*H48) -> 301799.52 | M48: ='7.2'!$M$4 -> 272960.62 | N48: ='7.2'!$N$4 -> 24032.408 | O48: ='7.2'!$O$4 -> 0 | P48: ='7.2'!$P$4 -> 4806.4825 | Q48: =SUM(M48:P48) -> 301799.51 | S48: =I48-Q48 -> 0
B49: 7.3 | C49: Suministro e Instalación relleno estructural compactado al 95% DMSC | F49: m3 | G49: ='03.- Cubicaciones'!C38 -> 24.3775 | H49: ='7.3'!$G$4 -> 46609.266 | I49: =IF(G49="","",G49*H49) -> 1136217.4 | M49: ='7.3'!$M$4 -> 633815 | N49: ='7.3'!$N$4 -> 35150.99 | O49: ='7.3'!$O$4 -> 0 | P49: ='7.3'!$P$4 -> 467251.39 | Q49: =SUM(M49:P49) -> 1136217.4 | S49: =I49-Q49 -> 0
B50: 7.4 | C50: Excavación maquinaría local y traslado a botadero, hasta 20 Km | F50: m3 | G50: ='03.- Cubicaciones'!C39 -> 48.05 | H50: ='7.4'!$G$4 -> 25500 | I50: =IF(G50="","",G50*H50) -> 1225275 | M50: ='7.4'!$M$4 -> 0 | N50: ='7.4'!$N$4 -> 0 | O50: ='7.4'!$O$4 -> 0 | P50: ='7.4'!$P$4 -> 1225275 | Q50: =SUM(M50:P50) -> 1225275 | S50: =I50-Q50 -> 0
B51: 7.5 | C51: Suministro y construcción moldajes de madera o metálicos | F51: m2 | G51: ='03.- Cubicaciones'!C40 -> 95 | H51: ='7.5'!$G$4 -> 16475.796 | I51: =IF(G51="","",G51*H51) -> 1565200.6 | M51: ='7.5'!$M$4 -> 1124400.6 | N51: ='7.5'!$N$4 -> 367333.36 | O51: ='7.5'!$O$4 -> 0 | P51: ='7.5'!$P$4 -> 73466.635 | Q51: =SUM(M51:P51) -> 1565200.6 | S51: =I51-Q51 -> 0
B52: 7.6 | C52: Suministro e instalación armadura A630-420H, diámetro 12mm | F52: kg | G52: ='03.- Cubicaciones'!C41 -> 600 | H52: ='7.6'!$G$4 -> 1644.333 | I52: =IF(G52="","",G52*H52) -> 986599.8 | M52: ='7.6'!$M$4 -> 626599.8 | N52: ='7.6'!$N$4 -> 0 | O52: ='7.6'!$O$4 -> 360000 | P52: ='7.6'!$P$4 -> 0 | Q52: =SUM(M52:P52) -> 986599.8 | S52: =I52-Q52 -> 0
B53: 7.7 | C53: Suministro e instalación de pernos de anclaje químico | F53: un | G53: ='03.- Cubicaciones'!C42 -> 20 | H53: ='7.7'!$G$4 -> 11342.214 | I53: =IF(G53="","",G53*H53) -> 226844.28 | M53: ='7.7'!$M$4 -> 197844.28 | N53: ='7.7'!$N$4 -> 24166.66 | O53: ='7.7'!$O$4 -> 0 | P53: ='7.7'!$P$4 -> 4833.34 | Q53: =SUM(M53:P53) -> 226844.28 | S53: =I53-Q53 -> 0
B54: 7.8 | C54: Suministro e instalación enfierradura malla acma C-188 | F54: kg | G54: ='03.- Cubicaciones'!C43 -> 180 | H54: ='7.8'!$G$4 -> 2586.773 | I54: =IF(G54="","",G54*H54) -> 465619.14 | M54: ='7.8'!$M$4 -> 257979.06 | N54: ='7.8'!$N$4 -> 173033.46 | O54: ='7.8'!$O$4 -> 0 | P54: ='7.8'!$P$4 -> 34606.62 | Q54: =SUM(M54:P54) -> 465619.14 | S54: =I54-Q54 -> 0
B55: 7.9 | C55: Suministro e instalación parrilla de piso Arriogoni ARS-3 | F55: m2 | G55: ='03.- Cubicaciones'!C44 -> 19 | H55: ='7.9'!$G$4 -> 85931.568 | I55: =IF(G55="","",G55*H55) -> 1632699.8 | M55: ='7.9'!$M$4 -> 863199.79 | N55: ='7.9'!$N$4 -> 0 | O55: ='7.9'!$O$4 -> 769500 | P55: ='7.9'!$P$4 -> 0 | Q55: =SUM(M55:P55) -> 1632699.8 | S55: =I55-Q55 -> 0
B56: 7.10 | C56: Suministro e instalación ángulo acero L30x3 | F56: m | G56: ='03.- Cubicaciones'!C45 -> 60 | H56: ='7.10'!$G$4 -> 4973.725 | I56: =IF(G56="","",G56*H56) -> 298423.5 | M56: ='7.10'!$M$4 -> 175573.5 | N56: ='7.10'!$N$4 -> 0 | O56: ='7.10'!$O$4 -> 122850 | P56: ='7.10'!$P$4 -> 0 | Q56: =SUM(M56:P56) -> 298423.5 | S56: =I56-Q56 -> 0
B57: 7.11 | C57: Suministro e instalación ángulo acero L50x5 | F57: m | G57: ='03.- Cubicaciones'!C46 -> 50 | H57: ='7.11'!$G$4 -> 12127.177 | I57: =IF(G57="","",G57*H57) -> 606358.85 | M57: ='7.11'!$M$4 -> 317936.95 | N57: ='7.11'!$N$4 -> 0 | O57: ='7.11'!$O$4 -> 288421.9 | P57: ='7.11'!$P$4 -> 0 | Q57: =SUM(M57:P57) -> 606358.85 | S57: =I57-Q57 -> 0
B58: 8 | C58: Fundaciones Radiadores
B59: 8.1 | C59: Suministro e Instalación Hormigón G25(10)20-8 | F59: m3 | G59: ='03.- Cubicaciones'!C48 -> 5.916 | H59: ='8.1'!$G$4 -> 141504.27 | I59: =IF(G59="","",G59*H59) -> 837139.24 | M59: ='8.1'!$M$4 -> 735370.9 | N59: ='8.1'!$N$4 -> 56870.289 | O59: ='8.1'!$O$4 -> 0 | P59: ='8.1'!$P$4 -> 44898.056 | Q59: =SUM(M59:P59) -> 837139.24 | S59: =I59-Q59 -> 0
B60: 8.2 | C60: Suministro e instalación emplantillado hormigón G5 | F60: m3 | G60: ='03.- Cubicaciones'!C49 -> 0.493 | H60: ='8.2'!$G$4 -> 120719.81 | I60: =IF(G60="","",G60*H60) -> 59514.864 | M60: ='8.2'!$M$4 -> 53827.835 | N60: ='8.2'!$N$4 -> 4739.1908 | O60: ='8.2'!$O$4 -> 0 | P60: ='8.2'!$P$4 -> 947.83835 | Q60: =SUM(M60:P60) -> 59514.864 | S60: =I60-Q60 -> 0
B61: 8.3 | C61: Suministro e Instalación relleno estructural compactado al 95% DMSC | F61: m3 | G61: ='03.- Cubicaciones'!C50 -> 7.6415 | H61: ='8.3'!$G$4 -> 84110.441 | I61: =IF(G61="","",G61*H61) -> 642729.93 | M61: ='8.3'!$M$4 -> 198679 | N61: ='8.3'!$N$4 -> 11018.615 | O61: ='8.3'!$O$4 -> 0 | P61: ='8.3'!$P$4 -> 433032.32 | Q61: =SUM(M61:P61) -> 642729.93 | S61: =I61-Q61 -> 0
B62: 8.4 | C62: Excavación maquinaría local y traslado a botadero, hasta 20 Km | F62: m3 | G62: ='03.- Cubicaciones'!C51 -> 15.283 | H62: ='8.4'!$G$4 -> 25500 | I62: =IF(G62="","",G62*H62) -> 389716.5 | M62: ='8.4'!$M$4 -> 0 | N62: ='8.4'!$N$4 -> 0 | O62: ='8.4'!$O$4 -> 0 | P62: ='8.4'!$P$4 -> 389716.5 | Q62: =SUM(M62:P62) -> 389716.5 | S62: =I62-Q62 -> 0
B63: 8.5 | C63: Suministro y construcción moldajes de madera o metálicos | F63: m2 | G63: ='03.- Cubicaciones'!C52 -> 26.16 | H63: ='8.5'!$G$4 -> 16475.796 | I63: =IF(G63="","",G63*H63) -> 431006.82 | M63: ='8.5'!$M$4 -> 309624.42 | N63: ='8.5'!$N$4 -> 101152.01 | O63: ='8.5'!$O$4 -> 0 | P63: ='8.5'!$P$4 -> 20230.391 | Q63: =SUM(M63:P63) -> 431006.82 | S63: =I63-Q63 -> 0
B64: 8.6 | C64: Suministro e instalación armadura A630-420H, diámetro 12mm | F64: kg | G64: ='03.- Cubicaciones'!C53 -> 392 | H64: ='8.6'!$G$4 -> 1644.333 | I64: =IF(G64="","",G64*H64) -> 644578.54 | M64: ='8.6'!$M$4 -> 409378.54 | N64: ='8.6'!$N$4 -> 0 | O64: ='8.6'!$O$4 -> 235200 | P64: ='8.6'!$P$4 -> 0 | Q64: =SUM(M64:P64) -> 644578.54 | S64: =I64-Q64 -> 0
B65: 8.7 | C65: Suministro e instalación de pernos de anclaje químico | F65: un | G65: ='03.- Cubicaciones'!C54 -> 64 | H65: ='8.7'!$G$4 -> 11342.214 | I65: =IF(G65="","",G65*H65) -> 725901.7 | M65: ='8.7'!$M$4 -> 633101.7 | N65: ='8.7'!$N$4 -> 77333.312 | O65: ='8.7'!$O$4 -> 0 | P65: ='8.7'!$P$4 -> 15466.688 | Q65: =SUM(M65:P65) -> 725901.7 | S65: =I65-Q65 -> 0
B66: 9 | C66: Cámara Separadora, ubicación aledaño a PMT
B67: 9.1 | C67: Suministro e Instalación Hormigón G15, con aditivo impermeabilizante, igol denso. | F67: m3 | G67: ='03.- Cubicaciones'!C56 -> 2.112 | H67: ='9.1'!$G$4 -> 222362.55 | I67: =IF(G67="","",G67*H67) -> 469629.71 | M67: ='9.1'!$M$4 -> 331218.62 | N67: ='9.1'!$N$4 -> 105369.24 | O67: ='9.1'!$O$4 -> 0 | P67: ='9.1'!$P$4 -> 33041.847 | Q67: =SUM(M67:P67) -> 469629.71 | S67: =I67-Q67 -> 0
B68: 9.2 | C68: Suministro e instalación emplantillado hormigón G5 | F68: m3 | G68: ='03.- Cubicaciones'!C57 -> 0.1805 | H68: ='9.2'!$G$4 -> 120719.81 | I68: =IF(G68="","",G68*H68) -> 21789.925 | M68: ='9.2'!$M$4 -> 19707.757 | N68: ='9.2'!$N$4 -> 1735.1398 | O68: ='9.2'!$O$4 -> 0 | P68: ='9.2'!$P$4 -> 347.02804 | Q68: =SUM(M68:P68) -> 21789.925 | S68: =I68-Q68 -> 0
B69: 9.3 | C69: Suministro e instalación enfierradura malla acma C-188 | F69: kg | G69: ='03.- Cubicaciones'!C58 -> 66 | H69: ='9.3'!$G$4 -> 2586.773 | I69: =IF(G69="","",G69*H69) -> 170727.02 | M69: ='9.3'!$M$4 -> 94592.322 | N69: ='9.3'!$N$4 -> 63445.602 | O69: ='9.3'!$O$4 -> 0 | P69: ='9.3'!$P$4 -> 12689.094 | Q69: =SUM(M69:P69) -> 170727.02 | S69: =I69-Q69 -> 0
B70: 9.4 | C70: Excavación maquinaría local y traslado a botadero, hasta 20 Km | F70: m3 | G70: ='03.- Cubicaciones'!C59 -> 6.137 | H70: ='9.4'!$G$4 -> 25500 | I70: =IF(G70="","",G70*H70) -> 156493.5 | M70: ='9.4'!$M$4 -> 0 | N70: ='9.4'!$N$4 -> 0 | O70: ='9.4'!$O$4 -> 0 | P70: ='9.4'!$P$4 -> 156493.5 | Q70: =SUM(M70:P70) -> 156493.5 | S70: =I70-Q70 -> 0
B71: 9.5 | C71: Suministro y construcción moldajes de madera o metálicos | F71: m2 | G71: ='03.- Cubicaciones'!C60 -> 21.12 | H71: ='9.5'!$G$4 -> 16475.796 | I71: =IF(G71="","",G71*H71) -> 347968.81 | M71: ='9.5'!$M$4 -> 249972.01 | N71: ='9.5'!$N$4 -> 81664.007 | O71: ='9.5'!$O$4 -> 0 | P71: ='9.5'!$P$4 -> 16332.793 | Q71: =SUM(M71:P71) -> 347968.81 | S71: =I71-Q71 -> 0
B72: 9.6 | C72: Tapa en losa de hormigón G15, incluye armadura acma 188, aditivo imperm. | F72: un | G72: ='03.- Cubicaciones'!C61 -> 1 | H72: ='9.6'!$G$4 -> 136004.35 | I72: =IF(G72="","",G72*H72) -> 136004.35 | M72: ='9.6'!$M$4 -> 88379.347 | N72: ='9.6'!$N$4 -> 27187.5 | O72: ='9.6'!$O$4 -> 0 | P72: ='9.6'!$P$4 -> 20437.5 | Q72: =SUM(M72:P72) -> 136004.35 | S72: =I72-Q72 -> 0
B73: 10 | C73: Fundación Grupo Generador 400kVA SS.AA + Pretil de Contención
B74: 10.1 | C74: Suministro e instalación de hormigón G-15 con aditivo imp, igol denso, pintura, junta poliuretano | F74: m3 | G74: ='03.- Cubicaciones'!C63 -> 4.4486 | H74: ='10.1'!$G$4 -> 222362.55 | I74: =IF(G74="","",G74*H74) -> 989202.06 | M74: ='10.1'!$M$4 -> 697660.59 | N74: ='10.1'!$N$4 -> 221943.95 | O74: ='10.1'!$O$4 -> 0 | P74: ='10.1'!$P$4 -> 69597.52 | Q74: =SUM(M74:P74) -> 989202.06 | S74: =I74-Q74 -> 0
B75: 10.2 | C75: Suministro e instalación emplantillado hormigón G5 | F75: m3 | G75: ='03.- Cubicaciones'!C64 -> 1.11215 | H75: ='10.2'!$G$4 -> 120719.81 | I75: =IF(G75="","",G75*H75) -> 134258.53 | M75: ='10.2'!$M$4 -> 121429.26 | N75: ='10.2'!$N$4 -> 10691.057 | O75: ='10.2'!$O$4 -> 0 | P75: ='10.2'!$P$4 -> 2138.2118 | Q75: =SUM(M75:P75) -> 134258.53 | S75: =I75-Q75 -> 0
B76: 10.3 | C76: Suministro e Instalación relleno estructural compactado al 95% DMSC | F76: m3 | G76: ='03.- Cubicaciones'!C65 -> 16 | H76: ='10.3'!$G$4 -> 55574.597 | I76: =IF(G76="","",G76*H76) -> 889193.55 | M76: ='10.3'!$M$4 -> 416000 | N76: ='10.3'!$N$4 -> 23071.104 | O76: ='10.3'!$O$4 -> 0 | P76: ='10.3'!$P$4 -> 450122.45 | Q76: =SUM(M76:P76) -> 889193.55 | S76: =I76-Q76 -> 0
B77: 10.4 | C77: Excavación maquinaría local y traslado a botadero, hasta 20 Km | F77: m3 | G77: ='03.- Cubicaciones'!C66 -> 7.78505 | H77: ='10.4'!$G$4 -> 25500 | I77: =IF(G77="","",G77*H77) -> 198518.77 | M77: ='10.4'!$M$4 -> 0 | N77: ='10.4'!$N$4 -> 0 | O77: ='10.4'!$O$4 -> 0 | P77: ='10.4'!$P$4 -> 198518.78 | Q77: =SUM(M77:P77) -> 198518.78 | S77: =I77-Q77 -> 0
B78: 10.5 | C78: Suministro y construcción moldajes de madera o metálicos | F78: m2 | G78: ='03.- Cubicaciones'!C67 -> 4.196 | H78: ='10.5'!$G$4 -> 16475.796 | I78: =IF(G78="","",G78*H78) -> 69132.44 | M78: ='10.5'!$M$4 -> 49663 | N78: ='10.5'!$N$4 -> 16224.535 | O78: ='10.5'!$O$4 -> 0 | P78: ='10.5'!$P$4 -> 3244.9053 | Q78: =SUM(M78:P78) -> 69132.44 | S78: =I78-Q78 -> 0
B79: 10.6 | C79: Suministro e instalación de pernos de anclaje químico | F79: un | G79: ='03.- Cubicaciones'!C68 -> 10 | H79: ='10.6'!$G$4 -> 11342.214 | I79: =IF(G79="","",G79*H79) -> 113422.14 | M79: ='10.6'!$M$4 -> 98922.14 | N79: ='10.6'!$N$4 -> 12083.33 | O79: ='10.6'!$O$4 -> 0 | P79: ='10.6'!$P$4 -> 2416.67 | Q79: =SUM(M79:P79) -> 113422.14 | S79: =I79-Q79 -> 0
B80: 10.7 | C80: Suministro e instalación rejilla galvanizada nervada | F80: un | G80: ='03.- Cubicaciones'!C69 -> 21 | H80: ='10.7'!$G$4 -> 25620.333 | I80: =IF(G80="","",G80*H80) -> 538026.99 | M80: ='10.7'!$M$4 -> 501690 | N80: ='10.7'!$N$4 -> 30280.824 | O80: ='10.7'!$O$4 -> 0 | P80: ='10.7'!$P$4 -> 6056.169 | Q80: =SUM(M80:P80) -> 538026.99 | S80: =I80-Q80 -> 0
B81: 10.8 | C81: Suministro e instalación armadura A630-420H, diámetro 12mm | F81: kg | G81: ='03.- Cubicaciones'!C70 -> 149.916 | H81: ='10.8'!$G$4 -> 1644.333 | I81: =IF(G81="","",G81*H81) -> 246511.83 | M81: ='10.8'!$M$4 -> 156562.23 | N81: ='10.8'!$N$4 -> 0 | O81: ='10.8'!$O$4 -> 89949.6 | P81: ='10.8'!$P$4 -> 0 | Q81: =SUM(M81:P81) -> 246511.83 | S81: =I81-Q81 -> 0
B82: 11 | C82: Cámaras Separadora Agua - Hidrocarburos
B83: 11.1 | C83: Suministro e Instalación Cámara separadora de hidrocarburos de 230 litros Infraplast | F83: un | G83: ='03.- Cubicaciones'!C72 -> 1 | H83: ='11.1'!$G$4 -> 2168971.7 | I83: =IF(G83="","",G83*H83) -> 2168971.7 | M83: ='11.1'!$M$4 -> 1754158.6 | N83: ='11.1'!$N$4 -> 310300 | O83: ='11.1'!$O$4 -> 27453.102 | P83: ='11.1'!$P$4 -> 77060 | Q83: =SUM(M83:P83) -> 2168971.7 | S83: =I83-Q83 -> 0
B84: 11.2 | C84: Suministro e instalación ducto PVC hidra Ø=110 mm flexodren | F84: m | G84: ='03.- Cubicaciones'!C73 -> 3 | H84: ='11.2'!$G$4 -> 20083.494 | I84: =IF(G84="","",G84*H84) -> 60250.482 | M84: ='11.2'!$M$4 -> 9250.482 | N84: ='11.2'!$N$4 -> 0 | O84: ='11.2'!$O$4 -> 51000 | P84: ='11.2'!$P$4 -> 0 | Q84: =SUM(M84:P84) -> 60250.482 | S84: =I84-Q84 -> 0
B85: 11.3 | C85: Suministro e instalación arena compactada | F85: m3 | G85: ='03.- Cubicaciones'!C74 -> 1.8 | H85: ='11.3'!$G$4 -> 34686.583 | I85: =IF(G85="","",G85*H85) -> 62435.849 | M85: ='11.3'!$M$4 -> 56160 | N85: ='11.3'!$N$4 -> 2595.4992 | O85: ='11.3'!$O$4 -> 0 | P85: ='11.3'!$P$4 -> 3680.3502 | Q85: =SUM(M85:P85) -> 62435.849 | S85: =I85-Q85 -> 0
B86: 11.4 | C86: Excavación, carguío sobre camión y traslado a botadero | F86: m3 | G86: ='03.- Cubicaciones'!C75 -> 3.2 | H86: ='11.4'!$G$4 -> 25500 | I86: =IF(G86="","",G86*H86) -> 81600 | M86: ='11.4'!$M$4 -> 0 | N86: ='11.4'!$N$4 -> 0 | O86: ='11.4'!$O$4 -> 0 | P86: ='11.4'!$P$4 -> 81600 | Q86: =SUM(M86:P86) -> 81600 | S86: =I86-Q86 -> 0
B87: 12 | C87: Cámara ciega para almacenar eventuales derrames, en sector exterior sala de máquinas
B88: 12.1 | C88: Suministro e Instalación Hormigón G15, con aditivo impermeabilizante, igol denso. | F88: m3 | G88: ='03.- Cubicaciones'!C77 -> 1.2 | H88: ='12.1'!$G$4 -> 222362.55 | I88: =IF(G88="","",G88*H88) -> 266835.06 | M88: ='12.1'!$M$4 -> 188192.4 | N88: ='12.1'!$N$4 -> 59868.889 | O88: ='12.1'!$O$4 -> 0 | P88: ='12.1'!$P$4 -> 18773.777 | Q88: =SUM(M88:P88) -> 266835.06 | S88: =I88-Q88 -> 0
B89: 12.2 | C89: Suministro e instalación emplantillado hormigón G5 | F89: m3 | G89: ='03.- Cubicaciones'!C78 -> 0.1 | H89: ='12.2'!$G$4 -> 120719.81 | I89: =IF(G89="","",G89*H89) -> 12071.981 | M89: ='12.2'!$M$4 -> 10918.425 | N89: ='12.2'!$N$4 -> 961.2963 | O89: ='12.2'!$O$4 -> 0 | P89: ='12.2'!$P$4 -> 192.2593 | Q89: =SUM(M89:P89) -> 12071.981 | S89: =I89-Q89 -> 0
B90: 12.3 | C90: Excavación maquinaría local y traslado a botadero, hasta 20 Km | F90: m3 | G90: ='03.- Cubicaciones'!C79 -> 1.3 | H90: ='12.3'!$G$4 -> 25500 | I90: =IF(G90="","",G90*H90) -> 33150 | M90: ='12.3'!$M$4 -> 0 | N90: ='12.3'!$N$4 -> 0 | O90: ='12.3'!$O$4 -> 0 | P90: ='12.3'!$P$4 -> 33150 | Q90: =SUM(M90:P90) -> 33150 | S90: =I90-Q90 -> 0
B91: 12.4 | C91: Suministro y construcción moldajes de madera o metálicos | F91: m2 | G91: ='03.- Cubicaciones'!C80 -> 17.3 | H91: ='12.4'!$G$4 -> 16475.796 | I91: =IF(G91="","",G91*H91) -> 285031.27 | M91: ='12.4'!$M$4 -> 204759.27 | N91: ='12.4'!$N$4 -> 66893.339 | O91: ='12.4'!$O$4 -> 0 | P91: ='12.4'!$P$4 -> 13378.661 | Q91: =SUM(M91:P91) -> 285031.27 | S91: =I91-Q91 -> 0
B92: 12.5 | C92: Suministro e instalación enfierradura malla acma C-188 | F92: kg | G92: ='03.- Cubicaciones'!C81 -> 35 | H92: ='12.5'!$G$4 -> 2586.773 | I92: =IF(G92="","",G92*H92) -> 90537.055 | M92: ='12.5'!$M$4 -> 50162.595 | N92: ='12.5'!$N$4 -> 33645.395 | O92: ='12.5'!$O$4 -> 0 | P92: ='12.5'!$P$4 -> 6729.065 | Q92: =SUM(M92:P92) -> 90537.055 | S92: =I92-Q92 -> 0
B93: 12.6 | C93: Ducto PVC 110mm, considera salida desde pretiles de transformador a cámara separadora | F93: m | G93: ='03.- Cubicaciones'!C82 -> 32 | H93: ='12.6'!$G$4 -> 19571.289 | I93: =IF(G93="","",G93*H93) -> 626281.25 | M93: ='12.6'!$M$4 -> 82281.248 | N93: ='12.6'!$N$4 -> 0 | O93: ='12.6'!$O$4 -> 544000 | P93: ='12.6'!$P$4 -> 0 | Q93: =SUM(M93:P93) -> 626281.25 | S93: =I93-Q93 -> 0
B94: 13 | C94: Zanjas de infiltración con cubo dren para sistema de contención de derrames
B95: 13.1 | C95: Suministro y colocación arena limpia compactada | F95: m3 | G95: ='03.- Cubicaciones'!C84 -> 14.4 | H95: ='13.1'!$G$4 -> 34686.583 | I95: =IF(G95="","",G95*H95) -> 499486.8 | M95: ='13.1'!$M$4 -> 449280 | N95: ='13.1'!$N$4 -> 20763.994 | O95: ='13.1'!$O$4 -> 0 | P95: ='13.1'!$P$4 -> 29442.802 | Q95: =SUM(M95:P95) -> 499486.8 | S95: =I95-Q95 -> 0
B96: 13.2 | C96: Suministro y colocación gravilla (bajo tamiz 1") | F96: m3 | G96: ='03.- Cubicaciones'!C85 -> 2.5 | H96: ='13.2'!$G$4 -> 37286.583 | I96: =IF(G96="","",G96*H96) -> 93216.458 | M96: ='13.2'!$M$4 -> 84500 | N96: ='13.2'!$N$4 -> 3604.86 | O96: ='13.2'!$O$4 -> 0 | P96: ='13.2'!$P$4 -> 5111.5975 | Q96: =SUM(M96:P96) -> 93216.458 | S96: =I96-Q96 -> 0
B97: 13.3 | C97: Suministro e instalación Cubos dren 26 t/m2 | F97: un | G97: ='03.- Cubicaciones'!C86 -> 48 | H97: ='13.3'!$G$4 -> 18599.722 | I97: =IF(G97="","",G97*H97) -> 892786.66 | M97: ='13.3'!$M$4 -> 546720 | N97: ='13.3'!$N$4 -> 346066.66 | O97: ='13.3'!$O$4 -> 0 | P97: ='13.3'!$P$4 -> 0 | Q97: =SUM(M97:P97) -> 892786.66 | S97: =I97-Q97 -> 0
B98: 13.4 | C98: Excavación máquinaria local, traslado a botadero hasta 20km (geométrica, sin esponajamiento) | F98: m3 | G98: ='03.- Cubicaciones'!C87 -> 15 | H98: ='13.4'!$G$4 -> 25500 | I98: =IF(G98="","",G98*H98) -> 382500 | M98: ='13.4'!$M$4 -> 0 | N98: ='13.4'!$N$4 -> 0 | O98: ='13.4'!$O$4 -> 0 | P98: ='13.4'!$P$4 -> 382500 | Q98: =SUM(M98:P98) -> 382500 | S98: =I98-Q98 -> 0
B99: 13.5 | C99: Suministro e instalación PVC 110mm | F99: m | G99: ='03.- Cubicaciones'!C88 -> 36 | H99: ='13.5'!$G$4 -> 19571.289 | I99: =IF(G99="","",G99*H99) -> 704566.4 | M99: ='13.5'!$M$4 -> 92566.404 | N99: ='13.5'!$N$4 -> 0 | O99: ='13.5'!$O$4 -> 612000 | P99: ='13.5'!$P$4 -> 0 | Q99: =SUM(M99:P99) -> 704566.4 | S99: =I99-Q99 -> 0
B100: 13.6 | C100: Suministro e instalación códo de PVC 110mm | F100: un | G100: ='03.- Cubicaciones'!C89 -> 5 | H100: ='13.6'!$G$4 -> 2698.506 | I100: =IF(G100="","",G100*H100) -> 13492.53 | M100: ='13.6'!$M$4 -> 1686.975 | N100: ='13.6'!$N$4 -> 0 | O100: ='13.6'!$O$4 -> 11805.555 | P100: ='13.6'!$P$4 -> 0 | Q100: =SUM(M100:P100) -> 13492.53 | S100: =I100-Q100 -> 0
B101: 13.7 | C101: Suministro e instalación de Geotextil | F101: m2 | G101: ='03.- Cubicaciones'!C90 -> 29 | H101: ='13.7'!$G$4 -> 1623.533 | I101: =IF(G101="","",G101*H101) -> 47082.457 | M101: ='13.7'!$M$4 -> 38280 | N101: ='13.7'!$N$4 -> 7335.376 | O101: ='13.7'!$O$4 -> 0 | P101: ='13.7'!$P$4 -> 1467.081 | Q101: =SUM(M101:P101) -> 47082.457 | S101: =I101-Q101 -> 0
B102: 13.8 | C102: Suministro e instalación PVC110 mm ranurado | F102: m | G102: ='03.- Cubicaciones'!C91 -> 6 | H102: ='13.8'!$G$4 -> 20083.494 | I102: =IF(G102="","",G102*H102) -> 120500.96 | M102: ='13.8'!$M$4 -> 18500.964 | N102: ='13.8'!$N$4 -> 0 | O102: ='13.8'!$O$4 -> 102000 | P102: ='13.8'!$P$4 -> 0 | Q102: =SUM(M102:P102) -> 120500.96 | S102: =I102-Q102 -> 0
B103: 14 | C103: Fundación Sala Eléctrica
...

Sheet 02.- Gastos Generales
H2: Fecha: | I2: ='01.- Presupuesto'!I2 -> 45847
H3: Revisión | I3: 0
B4: DETALLE DE GASTOS GENERALES
B5: ='01.- Presupuesto'!B5 -> OBRAS CIVILES CENTRAL LOICA
C7: TIPO | D7: Industrial
C8: CLIENTE | D8: Potencia Sur SpA
C9: DIRECCIÓN | D9: Avenida Providencia 329, Piso 6
C10: COMUNA | D10: Providencia, RM
B12: ITEM | C12: DESCRIPCION | F12: UNIDAD | G12: CANTIDAD | H12: P. UNITARIO | I12: P. TOTAL
C14: Profesionales | I14: =SUM(I15:I22) -> 51620000
B15: 1.1 | C15: Geente de Proyecto | F15: mes | G15: 3 | H15: =(6500000*1.45)/3 -> 3141666.7 | I15: =IF(G15="","",G15*H15) -> 9425000
B16: 1.2 | C16: Administrador de Obra | F16: mes | G16: 3 | H16: =3000000*1.45 -> 4350000 | I16: =IF(G16="","",G16*H16) -> 13050000
B17: 1.3 | C17: Profesional de Terreno | F17: mes | G17: 3 | H17: =2000000*1.45 -> 2900000 | I17: =IF(G17="","",G17*H17) -> 8700000
B18: 1.4 | C18: Profesional Oficina Técnica | F18: mes | G18: 3 | H18: =1500000*1.45 -> 2175000 | I18: =IF(G18="","",G18*H18) -> 6525000
B19: 1.5 | C19: Profesional Calidad | F19: mes | G19: 3 | H19: =1200000*1.45 -> 1740000 | I19: =IF(G19="","",G19*H19) -> 5220000
B20: 1.6 | C20: Asistente OT | F20: mes | G20: 3 | H20: =800000*1.45 -> 1160000 | I20: =IF(G20="","",G20*H20) -> 3480000
B21: 1.7 | C21: Profesional Prevención Riesgo | F21: mes | G21: 3 | H21: =1200000*1.45 -> 1740000 | I21: =IF(G21="","",G21*H21) -> 5220000
I22: =IF(G22="","",G22*H22)
C23: Administración y Bodega | I23: =SUM(I24:I33) -> 45892500
B24: 2.1 | C24: Jefe Administrativo | F24: mes | G24: 3 | H24: =1200000*1.45 -> 1740000 | I24: =IF(G24="","",G24*H24) -> 5220000
B25: 2.2 | C25: Jefe Bodega | F25: mes | G25: 3 | H25: =1200000*1.45 -> 1740000 | I25: =IF(G25="","",G25*H25) -> 5220000
B26: 2.3 | C26: Pañolero | F26: mes | G26: 3 | H26: =700000*1.45 -> 1015000 | I26: =IF(G26="","",G26*H26) -> 3045000
B27: 2.4 | C27: Jefe de Obra | F27: mes | G27: 3 | H27: =1600000*1.45 -> 2320000 | I27: =IF(G27="","",G27*H27) -> 6960000
B28: 2.5 | C28: Capataz OOGG | F28: mes | G28: 3 | H28: =1200000*1.45 -> 1740000 | I28: =IF(G28="","",G28*H28) -> 5220000
B29: 2.6 | C29: Capataz Patio | F29: mes | G29: 3 | H29: =1200000*1.45 -> 1740000 | I29: =IF(G29="","",G29*H29) -> 5220000
B30: 2.7 | C30: Trazador | F30: mes | G30: 3 | H30: =1000000*1.45 -> 1450000 | I30: =IF(G30="","",G30*H30) -> 4350000
B31: 2.8 | C31: Ayudante Trazador | F31: mes | G31: 3 | H31: =700000*1.45 -> 1015000 | I31: =IF(G31="","",G31*H31) -> 3045000
B32: 2.9 | C32: Porteria | F32: mes | G32: 3 | H32: =(700000*1.45)*2.5 -> 2537500 | I32: =IF(G32="","",G32*H32) -> 7612500
C34: Instalación de Faenas | I34: =SUM(I35:I46) -> 26700000
B35: 3.1 | C35: Contenedor Oficinas | F35: mes | G35: 3 | H35: =300000*3 -> 900000 | I35: =IF(G35="","",G35*H35) -> 2700000
B36: 3.2 | C36: Contenedor Baños | F36: mes | G36: 3 | H36: =350000*2 -> 700000 | I36: =IF(G36="","",G36*H36) -> 2100000
B37: 3.3 | C37: Contenedor Bodegas | F37: mes | G37: 3 | H37: =200000*2 -> 400000 | I37: =IF(G37="","",G37*H37) -> 1200000
B38: 3.4 | C38: Contenedor Casino | F38: mes | G38: 3 | H38: =200000*2 -> 400000 | I38: =IF(G38="","",G38*H38) -> 1200000
B39: 3.5 | C39: Traslado Contenedor | F39: un | G39: =9*2 -> 18 | H39: 150000 | I39: =IF(G39="","",G39*H39) -> 2700000
B40: 3.6 | C40: Señalización | F40: gl | G40: 1 | H40: 3000000 | I40: =IF(G40="","",G40*H40) -> 3000000
B41: 3.7 | C41: Instalación Radiotransmición | F41: gl | G41: 1 | H41: 1200000 | I41: =IF(G41="","",G41*H41) -> 1200000
B42: 3.8 | C42: Instalación Comunicaciones | F42: gl | G42: 1 | H42: 1200000 | I42: =IF(G42="","",G42*H42) -> 1200000
B43: 3.9 | C43: Elementos de Protección Personal y Comdiciones Seguridad | F43: mes | G43: 3 | H43: 2000000 | I43: =IF(G43="","",G43*H43) -> 6000000
B44: 3.10 | C44: Consumos luz, agua, telef, etc. | F44: mes | G44: 3 | H44: =200000*4 -> 800000 | I44: =IF(G44="","",G44*H44) -> 2400000
B45: 3.11 | C45: Alhajamiento Oficinas | F45: gl | G45: 1 | H45: 3000000 | I45: =IF(G45="","",G45*H45) -> 3000000
C47: Otros Gastos | I47: =SUM(I48:I54) -> 12600000
B48: 4.1 | C48: Arriendo Instrumentos | F48: mes | G48: 3 | H48: 500000 | I48: =IF(G48="","",G48*H48) -> 1500000
B49: 4.2 | C49: Movilización Profesional | F49: mes | G49: 3 | H49: 500000 | I49: =IF(G49="","",G49*H49) -> 1500000
B50: 4.3 | C50: Viaticos | F50: mes | G50: 3 | H50: 1000000 | I50: =IF(G50="","",G50*H50) -> 3000000
B51: 4.4 | C51: Fletes Vehiculo | F51: mes | G51: 3 | H51: 1000000 | I51: =IF(G51="","",G51*H51) -> 3000000
B52: 4.5 | C52: Consumo Combustible | F52: mes | G52: 3 | H52: 500000 | I52: =IF(G52="","",G52*H52) -> 1500000
B53: 4.6 | C53: Planos | F53: mes | G53: 3 | H53: 200000 | I53: =IF(G53="","",G53*H53) -> 600000
B54: 4.7 | C54: Caja Chica | F54: mes | G54: 3 | H54: 500000 | I54: =IF(G54="","",G54*H54) -> 1500000
B55: 4.8 | C55: Costo Financiero (Anticipo, Fiel Cumplimiento, TRC, etc.) | F55: gl | G55: 1 | H55: =750000000*0.01 -> 7500000 | I55: =IF(G55="","",G55*H55) -> 7500000
I58: =IF(G58="","",G58*H58)
F59: GASTOS GENERALES | I59: =I14+I23+I34+I47 -> 136812500 | M59: =I59/39300/3 -> 1160.4114 | N59: UF/Mes

Sheet 03.- Cubicaciones
C1: CANTIDAD | D1: UNIDAD
B3: Movimiento de Tierra
A4: 1 | B4: Desbroce
A5: 1.1 | B5: Desbroce | C5: 1 | D5: gl | F5: 2442 m2
A6: 2 | B6: Demoliciones y Retiros de Escombros
A7: 2.1 | B7: Excavación, carguió sobre camión y traslado a botadero, e = variable | C7: 890 | D7: m3
A8: 2.2 | B8: Retiro y reposición zanja para ducto malla de puesta a tierra | C8: 400 | D8: m3
A9: 2.3 | B9: Formación y compactación de plataforma e= variable. Relleno e= 20cm | C9: 754 | D9: m3
A10: 2.4 | B10: Tratamiento de taludes de corte con hidrosiembra según manual de carreteras | C10: 1 | D10: gl
A11: 3 | B11: Movimiento de Tierra Camino Acceso
A12: 3.1 | B12: Sobrexcavación para caminos interiores, carguio sobre camión y traslado | C12: 760 | D12: m3
A13: 3.2 | B13: Suministro y colocación Base Granular CBR >100% e=26cm | C13: =180*5*0.26 -> 234 | D13: m3
A14: 3.3 | B14: Suministro y colocación Sub-Base granular CBR > 50% e=20cm | C14: =180*5*0.2 -> 180 | D14: m3
A15: 3.4 | B15: Suministro y colocación de bolones para estabilización de suelos e=30cm | C15: =180*5*0.3 -> 270 | D15: m3
A16: 3.5 | B16: Suministro e Instalación de Geotextil bajo la Sub-Base | C16: =180*5 -> 900 | D16: m2
A17: 4 | B17: Sistema Drenajes
A18: 4.1 | B18: Suministro de materiales y construcción de zanja de infiltración, incluye cubo dren | C18: 6.3 | D18: m
A19: 4.2 | B19: Suministro de materiales y construcción cámaras de filtración y decantación | C19: 1 | D19: un
A20: 5 | B20: Cierre Perimetral Exterior
A21: 5.1 | B21: Suministro e instalación cierre perimetral tipo Bulldog | C21: 50 | D21: m
A22: 5.2 | B22: Suministro e instalación cierre perimetral tipo Acmafor | C22: 280 | D22: m | F22: =2.5*110+1+2.1+1.8 -> 279.9
A23: 5.3 | B23: Suministro e instalación portón metálico vehicular 5m | C23: 1 | D23: un
A24: 5.4 | B24: Suministro e instalación portón metálico peatonal 1m | C24: 1 | D24: un
B26: Fundación Equipos
A27: 6 | B27: Fundación Grupo Generador a gas GLP, 05 unidades.
A28: 6.1 | B28: Suministro e Instalación Hormigón G25(10)20-8 | C28: =F28*5 -> 36.75 | D28: m3 | F28: =7*3*0.35 -> 7.35 | I28: F1 | J28: 1 | K28: =J28*M28 -> 392.757 | M28: =SUM(M30:M32) -> 392.757
A29: 6.2 | B29: Suministro e instalación emplantillado hormigón G5 | C29: =F29*5 -> 5.25 | D29: m3 | F29: =7*3*0.05 -> 1.05 | I29: Cant | J29: diámetro | K29: L | L29: Kg/ml | M29: Kg
A30: 6.3 | B30: Suministro e Instalación relleno estructural compactado al 95% DMSC | C30: =F30*5 -> 199.5 | D30: m3 | F30: =7*3*1.9 -> 39.9 | I30: 30 | J30: 12 | K30: 7.15 | L30: 0.89 | M30: =I30*K30*L30 -> 190.905
A31: 6.4 | B31: Excavación maquinaría local y traslado a botadero, hasta 20 Km | C31: =F31*5 -> 246.75 | D31: m3 | F31: =7*3*(1.9+0.1+0.35) -> 49.35 | I31: =36*2 -> 72 | J31: 12 | K31: 3.15 | L31: 0.89 | M31: =I31*K31*L31 -> 201.852
A32: 6.5 | B32: Suministro y construcción moldajes de madera o metálicos | C32: =F32*5 -> 35 | D32: m2 | F32: =0.35*(7*2+3*2) -> 7
A33: 6.6 | B33: Suministro e instalación armadura A630-420H, diámetro 12mm | C33: =F33*5 -> 1963.785 | D33: kg | F33: =K28 -> 392.757
A34: 6.7 | B34: Suministro e instalación de pernos de anclaje químico | C34: 280 | D34: un
A35: 7 | B35: Fundación Transformador 2,0 MVA, 05 unidades
A36: 7.1 | B36: Suministro e Instalación Hormigón G20(10)20-8 | C36: =F36*5 -> 20 | D36: m3 | F36: 4
A37: 7.2 | B37: Suministro e instalación emplantillado hormigón G5 | C37: =F37*5 -> 2.5 | D37: m3 | F37: 0.5
A38: 7.3 | B38: Suministro e Instalación relleno estructural compactado al 95% DMSC | C38: =F38*5 -> 24.3775 | D38: m3 | F38: =3.1*3.1*0.7-2.3*2.3*0.35 -> 4.8755
A39: 7.4 | B39: Excavación maquinaría local y traslado a botadero, hasta 20 Km | C39: =F39*5 -> 48.05 | D39: m3 | F39: =3.1*3.1*(0.35+0.65) -> 9.61
A40: 7.5 | B40: Suministro y construcción moldajes de madera o metálicos | C40: =F40*5 -> 95 | D40: m2 | F40: 19
A41: 7.6 | B41: Suministro e instalación armadura A630-420H, diámetro 12mm | C41: =F41*5 -> 600 | D41: kg | F41: 120
A42: 7.7 | B42: Suministro e instalación de pernos de anclaje químico | C42: =F42*5 -> 20 | D42: un | F42: 4
A43: 7.8 | B43: Suministro e instalación enfierradura malla acma C-188 | C43: =F43*5 -> 180 | D43: kg | F43: 36
A44: 7.9 | B44: Suministro e instalación parrilla de piso Arriogoni ARS-3 | C44: =F44*5 -> 19 | D44: m2 | F44: 3.8
A45: 7.10 | B45: Suministro e instalación ángulo acero L30x3 | C45: =F45*5 -> 60 | D45: m | F45: 12
A46: 7.11 | B46: Suministro e instalación ángulo acero L50x5 | C46: =F46*5 -> 50 | D46: m | F46: 10
A47: 8 | B47: Fundaciones Radiadores
A48: 8.1 | B48: Suministro e Instalación Hormigón G25(10)20-8 | C48: =F48 -> 5.916 | D48: m3 | F48: =8*(0.85*0.85*0.6)+4*(0.85*1.2*0.6) -> 5.916
A49: 8.2 | B49: Suministro e instalación emplantillado hormigón G5 | C49: =F49 -> 0.493 | D49: m3 | F49: =8*(0.85*0.85*0.05)+4*(0.85*1.2*0.05) -> 0.493
A50: 8.3 | B50: Suministro e Instalación relleno estructural compactado al 95% DMSC | C50: =F50 -> 7.6415 | D50: m3 | F50: =F51/2 -> 7.6415
A51: 8.4 | B51: Excavación maquinaría local y traslado a botadero, hasta 20 Km | C51: =F51 -> 15.283 | D51: m3 | F51: =8*(0.85*0.85*1.55)+4*(0.85*1.2*1.55) -> 15.283
A52: 8.5 | B52: Suministro y construcción moldajes de madera o metálicos | C52: =F52 -> 26.16 | D52: m2 | F52: =8*(0.6*0.85*4)+4*(0.6*1.2*2+0.6*0.85*2) -> 26.16
A53: 8.6 | B53: Suministro e instalación armadura A630-420H, diámetro 12mm | C53: =F53 -> 392 | D53: kg | F53: =29*8+40*4 -> 392
A54: 8.7 | B54: Suministro e instalación de pernos de anclaje químico | C54: =F54 -> 64 | D54: un | F54: =4*16 -> 64
A55: 9 | B55: Cámara Separadora, ubicación aledaño a PMT
A56: 9.1 | B56: Suministro e Instalación Hormigón G15, con aditivo impermeabilizante, igol denso. | C56: =F56 -> 2.112 | D56: m3 | F56: =0.1*(1.9*1.9+1.7*(4*1.9+1.4+1.3)) -> 2.112
A57: 9.2 | B57: Suministro e instalación emplantillado hormigón G5 | C57: =F57 -> 0.1805 | D57: m3 | F57: =1.9*1.9*0.05 -> 0.1805
A58: 9.3 | B58: Suministro e instalación enfierradura malla acma C-188 | C58: 66 | D58: kg
A59: 9.4 | B59: Excavación maquinaría local y traslado a botadero, hasta 20 Km | C59: =F59 -> 6.137 | D59: m3 | F59: =1.9*1.9*1.7 -> 6.137
A60: 9.5 | B60: Suministro y construcción moldajes de madera o metálicos | C60: =F60 -> 21.12 | D60: m2 | F60: =(1.9*1.9+1.7*(4*1.9+1.4+1.3)) -> 21.12
A61: 9.6 | B61: Tapa en losa de hormigón G15, incluye armadura acma 188, aditivo imperm. | C61: 1 | D61: un | F61: 1
A62: 10 | B62: Fundación Grupo Generador 400kVA SS.AA + Pretil de Contención
A63: 10.1 | B63: Suministro e instalación de hormigón G-15 con aditivo imp, igol denso, pintura, junta poliuretano | C63: =F63 -> 4.4486 | D63: m3 | F63: =0.2*2.95*7.54 -> 4.4486 | J63: 1 | K63: =J63*M63 -> 149.916 | M63: =SUM(M65:M67) -> 149.916
A64: 10.2 | B64: Suministro e instalación emplantillado hormigón G5 | C64: =F64 -> 1.11215 | D64: m3 | F64: =0.05*2.95*7.54 -> 1.11215 | I64: Cant | J64: diámetro | K64: L | L64: Kg/ml | M64: Kg
A65: 10.3 | B65: Suministro e Instalación relleno estructural compactado al 95% DMSC | C65: 16 | D65: m3 | F65: =0.1*2.95*7.54 -> 2.2243 | I65: =ROUNDUP(2.95/0.2,0)+1 -> 16 | J65: 10 | K65: 7.8 | L65: 0.62 | M65: =I65*K65*L65 -> 77.376
A66: 10.4 | B66: Excavación maquinaría local y traslado a botadero, hasta 20 Km | C66: =F66 -> 7.78505 | D66: m3 | F66: =0.35*2.95*7.54 -> 7.78505 | I66: =ROUNDUP(7.54/0.2,0)+1 -> 39 | J66: 10 | K66: 3 | L66: 0.62 | M66: =I66*K66*L66 -> 72.54
A67: 10.5 | B67: Suministro y construcción moldajes de madera o metálicos | C67: =F67 -> 4.196 | D67: m2 | F67: =0.2*(2.95*2+7.54*2) -> 4.196
A68: 10.6 | B68: Suministro e instalación de pernos de anclaje químico | C68: 10 | D68: un | K68: En plano multiplican la cantidad mayor por el largo mayor, lo que esta incorrecto
A69: 10.7 | B69: Suministro e instalación rejilla galvanizada nervada | C69: 21 | D69: un
A70: 10.8 | B70: Suministro e instalación armadura A630-420H, diámetro 12mm | C70: =M63 -> 149.916 | D70: kg
A71: 11 | B71: Cámaras Separadora Agua - Hidrocarburos
A72: 11.1 | B72: Suministro e Instalación Cámara separadora de hidrocarburos de 230 litros Infraplast | C72: 1 | D72: un
A73: 11.2 | B73: Suministro e instalación ducto PVC hidra Ø=110 mm flexodren | C73: 3 | D73: m
A74: 11.3 | B74: Suministro e instalación arena compactada | C74: 1.8 | D74: m3
A75: 11.4 | B75: Excavación, carguío sobre camión y traslado a botadero | C75: 3.2 | D75: m3
A76: 12 | B76: Cámara ciega para almacenar eventuales derrames, en sector exterior sala de máquinas
A77: 12.1 | B77: Suministro e Instalación Hormigón G15, con aditivo impermeabilizante, igol denso. | C77: 1.2 | D77: m3
A78: 12.2 | B78: Suministro e instalación emplantillado hormigón G5 | C78: 0.1 | D78: m3
A79: 12.3 | B79: Excavación maquinaría local y traslado a botadero, hasta 20 Km | C79: 1.3 | D79: m3
A80: 12.4 | B80: Suministro y construcción moldajes de madera o metálicos | C80: 17.3 | D80: m2
A81: 12.5 | B81: Suministro e instalación enfierradura malla acma C-188 | C81: 35 | D81: kg
A82: 12.6 | B82: Ducto PVC 110mm, considera salida desde pretiles de transformador a cámara separadora | C82: 32 | D82: m
A83: 13 | B83: Zanjas de infiltración con cubo dren para sistema de contención de derrames
A84: 13.1 | B84: Suministro y colocación arena limpia compactada | C84: 14.4 | D84: m3
A85: 13.2 | B85: Suministro y colocación gravilla (bajo tamiz 1") | C85: 2.5 | D85: m3
A86: 13.3 | B86: Suministro e instalación Cubos dren 26 t/m2 | C86: 48 | D86: un
A87: 13.4 | B87: Excavación máquinaria local, traslado a botadero hasta 20km (geométrica, sin esponajamiento) | C87: 15 | D87: m3
A88: 13.5 | B88: Suministro e instalación PVC 110mm | C88: 36 | D88: m
A89: 13.6 | B89: Suministro e instalación códo de PVC 110mm | C89: 5 | D89: un
A90: 13.7 | B90: Suministro e instalación de Geotextil | C90: 29 | D90: m2
A91: 13.8 | B91: Suministro e instalación PVC110 mm ranurado | C91: 6 | D91: m
A92: 14 | B92: Fundación Sala Eléctrica
A93: 14.1 | B93: Suministro e Instalación Hormigón G20(10)20-8 | C93: 2.94 | D93: m3 | F93: =10*(0.6*0.7*0.7) -> 2.94
A94: 14.2 | B94: Suministro e instalación emplantillado hormigón G5 | C94: 0.25 | D94: m3 | F94: =10*(0.05*0.7*0.7) -> 0.245
A95: 14.3 | B95: Suministro e Instalación relleno estructural compactado al 95% DMSC | C95: =F95 -> 7.865 | D95: m3 | F95: =10*((0.65)*1.1*1.1) -> 7.865
A96: 14.4 | B96: Excavación maquinaría local y traslado a botadero, hasta 20 Km | C96: =F96 -> 12.705 | D96: m3 | F96: =10*((0.4+0.65)*1.1*1.1) -> 12.705
A97: 14.5 | B97: Suministro y construcción moldajes de madera o metálicos | C97: 17 | D97: m2 | F97: =10*(0.6*0.7*4) -> 16.8
A98: 14.6 | B98: Suministro e instalación armadura A630-420H, diámetro 12mm | C98: =F98 -> 150 | D98: kg | F98: 150
A99: 14.7 | B99: Suministro e instalación de pernos de anclaje químico | C99: 10 | D99: un | F99: 10
A100: 14.8 | B100: Suministro e Instalación L100x100x6 L=100mm | C100: 10 | D100: un | F100: 10
B102: Estructuras
A103: 15 | B103: Estructura Soporte Transformador 0,5 MVA, 5 unidades.
...

Sheet 04.- CC Cubicaciones
B2: Movimiento de Tierra | D2: GECOT | E2: ITEMIZADO | F2: DELTA
A3: 1 | B3: Desbroce
A4: 1.1 | B4: Desbroce | C4: gl | D4: ='03.- Cubicaciones'!C5 -> 1 | E4: 1 | F4: =E4-D4 -> 0 | G4: =F4/E4 -> 0
A5: 2 | B5: Demoliciones y Retiros de Escombros
A6: 2.1 | B6: Excavación, carguió sobre camión y traslado a botadero, e = variable | C6: m3 | D6: ='03.- Cubicaciones'!C7 -> 890 | E6: =640+250 -> 890 | F6: =E6-D6 -> 0 | G6: =F6/E6 -> 0
A7: 2.2 | B7: Retiro y reposición zanja para ducto malla de puesta a tierra | C7: m3 | D7: ='03.- Cubicaciones'!C8 -> 400 | E7: 400 | F7: =E7-D7 -> 0 | G7: =F7/E7 -> 0
A8: 2.3 | B8: Formación y compactación de plataforma e= variable. Relleno e= 20cm | C8: m3 | D8: ='03.- Cubicaciones'!C9 -> 754 | E8: =(768-870*0.4)*1.2+250 -> 754 | F8: =E8-D8 -> 0 | G8: =F8/E8 -> 0
A9: 2.4 | B9: Tratamiento de taludes de corte con hidrosiembra según manual de carreteras | C9: gl | D9: ='03.- Cubicaciones'!C10 -> 1 | E9: 1 | F9: =E9-D9 -> 0 | G9: =F9/E9 -> 0
A10: 3 | B10: Movimiento de Tierra Camino Acceso
A11: 3.1 | B11: Sobrexcavación para caminos interiores, carguio sobre camión y traslado | C11: m3 | D11: ='03.- Cubicaciones'!C12 -> 760 | E11: =860*0.8*1.1 -> 756.8 | F11: =E11-D11 -> -3.2 | G11: =F11/E11 -> -0.0042283298
A12: 3.2 | B12: Suministro y colocación Base Granular CBR >100% e=26cm | C12: m3 | D12: ='03.- Cubicaciones'!C13 -> 234 | E12: 240 | F12: =E12-D12 -> 6 | G12: =F12/E12 -> 0.025
A13: 3.3 | B13: Suministro y colocación Sub-Base granular CBR > 50% e=20cm | C13: m3 | D13: ='03.- Cubicaciones'!C14 -> 180 | E13: 180 | F13: =E13-D13 -> 0 | G13: =F13/E13 -> 0
A14: 3.4 | B14: Suministro y colocación de bolones para estabilización de suelos e=30cm | C14: m3 | D14: ='03.- Cubicaciones'!C15 -> 270 | E14: 270 | F14: =E14-D14 -> 0 | G14: =F14/E14 -> 0
A15: 3.5 | B15: Suministro e Instalación de Geotextil bajo la Sub-Base | C15: m2 | D15: ='03.- Cubicaciones'!C16 -> 900 | E15: =860*1.2 -> 1032 | F15: =E15-D15 -> 132 | G15: =F15/E15 -> 0.12790698
A16: 4 | B16: Sistema Drenajes
A17: 4.1 | B17: Suministro de materiales y construcción de zanja de infiltración, incluye cubo dren | C17: m | D17: ='03.- Cubicaciones'!C18 -> 6.3 | E17: 6.3 | F17: =E17-D17 -> 0 | G17: =F17/E17 -> 0
A18: 4.2 | B18: Suministro de materiales y construcción cámaras de filtración y decantación | C18: un | D18: ='03.- Cubicaciones'!C19 -> 1 | E18: 1 | F18: =E18-D18 -> 0 | G18: =F18/E18 -> 0
A19: 5 | B19: Cierre Perimetral Exterior
A20: 5.1 | B20: Suministro e instalación cierre perimetral tipo Bulldog | C20: m | D20: ='03.- Cubicaciones'!C21 -> 50 | E20: 50 | F20: =E20-D20 -> 0 | G20: =F20/E20 -> 0
A21: 5.2 | B21: Suministro e instalación cierre perimetral tipo Acmafor | C21: m | D21: ='03.- Cubicaciones'!C22 -> 280 | E21: 362 | F21: =E21-D21 -> 82 | G21: =F21/E21 -> 0.22651934
A22: 5.3 | B22: Suministro e instalación portón metálico vehicular 5m | C22: un | D22: ='03.- Cubicaciones'!C23 -> 1 | E22: 1 | F22: =E22-D22 -> 0 | G22: =F22/E22 -> 0
A23: 5.4 | B23: Suministro e instalación portón metálico peatonal 1m | C23: un | D23: ='03.- Cubicaciones'!C24 -> 1 | E23: 1 | F23: =E23-D23 -> 0 | G23: =F23/E23 -> 0
B25: Fundación Equipos
A26: 6 | B26: Fundación Grupo Generador a gas GLP, 05 unidades.
A27: 6.1 | B27: Suministro e Instalación Hormigón G25(10)20-8 | C27: m3 | D27: ='03.- Cubicaciones'!C28 -> 36.75 | E27: =8*5 -> 40 | F27: =E27-D27 -> 3.25 | G27: =F27/E27 -> 0.08125
A28: 6.2 | B28: Suministro e instalación emplantillado hormigón G5 | C28: m3 | D28: ='03.- Cubicaciones'!C29 -> 5.25 | E28: =2.1*5 -> 10.5 | F28: =E28-D28 -> 5.25 | G28: =F28/E28 -> 0.5
A29: 6.3 | B29: Suministro e Instalación relleno estructural compactado al 95% DMSC | C29: m3 | D29: ='03.- Cubicaciones'!C30 -> 199.5 | E29: =24.15*5 -> 120.75 | F29: =E29-D29 -> -78.75 | G29: =F29/E29 -> -0.65217391
A30: 6.4 | B30: Excavación maquinaría local y traslado a botadero, hasta 20 Km | C30: m3 | D30: ='03.- Cubicaciones'!C31 -> 246.75 | E30: =+(23+2.1+8)*5 -> 165.5 | F30: =E30-D30 -> -81.25 | G30: =F30/E30 -> -0.49093656
A31: 6.5 | B31: Suministro y construcción moldajes de madera o metálicos | C31: m2 | D31: ='03.- Cubicaciones'!C32 -> 35 | E31: =8*5 -> 40 | F31: =E31-D31 -> 5 | G31: =F31/E31 -> 0.125
A32: 6.6 | B32: Suministro e instalación armadura A630-420H, diámetro 12mm | C32: kg | D32: ='03.- Cubicaciones'!C33 -> 1963.785 | E32: =452*5*1.1 -> 2486 | F32: =E32-D32 -> 522.215 | G32: =F32/E32 -> 0.21006235
A33: 6.7 | B33: Suministro e instalación de pernos de anclaje químico | C33: un | D33: ='03.- Cubicaciones'!C34 -> 280 | E33: =56*5 -> 280 | F33: =E33-D33 -> 0 | G33: =F33/E33 -> 0
A34: 7 | B34: Fundación Transformador 2,0 MVA, 05 unidades
A35: 7.1 | B35: Suministro e Instalación Hormigón G20(10)20-8 | C35: m3 | D35: ='03.- Cubicaciones'!C36 -> 20 | E35: =4*5 -> 20 | F35: =E35-D35 -> 0 | G35: =F35/E35 -> 0
A36: 7.2 | B36: Suministro e instalación emplantillado hormigón G5 | C36: m3 | D36: ='03.- Cubicaciones'!C37 -> 2.5 | E36: =0.5*5 -> 2.5 | F36: =E36-D36 -> 0 | G36: =F36/E36 -> 0
A37: 7.3 | B37: Suministro e Instalación relleno estructural compactado al 95% DMSC | C37: m3 | D37: ='03.- Cubicaciones'!C38 -> 24.3775 | E37: =4*2.1 -> 8.4 | F37: =E37-D37 -> -15.9775 | G37: =F37/E37 -> -1.9020833
A38: 7.4 | B38: Excavación maquinaría local y traslado a botadero, hasta 20 Km | C38: m3 | D38: ='03.- Cubicaciones'!C39 -> 48.05 | E38: =4.5*5 -> 22.5 | F38: =E38-D38 -> -25.55 | G38: =F38/E38 -> -1.1355556
A39: 7.5 | B39: Suministro y construcción moldajes de madera o metálicos | C39: m2 | D39: ='03.- Cubicaciones'!C40 -> 95 | E39: =19*5 -> 95 | F39: =E39-D39 -> 0 | G39: =F39/E39 -> 0
A40: 7.6 | B40: Suministro e instalación armadura A630-420H, diámetro 12mm | C40: kg | D40: ='03.- Cubicaciones'!C41 -> 600 | E40: =12*5 -> 60 | F40: =E40-D40 -> -540 | G40: =F40/E40 -> -9
A41: 7.7 | B41: Suministro e instalación de pernos de anclaje químico | C41: un | D41: ='03.- Cubicaciones'!C42 -> 20 | E41: =4*5 -> 20 | F41: =E41-D41 -> 0 | G41: =F41/E41 -> 0
A42: 7.8 | B42: Suministro e instalación enfierradura malla acma C-188 | C42: kg | D42: ='03.- Cubicaciones'!C43 -> 180 | E42: =36*5 -> 180 | F42: =E42-D42 -> 0 | G42: =F42/E42 -> 0
A43: 7.9 | B43: Suministro e instalación parrilla de piso Arriogoni ARS-3 | C43: m2 | D43: ='03.- Cubicaciones'!C44 -> 19 | E43: =3.8*5 -> 19 | F43: =E43-D43 -> 0 | G43: =F43/E43 -> 0
A44: 7.10 | B44: Suministro e instalación ángulo acero L30x3 | C44: m | D44: ='03.- Cubicaciones'!C45 -> 60 | E44: =12*5 -> 60 | F44: =E44-D44 -> 0 | G44: =F44/E44 -> 0
A45: 7.11 | B45: Suministro e instalación ángulo acero L50x5 | C45: m | D45: ='03.- Cubicaciones'!C46 -> 50 | E45: =10*5 -> 50 | F45: =E45-D45 -> 0 | G45: =F45/E45 -> 0
A46: 8 | B46: Fundaciones Radiadores
A47: 8.1 | B47: Suministro e Instalación Hormigón G25(10)20-8 | C47: m3 | D47: ='03.- Cubicaciones'!C48 -> 5.916 | E47: 7.6 | F47: =E47-D47 -> 1.684 | G47: =F47/E47 -> 0.22157895
A48: 8.2 | B48: Suministro e instalación emplantillado hormigón G5 | C48: m3 | D48: ='03.- Cubicaciones'!C49 -> 0.493 | E48: 0.6 | F48: =E48-D48 -> 0.107 | G48: =F48/E48 -> 0.17833333
A49: 8.3 | B49: Suministro e Instalación relleno estructural compactado al 95% DMSC | C49: m3 | D49: ='03.- Cubicaciones'!C50 -> 7.6415 | E49: 7.6 | F49: =E49-D49 -> -0.0415 | G49: =F49/E49 -> -0.0054605263
A50: 8.4 | B50: Excavación maquinaría local y traslado a botadero, hasta 20 Km | C50: m3 | D50: ='03.- Cubicaciones'!C51 -> 15.283 | E50: =+E49*2 -> 15.2 | F50: =E50-D50 -> -0.083 | G50: =F50/E50 -> -0.0054605263
A51: 8.5 | B51: Suministro y construcción moldajes de madera o metálicos | C51: m2 | D51: ='03.- Cubicaciones'!C52 -> 26.16 | E51: 34 | F51: =E51-D51 -> 7.84 | G51: =F51/E51 -> 0.23058824
A52: 8.6 | B52: Suministro e instalación armadura A630-420H, diámetro 12mm | C52: kg | D52: ='03.- Cubicaciones'!C53 -> 392 | E52: 500 | F52: =E52-D52 -> 108 | G52: =F52/E52 -> 0.216
A53: 8.7 | B53: Suministro e instalación de pernos de anclaje químico | C53: un | D53: ='03.- Cubicaciones'!C54 -> 64 | E53: 64 | F53: =E53-D53 -> 0 | G53: =F53/E53 -> 0
A54: 9 | B54: Cámara Separadora, ubicación aledaño a PMT
A55: 9.1 | B55: Suministro e Instalación Hormigón G15, con aditivo impermeabilizante, igol denso. | C55: m3 | D55: ='03.- Cubicaciones'!C56 -> 2.112 | E55: 2.5 | F55: =E55-D55 -> 0.388 | G55: =F55/E55 -> 0.1552
A56: 9.2 | B56: Suministro e instalación emplantillado hormigón G5 | C56: m3 | D56: ='03.- Cubicaciones'!C57 -> 0.1805 | E56: 0.18 | F56: =E56-D56 -> -0.0005 | G56: =F56/E56 -> -0.0027777778
A57: 9.3 | B57: Suministro e instalación enfierradura malla acma C-188 | C57: kg | D57: ='03.- Cubicaciones'!C58 -> 66 | E57: 66 | F57: =E57-D57 -> 0 | G57: =F57/E57 -> 0
A58: 9.4 | B58: Excavación maquinaría local y traslado a botadero, hasta 20 Km | C58: m3 | D58: ='03.- Cubicaciones'!C59 -> 6.137 | E58: 6.4 | F58: =E58-D58 -> 0.263 | G58: =F58/E58 -> 0.04109375
A59: 9.5 | B59: Suministro y construcción moldajes de madera o metálicos | C59: m2 | D59: ='03.- Cubicaciones'!C60 -> 21.12 | E59: 26 | F59: =E59-D59 -> 4.88 | G59: =F59/E59 -> 0.18769231
A60: 9.6 | B60: Tapa en losa de hormigón G15, incluye armadura acma 188, aditivo imperm. | C60: un | D60: ='03.- Cubicaciones'!C61 -> 1 | E60: 1 | F60: =E60-D60 -> 0 | G60: =F60/E60 -> 0
A61: 10 | B61: Fundación Grupo Generador 400kVA SS.AA + Pretil de Contención
A62: 10.1 | B62: Suministro e instalación de hormigón G-15 con aditivo imp, igol denso, pintura, junta poliuretano | C62: m3 | D62: ='03.- Cubicaciones'!C63 -> 4.4486 | E62: =4.85 -> 4.85 | F62: =E62-D62 -> 0.4014 | G62: =F62/E62 -> 0.082762887
A63: 10.2 | B63: Suministro e instalación emplantillado hormigón G5 | C63: m3 | D63: ='03.- Cubicaciones'!C64 -> 1.11215 | E63: =1.3 -> 1.3 | F63: =E63-D63 -> 0.18785 | G63: =F63/E63 -> 0.1445
A64: 10.3 | B64: Suministro e Instalación relleno estructural compactado al 95% DMSC | C64: m3 | D64: ='03.- Cubicaciones'!C65 -> 16 | E64: 16 | F64: =E64-D64 -> 0 | G64: =F64/E64 -> 0
A65: 10.4 | B65: Excavación maquinaría local y traslado a botadero, hasta 20 Km | C65: m3 | D65: ='03.- Cubicaciones'!C66 -> 7.78505 | E65: 21 | F65: =E65-D65 -> 13.21495 | G65: =F65/E65 -> 0.62928333
A66: 10.5 | B66: Suministro y construcción moldajes de madera o metálicos | C66: m2 | D66: ='03.- Cubicaciones'!C67 -> 4.196 | E66: =4.2 -> 4.2 | F66: =E66-D66 -> 0.004 | G66: =F66/E66 -> 0.00095238095
A67: 10.6 | B67: Suministro e instalación de pernos de anclaje químico | C67: un | D67: ='03.- Cubicaciones'!C68 -> 10 | E67: =10 -> 10 | F67: =E67-D67 -> 0 | G67: =F67/E67 -> 0
A68: 10.7 | B68: Suministro e instalación rejilla galvanizada nervada | C68: un | D68: ='03.- Cubicaciones'!C69 -> 21 | E68: =21 -> 21 | F68: =E68-D68 -> 0 | G68: =F68/E68 -> 0
A69: 10.8 | B69: Suministro e instalación armadura A630-420H, diámetro 12mm | C69: kg | D69: ='03.- Cubicaciones'!C70 -> 149.916 | E69: =237 -> 237 | F69: =E69-D69 -> 87.084 | G69: =F69/E69 -> 0.36744304
A70: 11 | B70: Cámaras Separadora Agua - Hidrocarburos
A71: 11.1 | B71: Suministro e Instalación Cámara separadora de hidrocarburos de 230 litros Infraplast | C71: un | D71: ='03.- Cubicaciones'!C72 -> 1 | E71: 1 | F71: =E71-D71 -> 0 | G71: =F71/E71 -> 0
A72: 11.2 | B72: Suministro e instalación ducto PVC hidra Ø=110 mm flexodren | C72: m | D72: ='03.- Cubicaciones'!C73 -> 3 | E72: 3 | F72: =E72-D72 -> 0 | G72: =F72/E72 -> 0
A73: 11.3 | B73: Suministro e instalación arena compactada | C73: m3 | D73: ='03.- Cubicaciones'!C74 -> 1.8 | E73: 1.8 | F73: =E73-D73 -> 0 | G73: =F73/E73 -> 0
A74: 11.4 | B74: Excavación, carguío sobre camión y traslado a botadero | C74: m3 | D74: ='03.- Cubicaciones'!C75 -> 3.2 | E74: 3.2 | F74: =E74-D74 -> 0 | G74: =F74/E74 -> 0
A75: 12 | B75: Cámara ciega para almacenar eventuales derrames, en sector exterior sala de máquinas
A76: 12.1 | B76: Suministro e Instalación Hormigón G15, con aditivo impermeabilizante, igol denso. | C76: m3 | D76: ='03.- Cubicaciones'!C77 -> 1.2 | E76: 1.2 | F76: =E76-D76 -> 0 | G76: =F76/E76 -> 0
A77: 12.2 | B77: Suministro e instalación emplantillado hormigón G5 | C77: m3 | D77: ='03.- Cubicaciones'!C78 -> 0.1 | E77: 0.1 | F77: =E77-D77 -> 0 | G77: =F77/E77 -> 0
A78: 12.3 | B78: Excavación maquinaría local y traslado a botadero, hasta 20 Km | C78: m3 | D78: ='03.- Cubicaciones'!C79 -> 1.3 | E78: 1.3 | F78: =E78-D78 -> 0 | G78: =F78/E78 -> 0
A79: 12.4 | B79: Suministro y construcción moldajes de madera o metálicos | C79: m2 | D79: ='03.- Cubicaciones'!C80 -> 17.3 | E79: 17.3 | F79: =E79-D79 -> 0 | G79: =F79/E79 -> 0
A80: 12.5 | B80: Suministro e instalación enfierradura malla acma C-188 | C80: kg | D80: ='03.- Cubicaciones'!C81 -> 35 | E80: 35 | F80: =E80-D80 -> 0 | G80: =F80/E80 -> 0
A81: 12.6 | B81: Ducto PVC 110mm, considera salida desde pretiles de transformador a cámara separadora | C81: m | D81: ='03.- Cubicaciones'!C82 -> 32 | E81: 32 | F81: =E81-D81 -> 0 | G81: =F81/E81 -> 0
A82: 13 | B82: Zanjas de infiltración con cubo dren para sistema de contención de derrames
A83: 13.1 | B83: Suministro y colocación arena limpia compactada | C83: m3 | D83: ='03.- Cubicaciones'!C84 -> 14.4 | E83: 14.4 | F83: =E83-D83 -> 0 | G83: =F83/E83 -> 0
A84: 13.2 | B84: Suministro y colocación gravilla (bajo tamiz 1") | C84: m3 | D84: ='03.- Cubicaciones'!C85 -> 2.5 | E84: 2.5 | F84: =E84-D84 -> 0 | G84: =F84/E84 -> 0
A85: 13.3 | B85: Suministro e instalación Cubos dren 26 t/m2 | C85: un | D85: ='03.- Cubicaciones'!C86 -> 48 | E85: 48 | F85: =E85-D85 -> 0 | G85: =F85/E85 -> 0
A86: 13.4 | B86: Excavación máquinaria local, traslado a botadero hasta 20km (geométrica, sin esponajamiento) | C86: m3 | D86: ='03.- Cubicaciones'!C87 -> 15 | E86: 15 | F86: =E86-D86 -> 0 | G86: =F86/E86 -> 0
A87: 13.5 | B87: Suministro e instalación PVC 110mm | C87: m | D87: ='03.- Cubicaciones'!C88 -> 36 | E87: 36 | F87: =E87-D87 -> 0 | G87: =F87/E87 -> 0
A88: 13.6 | B88: Suministro e instalación códo de PVC 110mm | C88: un | D88: ='03.- Cubicaciones'!C89 -> 5 | E88: 5 | F88: =E88-D88 -> 0 | G88: =F88/E88 -> 0
A89: 13.7 | B89: Suministro e instalación de Geotextil | C89: m2 | D89: ='03.- Cubicaciones'!C90 -> 29 | E89: 29 | F89: =E89-D89 -> 0 | G89: =F89/E89 -> 0
A90: 13.8 | B90: Suministro e instalación PVC110 mm ranurado | C90: m | D90: ='03.- Cubicaciones'!C91 -> 6 | E90: 6 | F90: =E90-D90 -> 0 | G90: =F90/E90 -> 0
A91: 14 | B91: Fundación Sala Eléctrica
A92: 14.1 | B92: Suministro e Instalación Hormigón G20(10)20-8 | C92: m3 | D92: ='03.- Cubicaciones'!C93 -> 2.94 | E92: 2.94 | F92: =E92-D92 -> 0 | G92: =F92/E92 -> 0
A93: 14.2 | B93: Suministro e instalación emplantillado hormigón G5 | C93: m3 | D93: ='03.- Cubicaciones'!C94 -> 0.25 | E93: 0.25 | F93: =E93-D93 -> 0 | G93: =F93/E93 -> 0
A94: 14.3 | B94: Suministro e Instalación relleno estructural compactado al 95% DMSC | C94: m3 | D94: ='03.- Cubicaciones'!C95 -> 7.865 | E94: 6.5 | F94: =E94-D94 -> -1.365 | G94: =F94/E94 -> -0.21
A95: 14.4 | B95: Excavación maquinaría local y traslado a botadero, hasta 20 Km | C95: m3 | D95: ='03.- Cubicaciones'!C96 -> 12.705 | E95: 8 | F95: =E95-D95 -> -4.705 | G95: =F95/E95 -> -0.588125
A96: 14.5 | B96: Suministro y construcción moldajes de madera o metálicos | C96: m2 | D96: ='03.- Cubicaciones'!C97 -> 17 | E96: 17 | F96: =E96-D96 -> 0 | G96: =F96/E96 -> 0
A97: 14.6 | B97: Suministro e instalación armadura A630-420H, diámetro 12mm | C97: kg | D97: ='03.- Cubicaciones'!C98 -> 150 | E97: 10 | F97: =E97-D97 -> -140 | G97: =F97/E97 -> -14
A98: 14.7 | B98: Suministro e instalación de pernos de anclaje químico | C98: un | D98: ='03.- Cubicaciones'!C99 -> 10 | E98: 10 | F98: =E98-D98 -> 0 | G98: =F98/E98 -> 0
A99: 14.8 | B99: Suministro e Instalación L100x100x6 L=100mm | C99: un | D99: ='03.- Cubicaciones'!C100 -> 10 | E99: 10 | F99: =E99-D99 -> 0 | G99: =F99/E99 -> 0
B101: Estructuras
A102: 15 | B102: Estructura Soporte Transformador 0,5 MVA, 5 unidades.
A103: 15.1 | B103: Suministro y construcción de soporte con perfiles, metálicos galvanizados | C103: kg | D103: ='03.- Cubicaciones'!C104 -> 845.25 | E103: =161*5*1.05 -> 845.25 | F103: =E103-D103 -> 0 | G103: =F103/E103 -> 0
...

Sheet 05.- PU Clave
C4: Sueldos | D4: HH | E4: Sueldo L. | F4: Sueldo B. | I4: UF | J4: 39267
C5: Maestro | D5: =F5/180 -> 7250 | E5: 900000 | F5: =E5*1.45 -> 1305000
C6: Ayudante | D6: =F6/180 -> 5638.8889 | E6: 700000 | F6: =E6*1.45 -> 1015000
C7: Jornal | D7: =F7/180 -> 5397.2222 | E7: 670000 | F7: =E7*1.45 -> 971500
C8: Cerámista | D8: =F8/180 -> 11680.556 | E8: 1450000 | F8: =E8*1.45 -> 2102500
C9: Pintor | D9: =F9/180 -> 8055.5556 | E9: 1000000 | F9: =E9*1.45 -> 1450000
C10: SC Enfierrador | D10: 600
C11: SC Perfilería Metálica | D11: 1500
C12: Maestro Soldador | D12: =F12/180 -> 8055.5556 | E12: 1000000 | F12: =E12*1.45 -> 1450000
C13: Ayudante Soldador | D13: =F13/180 -> 7250 | E13: 900000 | F13: =E13*1.45 -> 1305000
C15: Maquinaría | D15: HM
C16: Excavadora | D16: 50000
C17: Retroexcavadora | D17: 32000
C18: Motoniveladora | D18: 62000
C19: Rodillo | D19: 42000
C20: Camión Tolva | D20: 38000
C21: Camión Aljibe | D21: 32000
C23: Aridos | D23: PU
C24: Base Granular CBR >100% | D24: 22000
C25: Base Granular CBR >50% | D25: 20000
C26: Arena | D26: 24000
C27: Gravilla | D27: 26000
C28: Grava Limpia | D28: 28000
C29: Bolones | D29: 37000
C31: Hormigón | D31: M3
C32: Hormigón G25(10)20-8 | D32: =2.85*UF -> 111910.95
C33: Hormigón G20(10)20-8 | D33: =2.76*UF -> 108376.92
C34: Hormigón G15(10)20-8 | D34: =2.67*UF -> 104842.89
C35: Hormigón G5 | D35: =2.5*UF -> 98167.5
C37: Subcontratos | D37: Ml
C38: Subcontrato Sum e Inst Bulldog | D38: 30000
C39: Subcontrato Sum e Inst Acmafor | D39: 30550
C40: Subcontrato Hidrosembrado | D40: 42742
C41: Subcontrato Sum e Instalación Hojalatería | D41: 16500
C42: Subcontrato Instalación Sanitaria | D42: 17000
C44: Cubo Dren Insytec | D44: 11390 | E44: un

Sheet 1.1
B1: 02.- Presupuesto'!A1
B3: Código | C3: Recurso | D3: Unidad | E3: Descripción | F3: Cantidad | G3: Precio Unitario | H3: Total | M3: Mat | N3: MO | O3: SC | P3: Arr
B4: 1.1 | C4: Partida | D4: ='01.- Presupuesto'!F16 -> gl | E4: ='01.- Presupuesto'!C16 -> Desbroce | F4: ='01.- Presupuesto'!G16 -> 1 | G4: =G9 -> 19164000 | H4: =H9 -> 19164000 | J4: Cantidad | K4: Costo | M4: =SUMIF(C5:C21,"Material",K5:K21) -> 0 | N4: =SUMIF(C5:C21,"Mano de Obra",K5:K21) -> 0 | O4: =SUMIF(C5:C21,"Subcontrato",K5:K21) -> 0 | P4: =SUMIF(C5:C21,"Ser&Arr",K5:K21) -> 19164000 | Q4: =SUM(M4:P4) -> 19164000
C5: Ser&Arr | D5: hm | E5: Motoniveladora | F5: =ROUNDUP(1/20*2442*0.3,0) -> 37 | G5: =Motoniveladora -> 62000 | H5: =ROUND(F5*G5,3) -> 2294000 | J5: =F5*$F$4 -> 37 | K5: =H5*$F$4 -> 2294000
C6: Ser&Arr | D6: hm | E6: Retroexcavadora | F6: =ROUNDUP(1/20*2442*0.3,0) -> 37 | G6: =Retroexcavadora -> 32000 | H6: =ROUND(F6*G6,3) -> 1184000 | J6: =F6*$F$4 -> 37 | K6: =H6*$F$4 -> 1184000
C7: Ser&Arr | D7: hm | E7: Camión Tolva | F7: =ROUNDUP(1/20*2442*0.3,0) -> 37 | G7: =Tolva -> 38000 | H7: =ROUND(F7*G7,3) -> 1406000 | J7: =F7*$F$4 -> 37 | K7: =H7*$F$4 -> 1406000
C8: Ser&Arr | D8: m3 | E8: Carga y Retiro de Escombros | F8: =ROUNDDOWN(1.3*2442*0.3,0) -> 952 | G8: 15000 | H8: =ROUND(F8*G8,3) -> 14280000 | J8: =F8*$F$4 -> 952 | K8: =H8*$F$4 -> 14280000
E9: Total APU 1.1 | F9: =$F$4 -> 1 | G9: =SUM(H5:H8) -> 19164000 | H9: =ROUND(F9*G9,3) -> 19164000 | K9: =SUM(K5:K8) -> 19164000

Sheet 2.1
B1: 02.- Presupuesto'!A1
B3: Código | C3: Recurso | D3: Unidad | E3: Descripción | F3: Cantidad | G3: Precio Unitario | H3: Total | M3: Mat | N3: MO | O3: SC | P3: Arr
B4: 2.1 | C4: Partida | D4: ='01.- Presupuesto'!F18 -> m3 | E4: ='01.- Presupuesto'!C18 -> Excavación, carguió sobre camión y traslado a botadero, e = variable | F4: ='01.- Presupuesto'!G18 -> 890 | G4: =G9 -> 25500 | H4: =H9 -> 22695000 | J4: Cantidad | K4: Costo | M4: =SUMIF(C5:C21,"Material",K5:K21) -> 0 | N4: =SUMIF(C5:C21,"Mano de Obra",K5:K21) -> 0 | O4: =SUMIF(C5:C21,"Subcontrato",K5:K21) -> 0 | P4: =SUMIF(C5:C21,"Ser&Arr",K5:K21) -> 22695000 | Q4: =SUM(M4:P4) -> 22695000
C5: Ser&Arr | D5: hm | E5: Excavadora | F5: =1/20 -> 0.05 | G5: =Excavadora -> 50000 | H5: =ROUND(F5*G5,3) -> 2500 | J5: =F5*$F$4 -> 44.5 | K5: =H5*$F$4 -> 2225000
C6: Ser&Arr | D6: hm | E6: Retroexcavadora | F6: =1/20 -> 0.05 | G6: =Retroexcavadora -> 32000 | H6: =ROUND(F6*G6,3) -> 1600 | J6: =F6*$F$4 -> 44.5 | K6: =H6*$F$4 -> 1424000
C7: Ser&Arr | D7: hm | E7: Camión Tolva | F7: =1/20 -> 0.05 | G7: =Tolva -> 38000 | H7: =ROUND(F7*G7,3) -> 1900 | J7: =F7*$F$4 -> 44.5 | K7: =H7*$F$4 -> 1691000
C8: Ser&Arr | D8: m3 | E8: Carga y Retiro de Escombros | F8: 1.3 | G8: 15000 | H8: =ROUND(F8*G8,3) -> 19500 | J8: =F8*$F$4 -> 1157 | K8: =H8*$F$4 -> 17355000
E9: Total APU 2.1 | F9: =$F$4 -> 890 | G9: =SUM(H5:H8) -> 25500 | H9: =ROUND(F9*G9,3) -> 22695000 | K9: =SUM(K5:K8) -> 22695000

Sheet 2.2
B1: 02.- Presupuesto'!A1
B3: Código | C3: Recurso | D3: Unidad | E3: Descripción | F3: Cantidad | G3: Precio Unitario | H3: Total | M3: Mat | N3: MO | O3: SC | P3: Arr
B4: 2.2 | C4: Partida | D4: ='01.- Presupuesto'!F19 -> m3 | E4: ='01.- Presupuesto'!C19 -> Retiro y reposición zanja para ducto malla de puesta a tierra | F4: ='01.- Presupuesto'!G19 -> 400 | G4: =G15 -> 34101.438 | H4: =H15 -> 13640575 | J4: Cantidad | K4: Costo | M4: =SUMIF(C5:C27,"Material",K5:K27) -> 10400000 | N4: =SUMIF(C5:C27,"Mano de Obra",K5:K27) -> 1153555.6 | O4: =SUMIF(C5:C27,"Subcontrato",K5:K27) -> 0 | P4: =SUMIF(C5:C27,"Ser&Arr",K5:K27) -> 2087019.6 | Q4: =SUM(M4:P4) -> 13640575
C5: Material | D5: m3 | E5: Base Granular CBR >50% | F5: 1.3 | G5: =Base50 -> 20000 | H5: =ROUND(F5*G5,3) -> 26000 | J5: =F5*$F$4 -> 520 | K5: =H5*$F$4 -> 10400000
C6: Mano de Obra | D6: hh | E6: Maestro | F6: =2*1/20 -> 0.1 | G6: =Maestro -> 7250 | H6: =ROUND(F6*G6,3) -> 725 | J6: =F6*$F$4 -> 40 | K6: =H6*$F$4 -> 290000
C7: Mano de Obra | D7: hh | E7: Jornal | F7: =2*4*1/20 -> 0.4 | G7: =Jornal -> 5397.2222 | H7: =ROUND(F7*G7,3) -> 2158.889 | J7: =F7*$F$4 -> 160 | K7: =H7*$F$4 -> 863555.6
C8: Ser&Arr | D8: % | E8: Desgaste de Herramientas | F8: 0.2 | G8: =SUM(H6:H7) -> 2883.889 | H8: =ROUND(F8*G8,3) -> 576.778 | J8: =F8*$F$4 -> 80 | K8: =H8*$F$4 -> 230711.2
C9: Ser&Arr | D9: un | E9: Chuzo | F9: 0.01 | G9: 17100 | H9: =ROUND(F9*G9,3) -> 171 | J9: =F9*$F$4 -> 4 | K9: =H9*$F$4 -> 68400
C10: Ser&Arr | D10: un | E10: Pala Punta Huevo | F10: 0.01 | G10: 7000 | H10: =ROUND(F10*G10,3) -> 70 | J10: =F10*$F$4 -> 4 | K10: =H10*$F$4 -> 28000
C11: Ser&Arr | D11: hm | E11: Retroexcavadora | F11: =2*1/20 -> 0.1 | G11: =Retroexcavadora -> 32000 | H11: =ROUND(F11*G11,3) -> 3200 | J11: =F11*$F$4 -> 40 | K11: =H11*$F$4 -> 1280000
C12: Ser&Arr | D12: día | E12: Placa Compactadora | F12: =1/20/8 -> 0.00625 | G12: 25000 | H12: =ROUND(F12*G12,3) -> 156.25 | J12: =F12*$F$4 -> 2.5 | K12: =H12*$F$4 -> 62500
C13: Ser&Arr | D13: un | E13: Ensayo Granulometría | F13: =1/F4 -> 0.0025 | G13: =(0.6+4.4)*UF -> 196335 | H13: =ROUND(F13*G13,3) -> 490.838 | J13: =F13*$F$4 -> 1 | K13: =H13*$F$4 -> 196335.2
C14: Ser&Arr | D14: un | E14: Ensayo Densidad In Situ | F14: =3/F4 -> 0.0075 | G14: =(0.41+4.4/3)*UF -> 73691.07 | H14: =ROUND(F14*G14,3) -> 552.683 | J14: =F14*$F$4 -> 3 | K14: =H14*$F$4 -> 221073.2
E15: Total APU 2.2 | F15: =$F$4 -> 400 | G15: =SUM(H5:H14) -> 34101.438 | H15: =ROUND(F15*G15,3) -> 13640575 | K15: =SUM(K5:K14) -> 13640575

Sheet 2.3
B1: 02.- Presupuesto'!A1
B3: Código | C3: Recurso | D3: Unidad | E3: Descripción | F3: Cantidad | G3: Precio Unitario | H3: Total | M3: Mat | N3: MO | O3: SC | P3: Arr
B4: 2.3 | C4: Partida | D4: ='01.- Presupuesto'!F20 -> m3 | E4: ='01.- Presupuesto'!C20 -> Formación y compactación de plataforma e= variable. Relleno e= 20cm | F4: ='01.- Presupuesto'!G20 -> 754 | G4: =G18 -> 67330.534 | H4: =H18 -> 50767223 | J4: Cantidad | K4: Costo | M4: =SUMIF(C5:C30,"Material",K5:K30) -> 42295257 | N4: =SUMIF(C5:C30,"Mano de Obra",K5:K30) -> 1961044.4 | O4: =SUMIF(C5:C30,"Subcontrato",K5:K30) -> 0 | P4: =SUMIF(C5:C30,"Ser&Arr",K5:K30) -> 6510921.2 | Q4: =SUM(M4:P4) -> 50767223
C5: Material | D5: m3 | E5: Base Granular CBR >100% | F5: 1.3 | G5: =Base100 -> 22000 | H5: =ROUND(F5*G5,3) -> 28600 | J5: =F5*$F$4 -> 980.2 | K5: =H5*$F$4 -> 21564400
C6: Ser&Arr | D6: hm | E6: Retroexcavadora | F6: =1/20 -> 0.05 | G6: =Retroexcavadora -> 32000 | H6: =ROUND(F6*G6,3) -> 1600 | J6: =F6*$F$4 -> 37.7 | K6: =H6*$F$4 -> 1206400
C7: Ser&Arr | D7: hm | E7: Rodillo | F7: =1/20 -> 0.05 | G7: =Rodillo -> 42000 | H7: =ROUND(F7*G7,3) -> 2100 | J7: =F7*$F$4 -> 37.7 | K7: =H7*$F$4 -> 1583400
C8: Ser&Arr | D8: hm | E8: Camión Aljibe | F8: =1/20 -> 0.05 | G8: =Aljibe -> 32000 | H8: =ROUND(F8*G8,3) -> 1600 | J8: =F8*$F$4 -> 37.7 | K8: =H8*$F$4 -> 1206400
C9: Ser&Arr | D9: un | E9: Ensayo Granulometría | F9: =1/F4 -> 0.0013262599 | G9: =(0.6+4.4)*UF -> 196335 | H9: =ROUND(F9*G9,3) -> 260.391 | J9: =F9*$F$4 -> 1 | K9: =H9*$F$4 -> 196334.81
C10: Ser&Arr | D10: un | E10: Ensayo Proctor | F10: =1/F4 -> 0.0013262599 | G10: =1.3*UF -> 51047.1 | H10: =ROUND(F10*G10,3) -> 67.702 | J10: =F10*$F$4 -> 1 | K10: =H10*$F$4 -> 51047.308
C11: Ser&Arr | D11: un | E11: Ensayo CBR | F11: =1/50 -> 0.02 | G11: =(1.7+4.4/3)*UF -> 124345.5 | H11: =ROUND(F11*G11,3) -> 2486.91 | J11: =F11*$F$4 -> 15.08 | K11: =H11*$F$4 -> 1875130.1
B12: 2.3.1 | C12: Partida | D12: m | E12: Gaviones | F12: =68/F4 -> 0.090185676 | G12: =SUM(H13:H17) -> 339472.21 | H12: =G12*F12 -> 30615.531
C13: Material | D13: un | E13: Gaviones | F13: =6/2 -> 3 | G13: =54290/1.19 -> 45621.849 | H13: =ROUND(F13*G13,3) -> 136865.55 | J13: =F13*$F$4*F12 -> 204 | K13: =G13*J13 -> 9306857.1
C14: Material | D14: m3 | E14: Grava | F14: =1*1*6 -> 6 | G14: =Grava -> 28000 | H14: =ROUND(F14*G14,3) -> 168000 | J14: =F14*$F$4*F12 -> 408 | K14: =G14*J14 -> 11424000
C15: Mano de Obra | D15: hh | E15: Maestro | F15: 1 | G15: =Maestro -> 7250 | H15: =ROUND(F15*G15,3) -> 7250 | J15: =F15*$F$4*F12 -> 68 | K15: =G15*J15 -> 493000
C16: Mano de Obra | D16: hh | E16: Jornal | F16: 4 | G16: =Jornal -> 5397.2222 | H16: =ROUND(F16*G16,3) -> 21588.889 | J16: =F16*$F$4*F12 -> 272 | K16: =G16*J16 -> 1468044.4
C17: Ser&Arr | D17: % | E17: Desgaste de Herramientas | F17: 0.2 | G17: =SUM(H15:H16) -> 28838.889 | H17: =ROUND(F17*G17,3) -> 5767.778 | J17: =F17*$F$4*F12 -> 13.6 | K17: =G17*J17 -> 392208.89
E18: Total APU 2.3 | F18: =$F$4 -> 754 | G18: =SUM(H5:H12) -> 67330.534 | H18: =ROUND(F18*G18,3) -> 50767223 | K18: =SUM(K5:K17) -> 50767223

Sheet 2.4
B1: 02.- Presupuesto'!A1
B3: Código | C3: Recurso | D3: Unidad | E3: Descripción | F3: Cantidad | G3: Precio Unitario | H3: Total | M3: Mat | N3: MO | O3: SC | P3: Arr
B4: 2.4 | C4: Partida | D4: ='01.- Presupuesto'!F21 -> gl | E4: ='01.- Presupuesto'!C21 -> Tratamiento de taludes de corte con hidrosiembra según manual de carreteras | F4: ='01.- Presupuesto'!G21 -> 1 | G4: =G6 -> 42742 | H4: =H6 -> 42742 | J4: Cantidad | K4: Costo | M4: =SUMIF(C5:C18,"Material",K5:K18) -> 0 | N4: =SUMIF(C5:C18,"Mano de Obra",K5:K18) -> 0 | O4: =SUMIF(C5:C18,"Subcontrato",K5:K18) -> 42742 | P4: =SUMIF(C5:C18,"Ser&Arr",K5:K18) -> 0 | Q4: =SUM(M4:P4) -> 42742
C5: Subcontrato | D5: m2 | E5: Subcontrato Tratamiento con Hidrosembrado | F5: 1 | G5: =SCHidrosembrado -> 42742 | H5: =ROUND(F5*G5,3) -> 42742 | J5: =F5*$F$4 -> 1 | K5: =H5*$F$4 -> 42742
E6: Total APU 2.4 | F6: =$F$4 -> 1 | G6: =SUM(H5:H5) -> 42742 | H6: =ROUND(F6*G6,3) -> 42742 | K6: =SUM(K5:K5) -> 42742

Sheet 3.1
B1: 02.- Presupuesto'!A1
B3: Código | C3: Recurso | D3: Unidad | E3: Descripción | F3: Cantidad | G3: Precio Unitario | H3: Total | M3: Mat | N3: MO | O3: SC | P3: Arr
B4: 3.1 | C4: Partida | D4: ='01.- Presupuesto'!F23 -> m3 | E4: ='01.- Presupuesto'!C23 -> Sobrexcavación para caminos interiores, carguio sobre camión y traslado | F4: ='01.- Presupuesto'!G23 -> 760 | G4: =G9 -> 25500 | H4: =H9 -> 19380000 | J4: Cantidad | K4: Costo | M4: =SUMIF(C5:C21,"Material",K5:K21) -> 0 | N4: =SUMIF(C5:C21,"Mano de Obra",K5:K21) -> 0 | O4: =SUMIF(C5:C21,"Subcontrato",K5:K21) -> 0 | P4: =SUMIF(C5:C21,"Ser&Arr",K5:K21) -> 19380000 | Q4: =SUM(M4:P4) -> 19380000
C5: Ser&Arr | D5: hm | E5: Excavadora | F5: =1/20 -> 0.05 | G5: =Excavadora -> 50000 | H5: =ROUND(F5*G5,3) -> 2500 | J5: =F5*$F$4 -> 38 | K5: =H5*$F$4 -> 1900000
C6: Ser&Arr | D6: hm | E6: Retroexcavadora | F6: =1/20 -> 0.05 | G6: =Retroexcavadora -> 32000 | H6: =ROUND(F6*G6,3) -> 1600 | J6: =F6*$F$4 -> 38 | K6: =H6*$F$4 -> 1216000
C7: Ser&Arr | D7: hm | E7: Camión Tolva | F7: =1/20 -> 0.05 | G7: =Tolva -> 38000 | H7: =ROUND(F7*G7,3) -> 1900 | J7: =F7*$F$4 -> 38 | K7: =H7*$F$4 -> 1444000
C8: Ser&Arr | D8: m3 | E8: Carga y Retiro de Escombros | F8: 1.3 | G8: 15000 | H8: =ROUND(F8*G8,3) -> 19500 | J8: =F8*$F$4 -> 988 | K8: =H8*$F$4 -> 14820000
E9: Total APU 3.1 | F9: =$F$4 -> 760 | G9: =SUM(H5:H8) -> 25500 | H9: =ROUND(F9*G9,3) -> 19380000 | K9: =SUM(K5:K8) -> 19380000

Sheet 3.2
B1: 02.- Presupuesto'!A1
B3: Código | C3: Recurso | D3: Unidad | E3: Descripción | F3: Cantidad | G3: Precio Unitario | H3: Total | M3: Mat | N3: MO | O3: SC | P3: Arr
B4: 3.2 | C4: Partida | D4: ='01.- Presupuesto'!F24 -> m3 | E4: ='01.- Presupuesto'!C24 -> Suministro y colocación Base Granular CBR >100% e=26cm | F4: ='01.- Presupuesto'!G24 -> 234 | G4: =G12 -> 37444.098 | H4: =H12 -> 8761918.9 | J4: Cantidad | K4: Costo | M4: =SUMIF(C5:C24,"Material",K5:K24) -> 6692400 | N4: =SUMIF(C5:C24,"Mano de Obra",K5:K24) -> 0 | O4: =SUMIF(C5:C24,"Subcontrato",K5:K24) -> 0 | P4: =SUMIF(C5:C24,"Ser&Arr",K5:K24) -> 2069518.9 | Q4: =SUM(M4:P4) -> 8761918.9
C5: Material | D5: m3 | E5: Base Granular CBR >100% | F5: 1.3 | G5: =Base100 -> 22000 | H5: =ROUND(F5*G5,3) -> 28600 | J5: =F5*$F$4 -> 304.2 | K5: =H5*$F$4 -> 6692400
C6: Ser&Arr | D6: hm | E6: Retroexcavadora | F6: =1/20 -> 0.05 | G6: =Retroexcavadora -> 32000 | H6: =ROUND(F6*G6,3) -> 1600 | J6: =F6*$F$4 -> 11.7 | K6: =H6*$F$4 -> 374400
C7: Ser&Arr | D7: hm | E7: Rodillo | F7: =1/20 -> 0.05 | G7: =Rodillo -> 42000 | H7: =ROUND(F7*G7,3) -> 2100 | J7: =F7*$F$4 -> 11.7 | K7: =H7*$F$4 -> 491400
C8: Ser&Arr | D8: hm | E8: Camión Aljibe | F8: =1/20 -> 0.05 | G8: =Aljibe -> 32000 | H8: =ROUND(F8*G8,3) -> 1600 | J8: =F8*$F$4 -> 11.7 | K8: =H8*$F$4 -> 374400
C9: Ser&Arr | D9: un | E9: Ensayo Granulometría | F9: =1/F4 -> 0.0042735043 | G9: =(0.6+4.4)*UF -> 196335 | H9: =ROUND(F9*G9,3) -> 839.038 | J9: =F9*$F$4 -> 1 | K9: =H9*$F$4 -> 196334.89
C10: Ser&Arr | D10: un | E10: Ensayo Proctor | F10: =1/F4 -> 0.0042735043 | G10: =1.3*UF -> 51047.1 | H10: =ROUND(F10*G10,3) -> 218.15 | J10: =F10*$F$4 -> 1 | K10: =H10*$F$4 -> 51047.1
C11: Ser&Arr | D11: un | E11: Ensayo CBR | F11: =1/50 -> 0.02 | G11: =(1.7+4.4/3)*UF -> 124345.5 | H11: =ROUND(F11*G11,3) -> 2486.91 | J11: =F11*$F$4 -> 4.68 | K11: =H11*$F$4 -> 581936.94
E12: Total APU 3.2 | F12: =$F$4 -> 234 | G12: =SUM(H5:H11) -> 37444.098 | H12: =ROUND(F12*G12,3) -> 8761918.9 | K12: =SUM(K5:K11) -> 8761918.9

Sheet 3.3
B1: 02.- Presupuesto'!A1
B3: Código | C3: Recurso | D3: Unidad | E3: Descripción | F3: Cantidad | G3: Precio Unitario | H3: Total | M3: Mat | N3: MO | O3: SC | P3: Arr
B4: 3.3 | C4: Partida | D4: ='01.- Presupuesto'!F25 -> m3 | E4: ='01.- Presupuesto'!C25 -> Suministro y colocación Sub-Base granular CBR > 50% e=20cm | F4: ='01.- Presupuesto'!G25 -> 180 | G4: =G12 -> 35161.255 | H4: =H12 -> 6329025.9 | J4: Cantidad | K4: Costo | M4: =SUMIF(C5:C24,"Material",K5:K24) -> 4680000 | N4: =SUMIF(C5:C24,"Mano de Obra",K5:K24) -> 0 | O4: =SUMIF(C5:C24,"Subcontrato",K5:K24) -> 0 | P4: =SUMIF(C5:C24,"Ser&Arr",K5:K24) -> 1649025.9 | Q4: =SUM(M4:P4) -> 6329025.9
C5: Material | D5: m3 | E5: Base Granular CBR >50% | F5: 1.3 | G5: =Base50 -> 20000 | H5: =ROUND(F5*G5,3) -> 26000 | J5: =F5*$F$4 -> 234 | K5: =H5*$F$4 -> 4680000
C6: Ser&Arr | D6: hm | E6: Retroexcavadora | F6: =1/20 -> 0.05 | G6: =Retroexcavadora -> 32000 | H6: =ROUND(F6*G6,3) -> 1600 | J6: =F6*$F$4 -> 9 | K6: =H6*$F$4 -> 288000
C7: Ser&Arr | D7: hm | E7: Rodillo | F7: =1/20 -> 0.05 | G7: =Rodillo -> 42000 | H7: =ROUND(F7*G7,3) -> 2100 | J7: =F7*$F$4 -> 9 | K7: =H7*$F$4 -> 378000
C8: Ser&Arr | D8: hm | E8: Camión Aljibe | F8: =1/20 -> 0.05 | G8: =Aljibe -> 32000 | H8: =ROUND(F8*G8,3) -> 1600 | J8: =F8*$F$4 -> 9 | K8: =H8*$F$4 -> 288000
C9: Ser&Arr | D9: un | E9: Ensayo Granulometría | F9: =1/F4 -> 0.0055555556 | G9: =(0.6+4.4)*UF -> 196335 | H9: =ROUND(F9*G9,3) -> 1090.75 | J9: =F9*$F$4 -> 1 | K9: =H9*$F$4 -> 196335
C10: Ser&Arr | D10: un | E10: Ensayo Proctor | F10: =1/F4 -> 0.0055555556 | G10: =1.3*UF -> 51047.1 | H10: =ROUND(F10*G10,3) -> 283.595 | J10: =F10*$F$4 -> 1 | K10: =H10*$F$4 -> 51047.1
C11: Ser&Arr | D11: un | E11: Ensayo CBR | F11: =1/50 -> 0.02 | G11: =(1.7+4.4/3)*UF -> 124345.5 | H11: =ROUND(F11*G11,3) -> 2486.91 | J11: =F11*$F$4 -> 3.6 | K11: =H11*$F$4 -> 447643.8
E12: Total APU 3.3 | F12: =$F$4 -> 180 | G12: =SUM(H5:H11) -> 35161.255 | H12: =ROUND(F12*G12,3) -> 6329025.9 | K12: =SUM(K5:K11) -> 6329025.9

Sheet 3.4
B1: 02.- Presupuesto'!A1
B3: Código | C3: Recurso | D3: Unidad | E3: Descripción | F3: Cantidad | G3: Precio Unitario | H3: Total | M3: Mat | N3: MO | O3: SC | P3: Arr
B4: 3.4 | C4: Partida | D4: ='01.- Presupuesto'!F26 -> m3 | E4: ='01.- Presupuesto'!C26 -> Suministro y colocación de bolones para estabilización de suelos e=30cm | F4: ='01.- Presupuesto'!G26 -> 270 | G4: =G7 -> 49700 | H4: =H7 -> 13419000 | J4: Cantidad | K4: Costo | M4: =SUMIF(C5:C19,"Material",K5:K19) -> 12987000 | N4: =SUMIF(C5:C19,"Mano de Obra",K5:K19) -> 0 | O4: =SUMIF(C5:C19,"Subcontrato",K5:K19) -> 0 | P4: =SUMIF(C5:C19,"Ser&Arr",K5:K19) -> 432000 | Q4: =SUM(M4:P4) -> 13419000
C5: Material | D5: m3 | E5: Bolones | F5: 1.3 | G5: =Bolones -> 37000 | H5: =ROUND(F5*G5,3) -> 48100 | J5: =F5*$F$4 -> 351 | K5: =H5*$F$4 -> 12987000
C6: Ser&Arr | D6: hm | E6: Retroexcavadora | F6: =1/20 -> 0.05 | G6: =Retroexcavadora -> 32000 | H6: =ROUND(F6*G6,3) -> 1600 | J6: =F6*$F$4 -> 13.5 | K6: =H6*$F$4 -> 432000
E7: Total APU 3.4 | F7: =$F$4 -> 270 | G7: =SUM(H5:H6) -> 49700 | H7: =ROUND(F7*G7,3) -> 13419000 | K7: =SUM(K5:K6) -> 13419000

Sheet 3.5
B1: 02.- Presupuesto'!A1
B3: Código | C3: Recurso | D3: Unidad | E3: Descripción | F3: Cantidad | G3: Precio Unitario | H3: Total | M3: Mat | N3: MO | O3: SC | P3: Arr
B4: 3.5 | C4: Partida | D4: ='01.- Presupuesto'!F27 -> m2 | E4: ='01.- Presupuesto'!C27 -> Suministro e Instalación de Geotextil bajo la Sub-Base | F4: ='01.- Presupuesto'!G27 -> 900 | G4: =G9 -> 1623.533 | H4: =H9 -> 1461179.7 | J4: Cantidad | K4: Costo | M4: =SUMIF(C5:C21,"Material",K5:K21) -> 1188000 | N4: =SUMIF(C5:C21,"Mano de Obra",K5:K21) -> 227649.6 | O4: =SUMIF(C5:C21,"Subcontrato",K5:K21) -> 0 | P4: =SUMIF(C5:C21,"Ser&Arr",K5:K21) -> 45530.1 | Q4: =SUM(M4:P4) -> 1461179.7
C5: Material | D5: uni | E5: Malla Geotextil 2x50 | F5: =1/(2*50)*1.1 -> 0.011 | G5: 120000 | H5: =ROUND(F5*G5,3) -> 1320 | J5: =F5*$F$4 -> 9.9 | K5: =H5*$F$4 -> 1188000
C6: Mano de Obra | D6: hh | E6: Maestro | F6: =1/50 -> 0.02 | G6: =Maestro -> 7250 | H6: =ROUND(F6*G6,3) -> 145 | J6: =F6*$F$4 -> 18 | K6: =H6*$F$4 -> 130500
C7: Mano de Obra | D7: hh | E7: Jornal | F7: =1/50 -> 0.02 | G7: =Jornal -> 5397.2222 | H7: =ROUND(F7*G7,3) -> 107.944 | J7: =F7*$F$4 -> 18 | K7: =H7*$F$4 -> 97149.6
C8: Ser&Arr | D8: % | E8: Desgaste de Herramientas | F8: 0.2 | G8: =SUM(H6:H7) -> 252.944 | H8: =ROUND(F8*G8,3) -> 50.589 | J8: =F8*$F$4 -> 180 | K8: =H8*$F$4 -> 45530.1
E9: Total APU 3.5 | F9: =$F$4 -> 900 | G9: =SUM(H5:H8) -> 1623.533 | H9: =ROUND(F9*G9,3) -> 1461179.7 | K9: =SUM(K5:K8) -> 1461179.7

Sheet 4.1
B1: 02.- Presupuesto'!A1
B3: Código | C3: Recurso | D3: Unidad | E3: Descripción | F3: Cantidad | G3: Precio Unitario | H3: Total | M3: Mat | N3: MO | O3: SC | P3: Arr
B4: 4.1 | C4: Partida | D4: ='01.- Presupuesto'!F29 -> m | E4: ='01.- Presupuesto'!C29 -> Suministro de materiales y construcción de zanja de infiltración, incluye cubo dren | F4: ='01.- Presupuesto'!G29 -> 6.3 | G4: =G50 -> 315982.17 | H4: =H50 -> 1990687.6 | J4: Cantidad | K4: Costo | M4: =SUMIF(C5:C48,"Material",K5:K55) -> 680431.52 | N4: =SUMIF(C5:C48,"Mano de Obra",K5:K55) -> 241535.93 | O4: =SUMIF(C5:C48,"Subcontrato",K5:K55) -> 767550 | P4: =SUMIF(C5:C48,"Ser&Arr",K5:K55) -> 301170.2 | Q4: =SUM(M4:P4) -> 1990687.6
B5: 13.1 | C5: Partida | D5: ='13.1'!$D$4 -> m3 | E5: ='13.1'!$E$4 -> Suministro y colocación arena limpia compactada | F5: =((1.16*(0.3+0.425*2)*F4)-(F21*F4*0.425*0.38*0.79))/F4 -> 0.68594921 | G5: ='13.1'!$G$4 -> 34686.583 | H5: =H12 -> 23793.234
C6: Material | D6: m3 | E6: Arena | F6: 1.3 | G6: =Arena -> 24000 | H6: =ROUND(F6*G6,3) -> 31200 | J6: =F6*$F$5*$F$4 -> 5.617924 | K6: =J6*G6 -> 134830.18
C7: Mano de Obra | D7: hh | E7: Maestro | F7: =1/20 -> 0.05 | G7: =Maestro -> 7250 | H7: =ROUND(F7*G7,3) -> 362.5 | J7: =F7*$F$5*$F$4 -> 0.216074 | K7: =J7*G7 -> 1566.5365
C8: Mano de Obra | D8: hh | E8: Jornal | F8: =4*1/20 -> 0.2 | G8: =Jornal -> 5397.2222 | H8: =ROUND(F8*G8,3) -> 1079.444 | J8: =F8*$F$5*$F$4 -> 0.864296 | K8: =J8*G8 -> 4664.7976
C9: Ser&Arr | D9: % | E9: Desgaste de Herramientas | F9: 0.2 | G9: =SUM(H7:H8) -> 1441.944 | H9: =ROUND(F9*G9,3) -> 288.389 | J9: =F9*$F$5*$F$4 -> 0.864296 | K9: =J9*G9 -> 1246.2664
C10: Ser&Arr | D10: hm | E10: Retroexcavadora | F10: =1/20 -> 0.05 | G10: =Retroexcavadora -> 32000 | H10: =ROUND(F10*G10,3) -> 1600 | J10: =F10*$F$5*$F$4 -> 0.216074 | K10: =J10*G10 -> 6914.368
C11: Ser&Arr | D11: día | E11: Placa Compactadora | F11: =1/20/8 -> 0.00625 | G11: 25000 | H11: =ROUND(F11*G11,3) -> 156.25 | J11: =F11*$F$5*$F$4 -> 0.02700925 | K11: =J11*G11 -> 675.23125
E12: Total APU 13.1 | F12: =F5 -> 0.68594921 | G12: =SUM(H6:H11) -> 34686.583 | H12: =ROUND(F12*G12,3) -> 23793.234
B13: 13.2 | C13: Partida | D13: ='13.2'!$D$4 -> m3 | E13: ='13.2'!$E$4 -> Suministro y colocación gravilla (bajo tamiz 1") | F13: =1.16*0.2 -> 0.232 | G13: ='13.2'!$G$4 -> 37286.583 | H13: =H20 -> 8650.487
C14: Material | D14: m3 | E14: Gravilla | F14: 1.3 | G14: =Gravilla -> 26000 | H14: =ROUND(F14*G14,3) -> 33800 | J14: =F14*$F$13*$F$4 -> 1.90008 | K14: =J14*G14 -> 49402.08
C15: Mano de Obra | D15: hh | E15: Maestro | F15: =1/20 -> 0.05 | G15: =Maestro -> 7250 | H15: =ROUND(F15*G15,3) -> 362.5 | J15: =F15*$F$13*$F$4 -> 0.07308 | K15: =J15*G15 -> 529.83
C16: Mano de Obra | D16: hh | E16: Jornal | F16: =4*1/20 -> 0.2 | G16: =Jornal -> 5397.2222 | H16: =ROUND(F16*G16,3) -> 1079.444 | J16: =F16*$F$13*$F$4 -> 0.29232 | K16: =J16*G16 -> 1577.716
C17: Ser&Arr | D17: % | E17: Desgaste de Herramientas | F17: 0.2 | G17: =SUM(H15:H16) -> 1441.944 | H17: =ROUND(F17*G17,3) -> 288.389 | J17: =F17*$F$13*$F$4 -> 0.29232 | K17: =J17*G17 -> 421.50907
C18: Ser&Arr | D18: hm | E18: Retroexcavadora | F18: =1/20 -> 0.05 | G18: =Retroexcavadora -> 32000 | H18: =ROUND(F18*G18,3) -> 1600 | J18: =F18*$F$13*$F$4 -> 0.07308 | K18: =J18*G18 -> 2338.56
C19: Ser&Arr | D19: día | E19: Placa Compactadora | F19: =1/20/8 -> 0.00625 | G19: 25000 | H19: =ROUND(F19*G19,3) -> 156.25 | J19: =F19*$F$13*$F$4 -> 0.009135 | K19: =J19*G19 -> 228.375
E20: Total APU 13.2 | F20: =F13 -> 0.232 | G20: =SUM(H14:H19) -> 37286.583 | H20: =ROUND(F20*G20,3) -> 8650.487
B21: 13.3 | C21: Partida | D21: ='13.3'!$D$4 -> un | E21: ='13.3'!$E$4 -> Suministro e instalación Cubos dren 26 t/m2 | F21: =(4*ROUNDUP((F4/0.79),0))/F4 -> 5.0793651 | G21: ='13.3'!$G$4 -> 18599.722 | H21: =H25 -> 94474.778
C22: Material | D22: uni | E22: Cubo Drenaje INSYTEC Serie 3000 16/26T 0,425 x 0,38 x 0,79 m | F22: 1 | G22: =CuboDren -> 11390 | H22: =ROUND(F22*G22,3) -> 11390 | J22: =F22*$F$21*$F$4 -> 32 | K22: =J22*G22 -> 364480
C23: Mano de Obra | D23: hh | E23: Maestro | F23: =1/4 -> 0.25 | G23: =Maestro -> 7250 | H23: =ROUND(F23*G23,3) -> 1812.5 | J23: =F23*$F$21*$F$4 -> 8 | K23: =J23*G23 -> 58000
C24: Mano de Obra | D24: hh | E24: Jornal | F24: 1 | G24: =Jornal -> 5397.2222 | H24: =ROUND(F24*G24,3) -> 5397.222 | J24: =F24*$F$21*$F$4 -> 32 | K24: =J24*G24 -> 172711.11
E25: Total APU 13.3 | F25: =F21 -> 5.0793651 | G25: =SUM(H22:H24) -> 18599.722 | H25: =ROUND(F25*G25,3) -> 94474.778
B26: 13.4 | C26: Partida | D26: ='13.4'!$D$4 -> m3 | E26: ='13.4'!$E$4 -> Excavación máquinaria local, traslado a botadero hasta 20km (geométrica, sin esponajamiento) | F26: =((1.16*(0.3+0.425*2+0.4)*F4))/F4 -> 1.798 | G26: ='13.4'!$G$4 -> 25500 | H26: =H31 -> 45849
C27: Ser&Arr | D27: hm | E27: Excavadora | F27: =1/20 -> 0.05 | G27: =Excavadora -> 50000 | H27: =ROUND(F27*G27,3) -> 2500 | J27: =F27*$F$26*$F$4 -> 0.56637 | K27: =J27*G27 -> 28318.5
C28: Ser&Arr | D28: hm | E28: Retroexcavadora | F28: =1/20 -> 0.05 | G28: =Retroexcavadora -> 32000 | H28: =ROUND(F28*G28,3) -> 1600 | J28: =F28*$F$26*$F$4 -> 0.56637 | K28: =J28*G28 -> 18123.84
C29: Ser&Arr | D29: hm | E29: Camión Tolva | F29: =1/20 -> 0.05 | G29: =Tolva -> 38000 | H29: =ROUND(F29*G29,3) -> 1900 | J29: =F29*$F$26*$F$4 -> 0.56637 | K29: =J29*G29 -> 21522.06
C30: Ser&Arr | D30: m3 | E30: Carga y Retiro de Escombros | F30: 1.3 | G30: 15000 | H30: =ROUND(F30*G30,3) -> 19500 | J30: =F30*$F$26*$F$4 -> 14.72562 | K30: =J30*G30 -> 220884.3
E31: Total APU 13.4 | F31: =F26 -> 1.798 | G31: =SUM(H27:H30) -> 25500 | H31: =ROUND(F31*G31,3) -> 45849
B32: 13.5 | C32: Partida | D32: ='13.5'!$D$4 -> m | E32: ='13.5'!$E$4 -> Suministro e instalación PVC 110mm | F32: 6 | G32: ='13.5'!$G$4 -> 19571.289 | H32: =H35 -> 117427.73
C33: Material | D33: uni | E33: Tubería PVC 110 mm Sanitario | F33: =1.1*1/6 -> 0.18333333 | G33: =16690/1.19 -> 14025.21 | H33: =ROUND(F33*G33,3) -> 2571.289 | J33: =F33*F32*$F$4 -> 6.93 | K33: =J33*G33 -> 97194.706
C34: Subcontrato | D34: m | E34: SC Instalación Tuberías PVC | F34: 1 | G34: =SCSan -> 17000 | H34: =ROUND(F34*G34,3) -> 17000 | J34: =F34*F32*$F$4 -> 37.8 | K34: =J34*G34 -> 642600
E35: Total APU 13.5 | F35: =F32 -> 6 | G35: =SUM(H33:H34) -> 19571.289 | H35: =ROUND(F35*G35,3) -> 117427.73
B36: 13.6 | C36: Partida | D36: ='13.6'!$D$4 -> un | E36: ='13.6'!$E$4 -> Suministro e instalación códo de PVC 110mm | F36: 1 | G36: ='13.6'!$G$4 -> 2698.506 | H36: =H39 -> 3170.728
C37: Material | D37: uni | E37: Codo PVC 110 mm Sanitario | F37: =1.1*1/6 -> 0.18333333 | G37: =2190/1.19 -> 1840.3361 | H37: =ROUND(F37*G37,3) -> 337.395 | J37: =F37*F36*$F$4 -> 1.155 | K37: =J37*G37 -> 2125.5882
C38: Subcontrato | D38: m | E38: SC Instalación Tuberías PVC | F38: =F36/F32 -> 0.16666667 | G38: =SCSan -> 17000 | H38: =ROUND(F38*G38,3) -> 2833.333 | J38: =F38*F36*$F$4 -> 1.05 | K38: =J38*G38 -> 17850
E39: Total APU 13.6 | F39: =F36 -> 1 | G39: =SUM(H37:H38) -> 3170.728 | H39: =ROUND(F39*G39,3) -> 3170.728
B40: 13.7 | C40: Partida | D40: ='13.7'!$D$4 -> m2 | E40: ='13.7'!$E$4 -> Suministro e instalación de Geotextil | F40: =1.16+0.4 -> 1.56 | G40: ='13.7'!$G$4 -> 1623.533 | H40: =H45 -> 2532.711
C41: Material | D41: uni | E41: Malla Geotextil 2x50 | F41: =1/(2*50)*1.1 -> 0.011 | G41: 120000 | H41: =ROUND(F41*G41,3) -> 1320 | J41: =F41*$F$40*$F$4 -> 0.108108 | K41: =J41*G41 -> 12972.96
C42: Mano de Obra | D42: hh | E42: Maestro | F42: =1/50 -> 0.02 | G42: =Maestro -> 7250 | H42: =ROUND(F42*G42,3) -> 145 | J42: =F42*$F$40*$F$4 -> 0.19656 | K42: =J42*G42 -> 1425.06
C43: Mano de Obra | D43: hh | E43: Jornal | F43: =1/50 -> 0.02 | G43: =Jornal -> 5397.2222 | H43: =ROUND(F43*G43,3) -> 107.944 | J43: =F43*$F$40*$F$4 -> 0.19656 | K43: =J43*G43 -> 1060.878
C44: Ser&Arr | D44: % | E44: Desgaste de Herramientas | F44: 0.2 | G44: =SUM(H42:H43) -> 252.944 | H44: =ROUND(F44*G44,3) -> 50.589 | J44: =F44*$F$40*$F$4 -> 1.9656 | K44: =J44*G44 -> 497.18673
E45: Total APU 13.7 | F45: =F40 -> 1.56 | G45: =SUM(H41:H44) -> 1623.533 | H45: =ROUND(F45*G45,3) -> 2532.711
B46: 13.8 | C46: Partida | D46: ='13.8'!$D$4 -> m | E46: ='13.8'!$E$4 -> Suministro e instalación PVC110 mm ranurado | F46: 1 | G46: ='13.8'!$G$4 -> 20083.494 | H46: =H49 -> 20083.494
C47: Material | D47: uni | E47: Tubería Flexodren 110 | F47: =1.1*1/50 -> 0.022 | G47: =166789/1.19 -> 140158.82 | H47: =ROUND(F47*G47,3) -> 3083.494 | J47: =F47*$F$46*$F$4 -> 0.1386 | K47: =J47*G47 -> 19426.013
C48: Subcontrato | D48: m | E48: SC Instalación Tuberías PVC | F48: 1 | G48: =SCSan -> 17000 | H48: =ROUND(F48*G48,3) -> 17000 | J48: =F48*$F$46*$F$4 -> 6.3 | K48: =J48*G48 -> 107100
E49: Total APU 13.8 | F49: =F46 -> 1 | G49: =SUM(H47:H48) -> 20083.494 | H49: =ROUND(F49*G49,3) -> 20083.494
E50: Total APU 4.1 | F50: =$F$4 -> 6.3 | G50: =H45+H39+H35+H31+H25+H20+H12+H49 -> 315982.17 | H50: =ROUND(F50*G50,3) -> 1990687.6 | K50: =SUM(K5:K48) -> 1990687.6

Sheet 4.2
B1: 02.- Presupuesto'!A1
B3: Código | C3: Recurso | D3: Unidad | E3: Descripción | F3: Cantidad | G3: Precio Unitario | H3: Total | M3: Mat | N3: MO | O3: SC | P3: Arr
B4: 4.2 | C4: Partida | D4: ='01.- Presupuesto'!F30 -> un | E4: ='01.- Presupuesto'!C30 -> Suministro de materiales y construcción cámaras de filtración y decantación | F4: ='01.- Presupuesto'!G30 -> 1 | G4: =G21 -> 650632.39 | H4: =H21 -> 650632.39 | J4: Cantidad | K4: Costo | M4: =SUMIF(C5:C22,"Material",K5:K22) -> 424713.73 | N4: =SUMIF(C5:C22,"Mano de Obra",K5:K22) -> 144355.56 | O4: =SUMIF(C5:C22,"Subcontrato",K5:K22) -> 37692 | P4: =SUMIF(C5:C22,"Ser&Arr",K5:K22) -> 43871.111 | Q4: =SUM(M4:P4) -> 650632.39
C5: Material | D5: m3 | E5: Hormigón G20(10)20-8 | F5: =((4*1.15*1.15)+(1.3*1.3))*0.15 -> 1.047 | G5: =HormG20 -> 108376.92 | H5: =ROUND(F5*G5,3) -> 113470.63 | J5: =F5*$F$4 -> 1.047 | K5: =H5*$F$4 -> 113470.63
C6: Material | D6: m3 | E6: Carga Incompleta | F6: =6-F5 -> 4.953 | G6: 12000 | H6: =ROUND(F6*G6,3) -> 59436 | J6: =F6*$F$4 -> 4.953 | K6: =H6*$F$4 -> 59436
C7: Material | D7: Kg | E7: Acero A630-420H | F7: =F5*60 -> 62.82 | G7: 900 | H7: =ROUND(F7*G7,3) -> 56538 | J7: =F7*$F$4 -> 62.82 | K7: =H7*$F$4 -> 56538
C8: Material | D8: Kg | E8: Alambre Negro Recocido #18 | F8: =1/30*F7 -> 2.094 | G8: 1630 | H8: =ROUND(F8*G8,3) -> 3413.22 | J8: =F8*$F$4 -> 2.094 | K8: =H8*$F$4 -> 3413.22
C9: Material | D9: un | E9: Tapa diamantada galvanizada | F9: 1 | G9: =129998/1.19 -> 109242.02 | H9: =ROUND(F9*G9,3) -> 109242.02 | J9: =F9*$F$4 -> 1 | K9: =H9*$F$4 -> 109242.02
C10: Material | D10: uni | E10: Pino Verde 2x3" 3,2m | F10: =1/0.48*((4*1.15*1.15)+(1.3*1.3)) -> 14.541667 | G10: 2400 | H10: =ROUND(F10*G10,3) -> 34900 | J10: =F10*$F$4 -> 14.541667 | K10: =H10*$F$4 -> 34900
C11: Material | D11: uni | E11: Terciado Estructural 1,22x2,44m 15 mm | F11: =1.05*1/(1.22*2.44)*((4*1.15*1.15)+(1.3*1.3)) -> 2.4620398 | G11: 16966 | H11: =ROUND(F11*G11,3) -> 41770.967 | J11: =F11*$F$4 -> 2.4620398 | K11: =H11*$F$4 -> 41770.967
C12: Material | D12: kg | E12: Clavos CTE 1 1/2" | F12: =1/4*((4*1.15*1.15)+(1.3*1.3)) -> 1.745 | G12: 1184 | H12: =ROUND(F12*G12,3) -> 2066.08 | J12: =F12*$F$4 -> 1.745 | K12: =H12*$F$4 -> 2066.08
C13: Material | D13: uni | E13: Alambre Negro Recocido #14 25 Kg | F13: =1/72*((4*1.15*1.15)+(1.3*1.3)) -> 0.096944444 | G13: 39990 | H13: =ROUND(F13*G13,3) -> 3876.808 | J13: =F13*$F$4 -> 0.096944444 | K13: =H13*$F$4 -> 3876.808
C14: Mano de Obra | D14: hh | E14: Maestro | F14: 8 | G14: =Maestro -> 7250 | H14: =ROUND(F14*G14,3) -> 58000 | J14: =F14*$F$4 -> 8 | K14: =H14*$F$4 -> 58000
C15: Mano de Obra | D15: hh | E15: Jornal | F15: 16 | G15: =Jornal -> 5397.2222 | H15: =ROUND(F15*G15,3) -> 86355.556 | J15: =F15*$F$4 -> 16 | K15: =H15*$F$4 -> 86355.556
C16: Ser&Arr | D16: % | E16: Desgaste de Herramientas | F16: 0.2 | G16: =SUM(H14:H15) -> 144355.56 | H16: =ROUND(F16*G16,3) -> 28871.111 | J16: =F16*$F$4 -> 0.2 | K16: =H16*$F$4 -> 28871.111
C17: Subcontrato | D17: kg | E17: Enfierrador | F17: =F7 -> 62.82 | G17: =Enf -> 600 | H17: =ROUND(F17*G17,3) -> 37692 | J17: =F17*$F$4 -> 62.82 | K17: =H17*$F$4 -> 37692
C18: Ser&Arr | D18: día | E18: Sonda Vibradora + Motor Bencinero | F18: 1 | G18: =3500+3500 -> 7000 | H18: =ROUND(F18*G18,3) -> 7000 | J18: =F18*$F$4 -> 1 | K18: =H18*$F$4 -> 7000
C19: Ser&Arr | D19: día | E19: Sonda Vibradora + Motor Electrico | F19: 1 | G19: =3500+3500 -> 7000 | H19: =ROUND(F19*G19,3) -> 7000 | J19: =F19*$F$4 -> 1 | K19: =H19*$F$4 -> 7000
C20: Ser&Arr | D20: un | E20: Compresión Probetas Cilindricas | F20: =1/50 -> 0.02 | G20: 50000 | H20: =ROUND(F20*G20,3) -> 1000 | J20: =F20*$F$4 -> 0.02 | K20: =H20*$F$4 -> 1000
E21: Total APU 4.2 | F21: =$F$4 -> 1 | G21: =SUM(H5:H20) -> 650632.39 | H21: =ROUND(F21*G21,3) -> 650632.39 | K21: =SUM(K5:K20) -> 650632.39

Sheet 5.1
B1: 02.- Presupuesto'!A1
B3: Código | C3: Recurso | D3: Unidad | E3: Descripción | F3: Cantidad | G3: Precio Unitario | H3: Total | M3: Mat | N3: MO | O3: SC | P3: Arr
B4: 5.1 | C4: Partida | D4: ='01.- Presupuesto'!F32 -> m | E4: ='01.- Presupuesto'!C32 -> Suministro e instalación cierre perimetral tipo Bulldog | F4: ='01.- Presupuesto'!G32 -> 50 | G4: =G6 -> 30000 | H4: =H6 -> 1500000 | J4: Cantidad | K4: Costo | M4: =SUMIF(C5:C18,"Material",K5:K18) -> 0 | N4: =SUMIF(C5:C18,"Mano de Obra",K5:K18) -> 0 | O4: =SUMIF(C5:C18,"Subcontrato",K5:K18) -> 1500000 | P4: =SUMIF(C5:C18,"Ser&Arr",K5:K18) -> 0 | Q4: =SUM(M4:P4) -> 1500000
C5: Subcontrato | D5: m | E5: Subcontrato Suministro e Instalación Cierro tipo Bulldog | F5: 1 | G5: =SCBulldog -> 30000 | H5: =ROUND(F5*G5,3) -> 30000 | J5: =F5*$F$4 -> 50 | K5: =H5*$F$4 -> 1500000
E6: Total APU 5.1 | F6: =$F$4 -> 50 | G6: =SUM(H5:H5) -> 30000 | H6: =ROUND(F6*G6,3) -> 1500000 | K6: =SUM(K5:K5) -> 1500000

Sheet 5.2
B1: 02.- Presupuesto'!A1
B3: Código | C3: Recurso | D3: Unidad | E3: Descripción | F3: Cantidad | G3: Precio Unitario | H3: Total | M3: Mat | N3: MO | O3: SC | P3: Arr
B4: 5.2 | C4: Partida | D4: ='01.- Presupuesto'!F33 -> m | E4: ='01.- Presupuesto'!C33 -> Suministro e instalación cierre perimetral tipo Acmafor | F4: ='01.- Presupuesto'!G33 -> 280 | G4: =G6 -> 30550 | H4: =H6 -> 8554000 | J4: Cantidad | K4: Costo | M4: =SUMIF(C5:C18,"Material",K5:K18) -> 0 | N4: =SUMIF(C5:C18,"Mano de Obra",K5:K18) -> 0 | O4: =SUMIF(C5:C18,"Subcontrato",K5:K18) -> 8554000 | P4: =SUMIF(C5:C18,"Ser&Arr",K5:K18) -> 0 | Q4: =SUM(M4:P4) -> 8554000
C5: Subcontrato | D5: m | E5: Subcontrato Suministro e Instalación Cierro tipo Acmafor | F5: 1 | G5: =SCAcmafor -> 30550 | H5: =ROUND(F5*G5,3) -> 30550 | J5: =F5*$F$4 -> 280 | K5: =H5*$F$4 -> 8554000
E6: Total APU 5.2 | F6: =$F$4 -> 280 | G6: =SUM(H5:H5) -> 30550 | H6: =ROUND(F6*G6,3) -> 8554000 | K6: =SUM(K5:K5) -> 8554000

Sheet 5.3
B1: 02.- Presupuesto'!A1
B3: Código | C3: Recurso | D3: Unidad | E3: Descripción | F3: Cantidad | G3: Precio Unitario | H3: Total | M3: Mat | N3: MO | O3: SC | P3: Arr
B4: 5.3 | C4: Partida | D4: ='01.- Presupuesto'!F34 -> un | E4: ='01.- Presupuesto'!C34 -> Suministro e instalación portón metálico vehicular 5m | F4: ='01.- Presupuesto'!G34 -> 1 | G4: =G6 -> 1214017 | H4: =H6 -> 1214017 | J4: Cantidad | K4: Costo | M4: =SUMIF(C5:C18,"Material",K5:K18) -> 0 | N4: =SUMIF(C5:C18,"Mano de Obra",K5:K18) -> 0 | O4: =SUMIF(C5:C18,"Subcontrato",K5:K18) -> 1214017 | P4: =SUMIF(C5:C18,"Ser&Arr",K5:K18) -> 0 | Q4: =SUM(M4:P4) -> 1214017
C5: Subcontrato | D5: un | E5: SC Portón Acmafor Vehicular | F5: 1 | G5: 1214017 | H5: =ROUND(F5*G5,3) -> 1214017 | J5: =F5*$F$4 -> 1 | K5: =H5*$F$4 -> 1214017
E6: Total APU 5.3 | F6: =$F$4 -> 1 | G6: =SUM(H5:H5) -> 1214017 | H6: =ROUND(F6*G6,3) -> 1214017 | K6: =SUM(K5:K5) -> 1214017

Sheet 5.4
B1: 02.- Presupuesto'!A1
B3: Código | C3: Recurso | D3: Unidad | E3: Descripción | F3: Cantidad | G3: Precio Unitario | H3: Total | M3: Mat | N3: MO | O3: SC | P3: Arr
B4: 5.4 | C4: Partida | D4: ='01.- Presupuesto'!F35 -> un | E4: ='01.- Presupuesto'!C35 -> Suministro e instalación portón metálico peatonal 1m | F4: ='01.- Presupuesto'!G35 -> 1 | G4: =G6 -> 520466 | H4: =H6 -> 520466 | J4: Cantidad | K4: Costo | M4: =SUMIF(C5:C18,"Material",K5:K18) -> 0 | N4: =SUMIF(C5:C18,"Mano de Obra",K5:K18) -> 0 | O4: =SUMIF(C5:C18,"Subcontrato",K5:K18) -> 520466 | P4: =SUMIF(C5:C18,"Ser&Arr",K5:K18) -> 0 | Q4: =SUM(M4:P4) -> 520466
C5: Subcontrato | D5: Kg | E5: SC Portón Acmafor Peatonal | F5: 1 | G5: 520466 | H5: =ROUND(F5*G5,3) -> 520466 | J5: =F5*$F$4 -> 1 | K5: =H5*$F$4 -> 520466
E6: Total APU 5.4 | F6: =$F$4 -> 1 | G6: =SUM(H5:H5) -> 520466 | H6: =ROUND(F6*G6,3) -> 520466 | K6: =SUM(K5:K5) -> 520466

Sheet 6.1
B1: 02.- Presupuesto'!A1
B3: Código | C3: Recurso | D3: Unidad | E3: Descripción | F3: Cantidad | G3: Precio Unitario | H3: Total | M3: Mat | N3: MO | O3: SC | P3: Arr
B4: 6.1 | C4: Partida | D4: ='01.- Presupuesto'!F39 -> m3 | E4: ='01.- Presupuesto'!C39 -> Suministro e Instalación Hormigón G25(10)20-8 | F4: ='01.- Presupuesto'!G39 -> 36.75 | G4: =G13 -> 141504.27 | H4: =H13 -> 5200281.8 | J4: Cantidad | K4: Costo | M4: =SUMIF(C5:C25,"Material",K5:K25) -> 4568100.2 | N4: =SUMIF(C5:C25,"Mano de Obra",K5:K25) -> 353276.39 | O4: =SUMIF(C5:C25,"Subcontrato",K5:K25) -> 0 | P4: =SUMIF(C5:C25,"Ser&Arr",K5:K25) -> 278905.27 | Q4: =SUM(M4:P4) -> 5200281.8
C5: Material | D5: m3 | E5: Hormigón G25(10)20-8 | F5: 1.1 | G5: =HormG25 -> 111910.95 | H5: =ROUND(F5*G5,3) -> 123102.04 | J5: =F5*$F$4 -> 40.425 | K5: =H5*$F$4 -> 4524000.2
C6: Material | D6: m3 | E6: Carga Incompleta | F6: =0.1 -> 0.1 | G6: 12000 | H6: =ROUND(F6*G6,3) -> 1200 | J6: =F6*$F$4 -> 3.675 | K6: =H6*$F$4 -> 44100
C7: Mano de Obra | D7: hh | E7: Maestro | F7: =1/3 -> 0.33333333 | G7: =Maestro -> 7250 | H7: =ROUND(F7*G7,3) -> 2416.667 | J7: =F7*$F$4 -> 12.25 | K7: =H7*$F$4 -> 88812.512
C8: Mano de Obra | D8: hh | E8: Jornal | F8: =4*(1/3) -> 1.3333333 | G8: =Jornal -> 5397.2222 | H8: =ROUND(F8*G8,3) -> 7196.296 | J8: =F8*$F$4 -> 49 | K8: =H8*$F$4 -> 264463.88
C9: Ser&Arr | D9: % | E9: Desgaste de Herramientas | F9: 0.2 | G9: =SUM(H7:H8) -> 9612.963 | H9: =ROUND(F9*G9,3) -> 1922.593 | J9: =F9*$F$4 -> 7.35 | K9: =H9*$F$4 -> 70655.293
C10: Ser&Arr | D10: día | E10: Sonda Vibradora + Motor Bencinero | F10: =1/3 -> 0.33333333 | G10: =3500+3500 -> 7000 | H10: =ROUND(F10*G10,3) -> 2333.333 | J10: =F10*$F$4 -> 12.25 | K10: =H10*$F$4 -> 85749.988
C11: Ser&Arr | D11: día | E11: Sonda Vibradora + Motor Electrico | F11: =1/3 -> 0.33333333 | G11: =3500+3500 -> 7000 | H11: =ROUND(F11*G11,3) -> 2333.333 | J11: =F11*$F$4 -> 12.25 | K11: =H11*$F$4 -> 85749.988
C12: Ser&Arr | D12: un | E12: Compresión Probetas Cilindricas | F12: =1/50 -> 0.02 | G12: 50000 | H12: =ROUND(F12*G12,3) -> 1000 | J12: =F12*$F$4 -> 0.735 | K12: =H12*$F$4 -> 36750
E13: Total APU 6.1 | F13: =$F$4 -> 36.75 | G13: =SUM(H5:H12) -> 141504.27 | H13: =ROUND(F13*G13,3) -> 5200281.8 | K13: =SUM(K5:K12) -> 5200281.8

Sheet 6.2
B1: 02.- Presupuesto'!A1
B3: Código | C3: Recurso | D3: Unidad | E3: Descripción | F3: Cantidad | G3: Precio Unitario | H3: Total | M3: Mat | N3: MO | O3: SC | P3: Arr
B4: 6.2 | C4: Partida | D4: ='01.- Presupuesto'!F40 -> m3 | E4: ='01.- Presupuesto'!C40 -> Suministro e instalación emplantillado hormigón G5 | F4: ='01.- Presupuesto'!G40 -> 5.25 | G4: =G10 -> 120719.81 | H4: =H10 -> 633778.98 | J4: Cantidad | K4: Costo | M4: =SUMIF(C5:C22,"Material",K5:K22) -> 573217.31 | N4: =SUMIF(C5:C22,"Mano de Obra",K5:K22) -> 50468.056 | O4: =SUMIF(C5:C22,"Subcontrato",K5:K22) -> 0 | P4: =SUMIF(C5:C22,"Ser&Arr",K5:K22) -> 10093.613 | Q4: =SUM(M4:P4) -> 633778.98
C5: Material | D5: m3 | E5: Hormigón G5 | F5: 1.1 | G5: =HormG5 -> 98167.5 | H5: =ROUND(F5*G5,3) -> 107984.25 | J5: =F5*$F$4 -> 5.775 | K5: =H5*$F$4 -> 566917.31
C6: Material | D6: m3 | E6: Carga Incompleta | F6: =0.1 -> 0.1 | G6: 12000 | H6: =ROUND(F6*G6,3) -> 1200 | J6: =F6*$F$4 -> 0.525 | K6: =H6*$F$4 -> 6300
C7: Mano de Obra | D7: hh | E7: Maestro | F7: =1/3 -> 0.33333333 | G7: =Maestro -> 7250 | H7: =ROUND(F7*G7,3) -> 2416.667 | J7: =F7*$F$4 -> 1.75 | K7: =H7*$F$4 -> 12687.502
C8: Mano de Obra | D8: hh | E8: Jornal | F8: =4*(1/3) -> 1.3333333 | G8: =Jornal -> 5397.2222 | H8: =ROUND(F8*G8,3) -> 7196.296 | J8: =F8*$F$4 -> 7 | K8: =H8*$F$4 -> 37780.554
C9: Ser&Arr | D9: % | E9: Desgaste de Herramientas | F9: 0.2 | G9: =SUM(H7:H8) -> 9612.963 | H9: =ROUND(F9*G9,3) -> 1922.593 | J9: =F9*$F$4 -> 1.05 | K9: =H9*$F$4 -> 10093.613
E10: Total APU 6.2 | F10: =$F$4 -> 5.25 | G10: =SUM(H5:H9) -> 120719.81 | H10: =ROUND(F10*G10,3) -> 633778.98 | K10: =SUM(K5:K9) -> 633778.98

Sheet 6.3
B1: 02.- Presupuesto'!A1
B3: Código | C3: Recurso | D3: Unidad | E3: Descripción | F3: Cantidad | G3: Precio Unitario | H3: Total | M3: Mat | N3: MO | O3: SC | P3: Arr
B4: 6.3 | C4: Partida | D4: ='01.- Presupuesto'!F41 -> m3 | E4: ='01.- Presupuesto'!C41 -> Suministro e Instalación relleno estructural compactado al 95% DMSC | F4: ='01.- Presupuesto'!G41 -> 199.5 | G4: =G13 -> 31578.854 | H4: =H13 -> 6299981.4 | J4: Cantidad | K4: Costo | M4: =SUMIF(C5:C25,"Material",K5:K25) -> 5187000 | N4: =SUMIF(C5:C25,"Mano de Obra",K5:K25) -> 287667.83 | O4: =SUMIF(C5:C25,"Subcontrato",K5:K25) -> 0 | P4: =SUMIF(C5:C25,"Ser&Arr",K5:K25) -> 825313.54 | Q4: =SUM(M4:P4) -> 6299981.4
C5: Material | D5: m3 | E5: Base Granular CBR >50% | F5: 1.3 | G5: =Base50 -> 20000 | H5: =ROUND(F5*G5,3) -> 26000 | J5: =F5*$F$4 -> 259.35 | K5: =H5*$F$4 -> 5187000
C6: Mano de Obra | D6: hh | E6: Maestro | F6: =1/20 -> 0.05 | G6: =Maestro -> 7250 | H6: =ROUND(F6*G6,3) -> 362.5 | J6: =F6*$F$4 -> 9.975 | K6: =H6*$F$4 -> 72318.75
C7: Mano de Obra | D7: hh | E7: Jornal | F7: =4*1/20 -> 0.2 | G7: =Jornal -> 5397.2222 | H7: =ROUND(F7*G7,3) -> 1079.444 | J7: =F7*$F$4 -> 39.9 | K7: =H7*$F$4 -> 215349.08
C8: Ser&Arr | D8: % | E8: Desgaste de Herramientas | F8: 0.2 | G8: =SUM(H6:H7) -> 1441.944 | H8: =ROUND(F8*G8,3) -> 288.389 | J8: =F8*$F$4 -> 39.9 | K8: =H8*$F$4 -> 57533.606
C9: Ser&Arr | D9: hm | E9: Retroexcavadora | F9: =1/20 -> 0.05 | G9: =Retroexcavadora -> 32000 | H9: =ROUND(F9*G9,3) -> 1600 | J9: =F9*$F$4 -> 9.975 | K9: =H9*$F$4 -> 319200
C10: Ser&Arr | D10: día | E10: Placa Compactadora | F10: =1/20/8 -> 0.00625 | G10: 25000 | H10: =ROUND(F10*G10,3) -> 156.25 | J10: =F10*$F$4 -> 1.246875 | K10: =H10*$F$4 -> 31171.875
C11: Ser&Arr | D11: un | E11: Ensayo Granulometría | F11: =1/F4 -> 0.0050125313 | G11: =(0.6+4.4)*UF -> 196335 | H11: =ROUND(F11*G11,3) -> 984.135 | J11: =F11*$F$4 -> 1 | K11: =H11*$F$4 -> 196334.93
C12: Ser&Arr | D12: un | E12: Ensayo Densidad In Situ | F12: =3/F4 -> 0.015037594 | G12: =(0.41+4.4/3)*UF -> 73691.07 | H12: =ROUND(F12*G12,3) -> 1108.136 | J12: =F12*$F$4 -> 3 | K12: =H12*$F$4 -> 221073.13
E13: Total APU 6.3 | F13: =$F$4 -> 199.5 | G13: =SUM(H5:H12) -> 31578.854 | H13: =ROUND(F13*G13,3) -> 6299981.4 | K13: =SUM(K5:K12) -> 6299981.4

Sheet 6.4
B1: 02.- Presupuesto'!A1
B3: Código | C3: Recurso | D3: Unidad | E3: Descripción | F3: Cantidad | G3: Precio Unitario | H3: Total | M3: Mat | N3: MO | O3: SC | P3: Arr
B4: 6.4 | C4: Partida | D4: ='01.- Presupuesto'!F42 -> m3 | E4: ='01.- Presupuesto'!C42 -> Excavación maquinaría local y traslado a botadero, hasta 20 Km | F4: ='01.- Presupuesto'!G42 -> 246.75 | G4: =G9 -> 25500 | H4: =H9 -> 6292125 | J4: Cantidad | K4: Costo | M4: =SUMIF(C5:C21,"Material",K5:K21) -> 0 | N4: =SUMIF(C5:C21,"Mano de Obra",K5:K21) -> 0 | O4: =SUMIF(C5:C21,"Subcontrato",K5:K21) -> 0 | P4: =SUMIF(C5:C21,"Ser&Arr",K5:K21) -> 6292125 | Q4: =SUM(M4:P4) -> 6292125
C5: Ser&Arr | D5: hm | E5: Excavadora | F5: =1/20 -> 0.05 | G5: =Excavadora -> 50000 | H5: =ROUND(F5*G5,3) -> 2500 | J5: =F5*$F$4 -> 12.3375 | K5: =H5*$F$4 -> 616875
C6: Ser&Arr | D6: hm | E6: Retroexcavadora | F6: =1/20 -> 0.05 | G6: =Retroexcavadora -> 32000 | H6: =ROUND(F6*G6,3) -> 1600 | J6: =F6*$F$4 -> 12.3375 | K6: =H6*$F$4 -> 394800
C7: Ser&Arr | D7: hm | E7: Camión Tolva | F7: =1/20 -> 0.05 | G7: =Tolva -> 38000 | H7: =ROUND(F7*G7,3) -> 1900 | J7: =F7*$F$4 -> 12.3375 | K7: =H7*$F$4 -> 468825
C8: Ser&Arr | D8: m3 | E8: Carga y Retiro de Escombros | F8: 1.3 | G8: 15000 | H8: =ROUND(F8*G8,3) -> 19500 | J8: =F8*$F$4 -> 320.775 | K8: =H8*$F$4 -> 4811625
E9: Total APU 6.4 | F9: =$F$4 -> 246.75 | G9: =SUM(H5:H8) -> 25500 | H9: =ROUND(F9*G9,3) -> 6292125 | K9: =SUM(K5:K8) -> 6292125

Sheet 6.5
B1: 02.- Presupuesto'!A1
B3: Código | C3: Recurso | D3: Unidad | E3: Descripción | F3: Cantidad | G3: Precio Unitario | H3: Total | M3: Mat | N3: MO | O3: SC | P3: Arr
B4: 6.5 | C4: Partida | D4: ='01.- Presupuesto'!F43 -> m2 | E4: ='01.- Presupuesto'!C43 -> Suministro y construcción moldajes de madera o metálicos | F4: ='01.- Presupuesto'!G43 -> 35 | G4: =G12 -> 16475.796 | H4: =H12 -> 576652.86 | J4: Cantidad | K4: Costo | M4: =SUMIF(C5:C24,"Material",K5:K24) -> 414252.86 | N4: =SUMIF(C5:C24,"Mano de Obra",K5:K24) -> 135333.35 | O4: =SUMIF(C5:C24,"Subcontrato",K5:K24) -> 0 | P4: =SUMIF(C5:C24,"Ser&Arr",K5:K24) -> 27066.655 | Q4: =SUM(M4:P4) -> 576652.86
C5: Material | D5: uni | E5: Pino Verde 2x3" 3,2m | F5: =1/0.48 -> 2.0833333 | G5: 2400 | H5: =ROUND(F5*G5,3) -> 5000 | J5: =F5*$F$4 -> 72.916667 | K5: =H5*$F$4 -> 175000
C6: Material | D6: uni | E6: Terciado Estructural 1,22x2,44m 15 mm | F6: =1.05*1/(1.22*2.44) -> 0.35272776 | G6: 16966 | H6: =ROUND(F6*G6,3) -> 5984.379 | J6: =F6*$F$4 -> 12.345472 | K6: =H6*$F$4 -> 209453.26
C7: Material | D7: kg | E7: Clavos CTE 1 1/2" | F7: =1/4 -> 0.25 | G7: 1184 | H7: =ROUND(F7*G7,3) -> 296 | J7: =F7*$F$4 -> 8.75 | K7: =H7*$F$4 -> 10360
C8: Material | D8: uni | E8: Alambre Negro Recocido #14 25 Kg | F8: =1/72 -> 0.013888889 | G8: 39990 | H8: =ROUND(F8*G8,3) -> 555.417 | J8: =F8*$F$4 -> 0.48611111 | K8: =H8*$F$4 -> 19439.595
C9: Mano de Obra | D9: hh | E9: Maestro | F9: =0.3 -> 0.3 | G9: =Maestro -> 7250 | H9: =ROUND(F9*G9,3) -> 2175 | J9: =F9*$F$4 -> 10.5 | K9: =H9*$F$4 -> 76125
C10: Mano de Obra | D10: hh | E10: Ayudante | F10: =0.3 -> 0.3 | G10: =Ayudante -> 5638.8889 | H10: =ROUND(F10*G10,3) -> 1691.667 | J10: =F10*$F$4 -> 10.5 | K10: =H10*$F$4 -> 59208.345
C11: Ser&Arr | D11: % | E11: Desgaste de Herramientas | F11: 0.2 | G11: =SUM(H9:H10) -> 3866.667 | H11: =ROUND(F11*G11,3) -> 773.333 | J11: =F11*$F$4 -> 7 | K11: =H11*$F$4 -> 27066.655
E12: Total APU 6.5 | F12: =$F$4 -> 35 | G12: =SUM(H5:H11) -> 16475.796 | H12: =ROUND(F12*G12,3) -> 576652.86 | K12: =SUM(K5:K11) -> 576652.86

Sheet 6.6
B1: 02.- Presupuesto'!A1
B3: Código | C3: Recurso | D3: Unidad | E3: Descripción | F3: Cantidad | G3: Precio Unitario | H3: Total | M3: Mat | N3: MO | O3: SC | P3: Arr
B4: 6.6 | C4: Partida | D4: ='01.- Presupuesto'!F44 -> kg | E4: ='01.- Presupuesto'!C44 -> Suministro e instalación armadura A630-420H, diámetro 12mm | F4: ='01.- Presupuesto'!G44 -> 1963.785 | G4: =G8 -> 1644.333 | H4: =H8 -> 3229116.5 | J4: Cantidad | K4: Costo | M4: =SUMIF(C5:C20,"Material",K5:K20) -> 2050845.5 | N4: =SUMIF(C5:C20,"Mano de Obra",K5:K20) -> 0 | O4: =SUMIF(C5:C20,"Subcontrato",K5:K20) -> 1178271 | P4: =SUMIF(C5:C20,"Ser&Arr",K5:K20) -> 0 | Q4: =SUM(M4:P4) -> 3229116.5
C5: Material | D5: Kg | E5: Acero A630-420H | F5: 1.1 | G5: 900 | H5: =ROUND(F5*G5,3) -> 990 | J5: =F5*$F$4 -> 2160.1635 | K5: =H5*$F$4 -> 1944147.1
C6: Material | D6: Kg | E6: Alambre Negro Recocido #18 | F6: =1/30 -> 0.033333333 | G6: 1630 | H6: =ROUND(F6*G6,3) -> 54.333 | J6: =F6*$F$4 -> 65.4595 | K6: =H6*$F$4 -> 106698.33
C7: Subcontrato | D7: Kg | E7: Enfierrador | F7: 1 | G7: =Enf -> 600 | H7: =ROUND(F7*G7,3) -> 600 | J7: =F7*$F$4 -> 1963.785 | K7: =H7*$F$4 -> 1178271
E8: Total APU 6.6 | F8: =$F$4 -> 1963.785 | G8: =SUM(H5:H7) -> 1644.333 | H8: =ROUND(F8*G8,3) -> 3229116.5 | K8: =SUM(K5:K7) -> 3229116.5

Sheet 6.7
B1: 02.- Presupuesto'!A1
B3: Código | C3: Recurso | D3: Unidad | E3: Descripción | F3: Cantidad | G3: Precio Unitario | H3: Total | M3: Mat | N3: MO | O3: SC | P3: Arr
B4: 6.7 | C4: Partida | D4: ='01.- Presupuesto'!F45 -> un | E4: ='01.- Presupuesto'!C45 -> Suministro e instalación de pernos de anclaje químico | F4: ='01.- Presupuesto'!G45 -> 280 | G4: =G9 -> 11342.214 | H4: =H9 -> 3175819.9 | J4: Cantidad | K4: Costo | M4: =SUMIF(C5:C21,"Material",K5:K21) -> 2769819.9 | N4: =SUMIF(C5:C21,"Mano de Obra",K5:K21) -> 338333.24 | O4: =SUMIF(C5:C21,"Subcontrato",K5:K21) -> 0 | P4: =SUMIF(C5:C21,"Ser&Arr",K5:K21) -> 67666.76 | Q4: =SUM(M4:P4) -> 3175819.9
C5: Material | D5: uni | E5: Perno Anclaje 3/4" | F5: 1 | G5: 9600 | H5: =ROUND(F5*G5,3) -> 9600 | J5: =F5*$F$4 -> 280 | K5: =H5*$F$4 -> 2688000
C6: Material | D6: uni | E6: Adhesivo Anclaje Químico | F6: =1.1*1/49 -> 0.02244898 | G6: =15490/1.19 -> 13016.807 | H6: =ROUND(F6*G6,3) -> 292.214 | J6: =F6*$F$4 -> 6.2857143 | K6: =H6*$F$4 -> 81819.92
C7: Mano de Obra | D7: hh | E7: Maestro | F7: =1/6 -> 0.16666667 | G7: =Maestro -> 7250 | H7: =ROUND(F7*G7,3) -> 1208.333 | J7: =F7*$F$4 -> 46.666667 | K7: =H7*$F$4 -> 338333.24
C8: Ser&Arr | D8: % | E8: Desgaste de Herramientas | F8: 0.2 | G8: =SUM(H7:H7) -> 1208.333 | H8: =ROUND(F8*G8,3) -> 241.667 | J8: =F8*$F$4 -> 56 | K8: =H8*$F$4 -> 67666.76
E9: Total APU 6.7 | F9: =$F$4 -> 280 | G9: =SUM(H5:H8) -> 11342.214 | H9: =ROUND(F9*G9,3) -> 3175819.9 | K9: =SUM(K5:K8) -> 3175819.9

Sheet 7.1
B1: 02.- Presupuesto'!A1
B3: Código | C3: Recurso | D3: Unidad | E3: Descripción | F3: Cantidad | G3: Precio Unitario | H3: Total | M3: Mat | N3: MO | O3: SC | P3: Arr
B4: 7.1 | C4: Partida | D4: ='01.- Presupuesto'!F47 -> m3 | E4: ='01.- Presupuesto'!C47 -> Suministro e Instalación Hormigón G20(10)20-8 | F4: ='01.- Presupuesto'!G47 -> 20 | G4: =G13 -> 137616.83 | H4: =H13 -> 2752336.7 | J4: Cantidad | K4: Costo | M4: =SUMIF(C5:C25,"Material",K5:K25) -> 2408292.2 | N4: =SUMIF(C5:C25,"Mano de Obra",K5:K25) -> 192259.26 | O4: =SUMIF(C5:C25,"Subcontrato",K5:K25) -> 0 | P4: =SUMIF(C5:C25,"Ser&Arr",K5:K25) -> 151785.18 | Q4: =SUM(M4:P4) -> 2752336.7
C5: Material | D5: m3 | E5: Hormigón G20(10)20-8 | F5: 1.1 | G5: =HormG20 -> 108376.92 | H5: =ROUND(F5*G5,3) -> 119214.61 | J5: =F5*$F$4 -> 22 | K5: =H5*$F$4 -> 2384292.2
C6: Material | D6: m3 | E6: Carga Incompleta | F6: =0.1 -> 0.1 | G6: 12000 | H6: =ROUND(F6*G6,3) -> 1200 | J6: =F6*$F$4 -> 2 | K6: =H6*$F$4 -> 24000
C7: Mano de Obra | D7: hh | E7: Maestro | F7: =1/3 -> 0.33333333 | G7: =Maestro -> 7250 | H7: =ROUND(F7*G7,3) -> 2416.667 | J7: =F7*$F$4 -> 6.6666667 | K7: =H7*$F$4 -> 48333.34
C8: Mano de Obra | D8: hh | E8: Jornal | F8: =4*(1/3) -> 1.3333333 | G8: =Jornal -> 5397.2222 | H8: =ROUND(F8*G8,3) -> 7196.296 | J8: =F8*$F$4 -> 26.666667 | K8: =H8*$F$4 -> 143925.92
C9: Ser&Arr | D9: % | E9: Desgaste de Herramientas | F9: 0.2 | G9: =SUM(H7:H8) -> 9612.963 | H9: =ROUND(F9*G9,3) -> 1922.593 | J9: =F9*$F$4 -> 4 | K9: =H9*$F$4 -> 38451.86
C10: Ser&Arr | D10: día | E10: Sonda Vibradora + Motor Bencinero | F10: =1/3 -> 0.33333333 | G10: =3500+3500 -> 7000 | H10: =ROUND(F10*G10,3) -> 2333.333 | J10: =F10*$F$4 -> 6.6666667 | K10: =H10*$F$4 -> 46666.66
C11: Ser&Arr | D11: día | E11: Sonda Vibradora + Motor Electrico | F11: =1/3 -> 0.33333333 | G11: =3500+3500 -> 7000 | H11: =ROUND(F11*G11,3) -> 2333.333 | J11: =F11*$F$4 -> 6.6666667 | K11: =H11*$F$4 -> 46666.66
C12: Ser&Arr | D12: un | E12: Compresión Probetas Cilindricas | F12: =1/50 -> 0.02 | G12: 50000 | H12: =ROUND(F12*G12,3) -> 1000 | J12: =F12*$F$4 -> 0.4 | K12: =H12*$F$4 -> 20000
E13: Total APU 7.1 | F13: =$F$4 -> 20 | G13: =SUM(H5:H12) -> 137616.83 | H13: =ROUND(F13*G13,3) -> 2752336.7 | K13: =SUM(K5:K12) -> 2752336.7

Sheet 7.2
B1: 02.- Presupuesto'!A1
B3: Código | C3: Recurso | D3: Unidad | E3: Descripción | F3: Cantidad | G3: Precio Unitario | H3: Total | M3: Mat | N3: MO | O3: SC | P3: Arr
B4: 7.2 | C4: Partida | D4: ='01.- Presupuesto'!F48 -> m3 | E4: ='01.- Presupuesto'!C48 -> Suministro e instalación emplantillado hormigón G5 | F4: ='01.- Presupuesto'!G48 -> 2.5 | G4: =G10 -> 120719.81 | H4: =H10 -> 301799.52 | J4: Cantidad | K4: Costo | M4: =SUMIF(C5:C22,"Material",K5:K22) -> 272960.62 | N4: =SUMIF(C5:C22,"Mano de Obra",K5:K22) -> 24032.408 | O4: =SUMIF(C5:C22,"Subcontrato",K5:K22) -> 0 | P4: =SUMIF(C5:C22,"Ser&Arr",K5:K22) -> 4806.4825 | Q4: =SUM(M4:P4) -> 301799.51
C5: Material | D5: m3 | E5: Hormigón G5 | F5: 1.1 | G5: =HormG5 -> 98167.5 | H5: =ROUND(F5*G5,3) -> 107984.25 | J5: =F5*$F$4 -> 2.75 | K5: =H5*$F$4 -> 269960.62
C6: Material | D6: m3 | E6: Carga Incompleta | F6: =0.1 -> 0.1 | G6: 12000 | H6: =ROUND(F6*G6,3) -> 1200 | J6: =F6*$F$4 -> 0.25 | K6: =H6*$F$4 -> 3000
C7: Mano de Obra | D7: hh | E7: Maestro | F7: =1/3 -> 0.33333333 | G7: =Maestro -> 7250 | H7: =ROUND(F7*G7,3) -> 2416.667 | J7: =F7*$F$4 -> 0.83333333 | K7: =H7*$F$4 -> 6041.6675
C8: Mano de Obra | D8: hh | E8: Jornal | F8: =4*(1/3) -> 1.3333333 | G8: =Jornal -> 5397.2222 | H8: =ROUND(F8*G8,3) -> 7196.296 | J8: =F8*$F$4 -> 3.3333333 | K8: =H8*$F$4 -> 17990.74
C9: Ser&Arr | D9: % | E9: Desgaste de Herramientas | F9: 0.2 | G9: =SUM(H7:H8) -> 9612.963 | H9: =ROUND(F9*G9,3) -> 1922.593 | J9: =F9*$F$4 -> 0.5 | K9: =H9*$F$4 -> 4806.4825
E10: Total APU 7.2 | F10: =$F$4 -> 2.5 | G10: =SUM(H5:H9) -> 120719.81 | H10: =ROUND(F10*G10,3) -> 301799.52 | K10: =SUM(K5:K9) -> 301799.51

Sheet 7.8
B1: 02.- Presupuesto'!A1
B3: Código | C3: Recurso | D3: Unidad | E3: Descripción | F3: Cantidad | G3: Precio Unitario | H3: Total | M3: Mat | N3: MO | O3: SC | P3: Arr
B4: 7.8 | C4: Partida | D4: ='01.- Presupuesto'!F54 -> kg | E4: ='01.- Presupuesto'!C54 -> Suministro e instalación enfierradura malla acma C-188 | F4: ='01.- Presupuesto'!G54 -> 180 | G4: =G9 -> 2586.773 | H4: =H9 -> 465619.14 | J4: Cantidad | K4: Costo | M4: =SUMIF(C5:C21,"Material",K5:K21) -> 257979.06 | N4: =SUMIF(C5:C21,"Mano de Obra",K5:K21) -> 173033.46 | O4: =SUMIF(C5:C21,"Subcontrato",K5:K21) -> 0 | P4: =SUMIF(C5:C21,"Ser&Arr",K5:K21) -> 34606.62 | Q4: =SUM(M4:P4) -> 465619.14
C5: Material | D5: uni | E5: Malla Acma C-188 | F5: =1.05*1/30.03 -> 0.034965035 | G5: 40990 | H5: =ROUND(F5*G5,3) -> 1433.217 | J5: =F5*$F$4 -> 6.2937063 | K5: =H5*$F$4 -> 257979.06
C6: Mano de Obra | D6: hh | E6: Maestro | F6: =1/30 -> 0.033333333 | G6: =Maestro -> 7250 | H6: =ROUND(F6*G6,3) -> 241.667 | J6: =F6*$F$4 -> 6 | K6: =H6*$F$4 -> 43500.06
C7: Mano de Obra | D7: hh | E7: Jornal | F7: =4/30 -> 0.13333333 | G7: =Jornal -> 5397.2222 | H7: =ROUND(F7*G7,3) -> 719.63 | J7: =F7*$F$4 -> 24 | K7: =H7*$F$4 -> 129533.4
C8: Ser&Arr | D8: % | E8: Desgaste de Herramientas | F8: 0.2 | G8: =SUM(H6:H7) -> 961.297 | H8: =ROUND(F8*G8,3) -> 192.259 | J8: =F8*$F$4 -> 36 | K8: =H8*$F$4 -> 34606.62
E9: Total APU 7.8 | F9: =$F$4 -> 180 | G9: =SUM(H5:H8) -> 2586.773 | H9: =ROUND(F9*G9,3) -> 465619.14 | K9: =SUM(K5:K8) -> 465619.14

Sheet 7.3
B1: 02.- Presupuesto'!A1
B3: Código | C3: Recurso | D3: Unidad | E3: Descripción | F3: Cantidad | G3: Precio Unitario | H3: Total | M3: Mat | N3: MO | O3: SC | P3: Arr
B4: 7.3 | C4: Partida | D4: ='01.- Presupuesto'!F49 -> m3 | E4: ='01.- Presupuesto'!C49 -> Suministro e Instalación relleno estructural compactado al 95% DMSC | F4: ='01.- Presupuesto'!G49 -> 24.3775 | G4: =G13 -> 46609.266 | H4: =H13 -> 1136217.4 | J4: Cantidad | K4: Costo | M4: =SUMIF(C5:C25,"Material",K5:K25) -> 633815 | N4: =SUMIF(C5:C25,"Mano de Obra",K5:K25) -> 35150.99 | O4: =SUMIF(C5:C25,"Subcontrato",K5:K25) -> 0 | P4: =SUMIF(C5:C25,"Ser&Arr",K5:K25) -> 467251.39 | Q4: =SUM(M4:P4) -> 1136217.4
C5: Material | D5: m3 | E5: Base Granular CBR >50% | F5: 1.3 | G5: =Base50 -> 20000 | H5: =ROUND(F5*G5,3) -> 26000 | J5: =F5*$F$4 -> 31.69075 | K5: =H5*$F$4 -> 633815
C6: Mano de Obra | D6: hh | E6: Maestro | F6: =1/20 -> 0.05 | G6: =Maestro -> 7250 | H6: =ROUND(F6*G6,3) -> 362.5 | J6: =F6*$F$4 -> 1.218875 | K6: =H6*$F$4 -> 8836.8438
C7: Mano de Obra | D7: hh | E7: Jornal | F7: =4*1/20 -> 0.2 | G7: =Jornal -> 5397.2222 | H7: =ROUND(F7*G7,3) -> 1079.444 | J7: =F7*$F$4 -> 4.8755 | K7: =H7*$F$4 -> 26314.146
C8: Ser&Arr | D8: % | E8: Desgaste de Herramientas | F8: 0.2 | G8: =SUM(H6:H7) -> 1441.944 | H8: =ROUND(F8*G8,3) -> 288.389 | J8: =F8*$F$4 -> 4.8755 | K8: =H8*$F$4 -> 7030.2028
C9: Ser&Arr | D9: hm | E9: Retroexcavadora | F9: =1/20 -> 0.05 | G9: =Retroexcavadora -> 32000 | H9: =ROUND(F9*G9,3) -> 1600 | J9: =F9*$F$4 -> 1.218875 | K9: =H9*$F$4 -> 39004
C10: Ser&Arr | D10: día | E10: Placa Compactadora | F10: =1/20/8 -> 0.00625 | G10: 25000 | H10: =ROUND(F10*G10,3) -> 156.25 | J10: =F10*$F$4 -> 0.15235938 | K10: =H10*$F$4 -> 3808.9844
C11: Ser&Arr | D11: un | E11: Ensayo Granulometría | F11: =1/F4 -> 0.041021434 | G11: =(0.6+4.4)*UF -> 196335 | H11: =ROUND(F11*G11,3) -> 8053.943 | J11: =F11*$F$4 -> 1 | K11: =H11*$F$4 -> 196335
C12: Ser&Arr | D12: un | E12: Ensayo Densidad In Situ | F12: =3/F4 -> 0.1230643 | G12: =(0.41+4.4/3)*UF -> 73691.07 | H12: =ROUND(F12*G12,3) -> 9068.74 | J12: =F12*$F$4 -> 3 | K12: =H12*$F$4 -> 221073.21
E13: Total APU 7.3 | F13: =$F$4 -> 24.3775 | G13: =SUM(H5:H12) -> 46609.266 | H13: =ROUND(F13*G13,3) -> 1136217.4 | K13: =SUM(K5:K12) -> 1136217.4

Sheet 7.4
B1: 02.- Presupuesto'!A1
B3: Código | C3: Recurso | D3: Unidad | E3: Descripción | F3: Cantidad | G3: Precio Unitario | H3: Total | M3: Mat | N3: MO | O3: SC | P3: Arr
B4: 7.4 | C4: Partida | D4: ='01.- Presupuesto'!F50 -> m3 | E4: ='01.- Presupuesto'!C50 -> Excavación maquinaría local y traslado a botadero, hasta 20 Km | F4: ='01.- Presupuesto'!G50 -> 48.05 | G4: =G9 -> 25500 | H4: =H9 -> 1225275 | J4: Cantidad | K4: Costo | M4: =SUMIF(C5:C21,"Material",K5:K21) -> 0 | N4: =SUMIF(C5:C21,"Mano de Obra",K5:K21) -> 0 | O4: =SUMIF(C5:C21,"Subcontrato",K5:K21) -> 0 | P4: =SUMIF(C5:C21,"Ser&Arr",K5:K21) -> 1225275 | Q4: =SUM(M4:P4) -> 1225275
C5: Ser&Arr | D5: hm | E5: Excavadora | F5: =1/20 -> 0.05 | G5: =Excavadora -> 50000 | H5: =ROUND(F5*G5,3) -> 2500 | J5: =F5*$F$4 -> 2.4025 | K5: =H5*$F$4 -> 120125
C6: Ser&Arr | D6: hm | E6: Retroexcavadora | F6: =1/20 -> 0.05 | G6: =Retroexcavadora -> 32000 | H6: =ROUND(F6*G6,3) -> 1600 | J6: =F6*$F$4 -> 2.4025 | K6: =H6*$F$4 -> 76880
C7: Ser&Arr | D7: hm | E7: Camión Tolva | F7: =1/20 -> 0.05 | G7: =Tolva -> 38000 | H7: =ROUND(F7*G7,3) -> 1900 | J7: =F7*$F$4 -> 2.4025 | K7: =H7*$F$4 -> 91295
C8: Ser&Arr | D8: m3 | E8: Carga y Retiro de Escombros | F8: 1.3 | G8: 15000 | H8: =ROUND(F8*G8,3) -> 19500 | J8: =F8*$F$4 -> 62.465 | K8: =H8*$F$4 -> 936975
E9: Total APU 7.4 | F9: =$F$4 -> 48.05 | G9: =SUM(H5:H8) -> 25500 | H9: =ROUND(F9*G9,3) -> 1225275 | K9: =SUM(K5:K8) -> 1225275

Sheet 7.5
B1: 02.- Presupuesto'!A1
B3: Código | C3: Recurso | D3: Unidad | E3: Descripción | F3: Cantidad | G3: Precio Unitario | H3: Total | M3: Mat | N3: MO | O3: SC | P3: Arr
B4: 7.5 | C4: Partida | D4: ='01.- Presupuesto'!F51 -> m2 | E4: ='01.- Presupuesto'!C51 -> Suministro y construcción moldajes de madera o metálicos | F4: ='01.- Presupuesto'!G51 -> 95 | G4: =G12 -> 16475.796 | H4: =H12 -> 1565200.6 | J4: Cantidad | K4: Costo | M4: =SUMIF(C5:C24,"Material",K5:K24) -> 1124400.6 | N4: =SUMIF(C5:C24,"Mano de Obra",K5:K24) -> 367333.36 | O4: =SUMIF(C5:C24,"Subcontrato",K5:K24) -> 0 | P4: =SUMIF(C5:C24,"Ser&Arr",K5:K24) -> 73466.635 | Q4: =SUM(M4:P4) -> 1565200.6
C5: Material | D5: uni | E5: Pino Verde 2x3" 3,2m | F5: =1/0.48 -> 2.0833333 | G5: 2400 | H5: =ROUND(F5*G5,3) -> 5000 | J5: =F5*$F$4 -> 197.91667 | K5: =H5*$F$4 -> 475000
C6: Material | D6: uni | E6: Terciado Estructural 1,22x2,44m 15 mm | F6: =1.05*1/(1.22*2.44) -> 0.35272776 | G6: 16966 | H6: =ROUND(F6*G6,3) -> 5984.379 | J6: =F6*$F$4 -> 33.509137 | K6: =H6*$F$4 -> 568516.01
C7: Material | D7: kg | E7: Clavos CTE 1 1/2" | F7: =1/4 -> 0.25 | G7: 1184 | H7: =ROUND(F7*G7,3) -> 296 | J7: =F7*$F$4 -> 23.75 | K7: =H7*$F$4 -> 28120
C8: Material | D8: uni | E8: Alambre Negro Recocido #14 25 Kg | F8: =1/72 -> 0.013888889 | G8: 39990 | H8: =ROUND(F8*G8,3) -> 555.417 | J8: =F8*$F$4 -> 1.3194444 | K8: =H8*$F$4 -> 52764.615
C9: Mano de Obra | D9: hh | E9: Maestro | F9: =0.3 -> 0.3 | G9: =Maestro -> 7250 | H9: =ROUND(F9*G9,3) -> 2175 | J9: =F9*$F$4 -> 28.5 | K9: =H9*$F$4 -> 206625
C10: Mano de Obra | D10: hh | E10: Ayudante | F10: =0.3 -> 0.3 | G10: =Ayudante -> 5638.8889 | H10: =ROUND(F10*G10,3) -> 1691.667 | J10: =F10*$F$4 -> 28.5 | K10: =H10*$F$4 -> 160708.36
C11: Ser&Arr | D11: % | E11: Desgaste de Herramientas | F11: 0.2 | G11: =SUM(H9:H10) -> 3866.667 | H11: =ROUND(F11*G11,3) -> 773.333 | J11: =F11*$F$4 -> 19 | K11: =H11*$F$4 -> 73466.635
E12: Total APU 7.5 | F12: =$F$4 -> 95 | G12: =SUM(H5:H11) -> 16475.796 | H12: =ROUND(F12*G12,3) -> 1565200.6 | K12: =SUM(K5:K11) -> 1565200.6

Sheet 7.6
B1: 02.- Presupuesto'!A1
B3: Código | C3: Recurso | D3: Unidad | E3: Descripción | F3: Cantidad | G3: Precio Unitario | H3: Total | M3: Mat | N3: MO | O3: SC | P3: Arr
B4: 7.6 | C4: Partida | D4: ='01.- Presupuesto'!F52 -> kg | E4: ='01.- Presupuesto'!C52 -> Suministro e instalación armadura A630-420H, diámetro 12mm | F4: ='01.- Presupuesto'!G52 -> 600 | G4: =G8 -> 1644.333 | H4: =H8 -> 986599.8 | J4: Cantidad | K4: Costo | M4: =SUMIF(C5:C20,"Material",K5:K20) -> 626599.8 | N4: =SUMIF(C5:C20,"Mano de Obra",K5:K20) -> 0 | O4: =SUMIF(C5:C20,"Subcontrato",K5:K20) -> 360000 | P4: =SUMIF(C5:C20,"Ser&Arr",K5:K20) -> 0 | Q4: =SUM(M4:P4) -> 986599.8
C5: Material | D5: Kg | E5: Acero A630-420H | F5: 1.1 | G5: 900 | H5: =ROUND(F5*G5,3) -> 990 | J5: =F5*$F$4 -> 660 | K5: =H5*$F$4 -> 594000
C6: Material | D6: Kg | E6: Alambre Negro Recocido #18 | F6: =1/30 -> 0.033333333 | G6: 1630 | H6: =ROUND(F6*G6,3) -> 54.333 | J6: =F6*$F$4 -> 20 | K6: =H6*$F$4 -> 32599.8
C7: Subcontrato | D7: Kg | E7: Enfierrador | F7: 1 | G7: =Enf -> 600 | H7: =ROUND(F7*G7,3) -> 600 | J7: =F7*$F$4 -> 600 | K7: =H7*$F$4 -> 360000
E8: Total APU 7.6 | F8: =$F$4 -> 600 | G8: =SUM(H5:H7) -> 1644.333 | H8: =ROUND(F8*G8,3) -> 986599.8 | K8: =SUM(K5:K7) -> 986599.8

Sheet 7.7
B1: 02.- Presupuesto'!A1
B3: Código | C3: Recurso | D3: Unidad | E3: Descripción | F3: Cantidad | G3: Precio Unitario | H3: Total | M3: Mat | N3: MO | O3: SC | P3: Arr
B4: 7.7 | C4: Partida | D4: ='01.- Presupuesto'!F53 -> un | E4: ='01.- Presupuesto'!C53 -> Suministro e instalación de pernos de anclaje químico | F4: ='01.- Presupuesto'!G53 -> 20 | G4: =G9 -> 11342.214 | H4: =H9 -> 226844.28 | J4: Cantidad | K4: Costo | M4: =SUMIF(C5:C21,"Material",K5:K21) -> 197844.28 | N4: =SUMIF(C5:C21,"Mano de Obra",K5:K21) -> 24166.66 | O4: =SUMIF(C5:C21,"Subcontrato",K5:K21) -> 0 | P4: =SUMIF(C5:C21,"Ser&Arr",K5:K21) -> 4833.34 | Q4: =SUM(M4:P4) -> 226844.28
C5: Material | D5: uni | E5: Perno Anclaje 3/4" | F5: 1 | G5: 9600 | H5: =ROUND(F5*G5,3) -> 9600 | J5: =F5*$F$4 -> 20 | K5: =H5*$F$4 -> 192000
C6: Material | D6: uni | E6: Adhesivo Anclaje Químico | F6: =1.1*1/49 -> 0.02244898 | G6: =15490/1.19 -> 13016.807 | H6: =ROUND(F6*G6,3) -> 292.214 | J6: =F6*$F$4 -> 0.44897959 | K6: =H6*$F$4 -> 5844.28
C7: Mano de Obra | D7: hh | E7: Maestro | F7: =1/6 -> 0.16666667 | G7: =Maestro -> 7250 | H7: =ROUND(F7*G7,3) -> 1208.333 | J7: =F7*$F$4 -> 3.3333333 | K7: =H7*$F$4 -> 24166.66
C8: Ser&Arr | D8: % | E8: Desgaste de Herramientas | F8: 0.2 | G8: =SUM(H7:H7) -> 1208.333 | H8: =ROUND(F8*G8,3) -> 241.667 | J8: =F8*$F$4 -> 4 | K8: =H8*$F$4 -> 4833.34
E9: Total APU 7.7 | F9: =$F$4 -> 20 | G9: =SUM(H5:H8) -> 11342.214 | H9: =ROUND(F9*G9,3) -> 226844.28 | K9: =SUM(K5:K8) -> 226844.28

Sheet 7.9
B1: 02.- Presupuesto'!A1
B3: Código | C3: Recurso | D3: Unidad | E3: Descripción | F3: Cantidad | G3: Precio Unitario | H3: Total | M3: Mat | N3: MO | O3: SC | P3: Arr
B4: 7.9 | C4: Partida | D4: ='01.- Presupuesto'!F55 -> m2 | E4: ='01.- Presupuesto'!C55 -> Suministro e instalación parrilla de piso Arriogoni ARS-3 | F4: ='01.- Presupuesto'!G55 -> 19 | G4: =G9 -> 85931.568 | H4: =H9 -> 1632699.8 | J4: Cantidad | K4: Costo | M4: =SUMIF(C5:C21,"Material",K5:K21) -> 863199.79 | N4: =SUMIF(C5:C21,"Mano de Obra",K5:K21) -> 0 | O4: =SUMIF(C5:C21,"Subcontrato",K5:K21) -> 769500 | P4: =SUMIF(C5:C21,"Ser&Arr",K5:K21) -> 0 | Q4: =SUM(M4:P4) -> 1632699.8
C5: Material | D5: uni | E5: Parrilla ARS-3 Negra 903x5800 | F5: =1.1*1/(5.8*0.903) -> 0.21002788 | G5: 195422 | H5: =ROUND(F5*G5,3) -> 41044.068 | J5: =F5*$F$4 -> 3.9905297 | K5: =H5*$F$4 -> 779837.29
C6: Material | D6: Kg | E6: Soldadura 6011 3/32 Punto azul | F6: =F8*0.03 -> 0.81 | G6: 2000 | H6: =ROUND(F6*G6,3) -> 1620 | J6: =F6*$F$4 -> 15.39 | K6: =H6*$F$4 -> 30780
C7: Material | D7: Kg | E7: Huaipe | F7: =F8*0.025 -> 0.675 | G7: 4100 | H7: =ROUND(F7*G7,3) -> 2767.5 | J7: =F7*$F$4 -> 12.825 | K7: =H7*$F$4 -> 52582.5
C8: Subcontrato | D8: Kg | E8: SC Perfilería Metálica | F8: 27 | G8: =Met -> 1500 | H8: =ROUND(F8*G8,3) -> 40500 | J8: =F8*$F$4 -> 513 | K8: =H8*$F$4 -> 769500
E9: Total APU 7.9 | F9: =$F$4 -> 19 | G9: =SUM(H5:H8) -> 85931.568 | H9: =ROUND(F9*G9,3) -> 1632699.8 | K9: =SUM(K5:K8) -> 1632699.8

Sheet 7.10
B1: 02.- Presupuesto'!A1
B3: Código | C3: Recurso | D3: Unidad | E3: Descripción | F3: Cantidad | G3: Precio Unitario | H3: Total | M3: Mat | N3: MO | O3: SC | P3: Arr
B4: 7.10 | C4: Partida | D4: ='01.- Presupuesto'!F56 -> m | E4: ='01.- Presupuesto'!C56 -> Suministro e instalación ángulo acero L30x3 | F4: ='01.- Presupuesto'!G56 -> 60 | G4: =G9 -> 4973.725 | H4: =H9 -> 298423.5 | J4: Cantidad | K4: Costo | M4: =SUMIF(C5:C21,"Material",K5:K21) -> 175573.5 | N4: =SUMIF(C5:C21,"Mano de Obra",K5:K21) -> 0 | O4: =SUMIF(C5:C21,"Subcontrato",K5:K21) -> 122850 | P4: =SUMIF(C5:C21,"Ser&Arr",K5:K21) -> 0 | Q4: =SUM(M4:P4) -> 298423.5
C5: Material | D5: uni | E5: Perfil Ángulo Laminado 30x30x3 mm 6m | F5: =1.05*(1/6) -> 0.175 | G5: =18390/1.19 -> 15453.782 | H5: =ROUND(F5*G5,3) -> 2704.412 | J5: =F5*$F$4 -> 10.5 | K5: =H5*$F$4 -> 162264.72
C6: Material | D6: Kg | E6: Soldadura 6011 3/32 Punto azul | F6: =F8*0.03 -> 0.04095 | G6: 2000 | H6: =ROUND(F6*G6,3) -> 81.9 | J6: =F6*$F$4 -> 2.457 | K6: =H6*$F$4 -> 4914
C7: Material | D7: Kg | E7: Huaipe | F7: =F8*0.025 -> 0.034125 | G7: 4100 | H7: =ROUND(F7*G7,3) -> 139.913 | J7: =F7*$F$4 -> 2.0475 | K7: =H7*$F$4 -> 8394.78
C8: Subcontrato | D8: Kg | E8: SC Perfilería Metálica | F8: =7.8*F5 -> 1.365 | G8: =Met -> 1500 | H8: =ROUND(F8*G8,3) -> 2047.5 | J8: =F8*$F$4 -> 81.9 | K8: =H8*$F$4 -> 122850
E9: Total APU 7.10 | F9: =$F$4 -> 60 | G9: =SUM(H5:H8) -> 4973.725 | H9: =ROUND(F9*G9,3) -> 298423.5 | K9: =SUM(K5:K8) -> 298423.5

Sheet 7.11
B1: 02.- Presupuesto'!A1
B3: Código | C3: Recurso | D3: Unidad | E3: Descripción | F3: Cantidad | G3: Precio Unitario | H3: Total | M3: Mat | N3: MO | O3: SC | P3: Arr
B4: 7.11 | C4: Partida | D4: ='01.- Presupuesto'!F57 -> m | E4: ='01.- Presupuesto'!C57 -> Suministro e instalación ángulo acero L50x5 | F4: ='01.- Presupuesto'!G57 -> 50 | G4: =G9 -> 12127.177 | H4: =H9 -> 606358.85 | J4: Cantidad | K4: Costo | M4: =SUMIF(C5:C21,"Material",K5:K21) -> 317936.95 | N4: =SUMIF(C5:C21,"Mano de Obra",K5:K21) -> 0 | O4: =SUMIF(C5:C21,"Subcontrato",K5:K21) -> 288421.9 | P4: =SUMIF(C5:C21,"Ser&Arr",K5:K21) -> 0 | Q4: =SUM(M4:P4) -> 606358.85
C5: Material | D5: uni | E5: Perfil Ángulo Laminado 50x50x5 mm 6m | F5: =1.05*(1/6) -> 0.175 | G5: =38990/1.19 -> 32764.706 | H5: =ROUND(F5*G5,3) -> 5733.824 | J5: =F5*$F$4 -> 8.75 | K5: =H5*$F$4 -> 286691.2
C6: Material | D6: Kg | E6: Soldadura 6011 3/32 Punto azul | F6: =F8*0.03 -> 0.11536875 | G6: 2000 | H6: =ROUND(F6*G6,3) -> 230.738 | J6: =F6*$F$4 -> 5.7684375 | K6: =H6*$F$4 -> 11536.9
C7: Material | D7: Kg | E7: Huaipe | F7: =F8*0.025 -> 0.096140625 | G7: 4100 | H7: =ROUND(F7*G7,3) -> 394.177 | J7: =F7*$F$4 -> 4.8070313 | K7: =H7*$F$4 -> 19708.85
C8: Subcontrato | D8: Kg | E8: SC Perfilería Metálica | F8: =21.975*F5 -> 3.845625 | G8: =Met -> 1500 | H8: =ROUND(F8*G8,3) -> 5768.438 | J8: =F8*$F$4 -> 192.28125 | K8: =H8*$F$4 -> 288421.9
E9: Total APU 7.11 | F9: =$F$4 -> 50 | G9: =SUM(H5:H8) -> 12127.177 | H9: =ROUND(F9*G9,3) -> 606358.85 | K9: =SUM(K5:K8) -> 606358.85

Sheet 8.1
B1: 02.- Presupuesto'!A1
B3: Código | C3: Recurso | D3: Unidad | E3: Descripción | F3: Cantidad | G3: Precio Unitario | H3: Total | M3: Mat | N3: MO | O3: SC | P3: Arr
B4: 8.1 | C4: Partida | D4: ='01.- Presupuesto'!F59 -> m3 | E4: ='01.- Presupuesto'!C59 -> Suministro e Instalación Hormigón G25(10)20-8 | F4: ='01.- Presupuesto'!G59 -> 5.916 | G4: =G13 -> 141504.27 | H4: =H13 -> 837139.24 | J4: Cantidad | K4: Costo | M4: =SUMIF(C5:C25,"Material",K5:K25) -> 735370.9 | N4: =SUMIF(C5:C25,"Mano de Obra",K5:K25) -> 56870.289 | O4: =SUMIF(C5:C25,"Subcontrato",K5:K25) -> 0 | P4: =SUMIF(C5:C25,"Ser&Arr",K5:K25) -> 44898.056 | Q4: =SUM(M4:P4) -> 837139.24
C5: Material | D5: m3 | E5: Hormigón G25(10)20-8 | F5: 1.1 | G5: =HormG25 -> 111910.95 | H5: =ROUND(F5*G5,3) -> 123102.04 | J5: =F5*$F$4 -> 6.5076 | K5: =H5*$F$4 -> 728271.7
C6: Material | D6: m3 | E6: Carga Incompleta | F6: =0.1 -> 0.1 | G6: 12000 | H6: =ROUND(F6*G6,3) -> 1200 | J6: =F6*$F$4 -> 0.5916 | K6: =H6*$F$4 -> 7099.2
C7: Mano de Obra | D7: hh | E7: Maestro | F7: =1/3 -> 0.33333333 | G7: =Maestro -> 7250 | H7: =ROUND(F7*G7,3) -> 2416.667 | J7: =F7*$F$4 -> 1.972 | K7: =H7*$F$4 -> 14297.002
C8: Mano de Obra | D8: hh | E8: Jornal | F8: =4*(1/3) -> 1.3333333 | G8: =Jornal -> 5397.2222 | H8: =ROUND(F8*G8,3) -> 7196.296 | J8: =F8*$F$4 -> 7.888 | K8: =H8*$F$4 -> 42573.287
C9: Ser&Arr | D9: % | E9: Desgaste de Herramientas | F9: 0.2 | G9: =SUM(H7:H8) -> 9612.963 | H9: =ROUND(F9*G9,3) -> 1922.593 | J9: =F9*$F$4 -> 1.1832 | K9: =H9*$F$4 -> 11374.06
C10: Ser&Arr | D10: día | E10: Sonda Vibradora + Motor Bencinero | F10: =1/3 -> 0.33333333 | G10: =3500+3500 -> 7000 | H10: =ROUND(F10*G10,3) -> 2333.333 | J10: =F10*$F$4 -> 1.972 | K10: =H10*$F$4 -> 13803.998
C11: Ser&Arr | D11: día | E11: Sonda Vibradora + Motor Electrico | F11: =1/3 -> 0.33333333 | G11: =3500+3500 -> 7000 | H11: =ROUND(F11*G11,3) -> 2333.333 | J11: =F11*$F$4 -> 1.972 | K11: =H11*$F$4 -> 13803.998
C12: Ser&Arr | D12: un | E12: Compresión Probetas Cilindricas | F12: =1/50 -> 0.02 | G12: 50000 | H12: =ROUND(F12*G12,3) -> 1000 | J12: =F12*$F$4 -> 0.11832 | K12: =H12*$F$4 -> 5916
E13: Total APU 8.1 | F13: =$F$4 -> 5.916 | G13: =SUM(H5:H12) -> 141504.27 | H13: =ROUND(F13*G13,3) -> 837139.24 | K13: =SUM(K5:K12) -> 837139.24

Sheet 8.2
B1: 02.- Presupuesto'!A1
B3: Código | C3: Recurso | D3: Unidad | E3: Descripción | F3: Cantidad | G3: Precio Unitario | H3: Total | M3: Mat | N3: MO | O3: SC | P3: Arr
B4: 8.2 | C4: Partida | D4: ='01.- Presupuesto'!F60 -> m3 | E4: ='01.- Presupuesto'!C60 -> Suministro e instalación emplantillado hormigón G5 | F4: ='01.- Presupuesto'!G60 -> 0.493 | G4: =G10 -> 120719.81 | H4: =H10 -> 59514.864 | J4: Cantidad | K4: Costo | M4: =SUMIF(C5:C22,"Material",K5:K22) -> 53827.835 | N4: =SUMIF(C5:C22,"Mano de Obra",K5:K22) -> 4739.1908 | O4: =SUMIF(C5:C22,"Subcontrato",K5:K22) -> 0 | P4: =SUMIF(C5:C22,"Ser&Arr",K5:K22) -> 947.83835 | Q4: =SUM(M4:P4) -> 59514.864
C5: Material | D5: m3 | E5: Hormigón G5 | F5: 1.1 | G5: =HormG5 -> 98167.5 | H5: =ROUND(F5*G5,3) -> 107984.25 | J5: =F5*$F$4 -> 0.5423 | K5: =H5*$F$4 -> 53236.235
C6: Material | D6: m3 | E6: Carga Incompleta | F6: =0.1 -> 0.1 | G6: 12000 | H6: =ROUND(F6*G6,3) -> 1200 | J6: =F6*$F$4 -> 0.0493 | K6: =H6*$F$4 -> 591.6
C7: Mano de Obra | D7: hh | E7: Maestro | F7: =1/3 -> 0.33333333 | G7: =Maestro -> 7250 | H7: =ROUND(F7*G7,3) -> 2416.667 | J7: =F7*$F$4 -> 0.16433333 | K7: =H7*$F$4 -> 1191.4168
C8: Mano de Obra | D8: hh | E8: Jornal | F8: =4*(1/3) -> 1.3333333 | G8: =Jornal -> 5397.2222 | H8: =ROUND(F8*G8,3) -> 7196.296 | J8: =F8*$F$4 -> 0.65733333 | K8: =H8*$F$4 -> 3547.7739
C9: Ser&Arr | D9: % | E9: Desgaste de Herramientas | F9: 0.2 | G9: =SUM(H7:H8) -> 9612.963 | H9: =ROUND(F9*G9,3) -> 1922.593 | J9: =F9*$F$4 -> 0.0986 | K9: =H9*$F$4 -> 947.83835
E10: Total APU 8.2 | F10: =$F$4 -> 0.493 | G10: =SUM(H5:H9) -> 120719.81 | H10: =ROUND(F10*G10,3) -> 59514.864 | K10: =SUM(K5:K9) -> 59514.864

Sheet 8.3
B1: 02.- Presupuesto'!A1
B3: Código | C3: Recurso | D3: Unidad | E3: Descripción | F3: Cantidad | G3: Precio Unitario | H3: Total | M3: Mat | N3: MO | O3: SC | P3: Arr
B4: 8.3 | C4: Partida | D4: ='01.- Presupuesto'!F61 -> m3 | E4: ='01.- Presupuesto'!C61 -> Suministro e Instalación relleno estructural compactado al 95% DMSC | F4: ='01.- Presupuesto'!G61 -> 7.6415 | G4: =G13 -> 84110.441 | H4: =H13 -> 642729.94 | J4: Cantidad | K4: Costo | M4: =SUMIF(C5:C25,"Material",K5:K25) -> 198679 | N4: =SUMIF(C5:C25,"Mano de Obra",K5:K25) -> 11018.615 | O4: =SUMIF(C5:C25,"Subcontrato",K5:K25) -> 0 | P4: =SUMIF(C5:C25,"Ser&Arr",K5:K25) -> 433032.32 | Q4: =SUM(M4:P4) -> 642729.93
C5: Material | D5: m3 | E5: Base Granular CBR >50% | F5: 1.3 | G5: =Base50 -> 20000 | H5: =ROUND(F5*G5,3) -> 26000 | J5: =F5*$F$4 -> 9.93395 | K5: =H5*$F$4 -> 198679
C6: Mano de Obra | D6: hh | E6: Maestro | F6: =1/20 -> 0.05 | G6: =Maestro -> 7250 | H6: =ROUND(F6*G6,3) -> 362.5 | J6: =F6*$F$4 -> 0.382075 | K6: =H6*$F$4 -> 2770.0438
C7: Mano de Obra | D7: hh | E7: Jornal | F7: =4*1/20 -> 0.2 | G7: =Jornal -> 5397.2222 | H7: =ROUND(F7*G7,3) -> 1079.444 | J7: =F7*$F$4 -> 1.5283 | K7: =H7*$F$4 -> 8248.5713
C8: Ser&Arr | D8: % | E8: Desgaste de Herramientas | F8: 0.2 | G8: =SUM(H6:H7) -> 1441.944 | H8: =ROUND(F8*G8,3) -> 288.389 | J8: =F8*$F$4 -> 1.5283 | K8: =H8*$F$4 -> 2203.7245
C9: Ser&Arr | D9: hm | E9: Retroexcavadora | F9: =1/20 -> 0.05 | G9: =Retroexcavadora -> 32000 | H9: =ROUND(F9*G9,3) -> 1600 | J9: =F9*$F$4 -> 0.382075 | K9: =H9*$F$4 -> 12226.4
C10: Ser&Arr | D10: día | E10: Placa Compactadora | F10: =1/20/8 -> 0.00625 | G10: 25000 | H10: =ROUND(F10*G10,3) -> 156.25 | J10: =F10*$F$4 -> 0.047759375 | K10: =H10*$F$4 -> 1193.9844
C11: Ser&Arr | D11: un | E11: Ensayo Granulometría | F11: =1/F4 -> 0.13086436 | G11: =(0.6+4.4)*UF -> 196335 | H11: =ROUND(F11*G11,3) -> 25693.254 | J11: =F11*$F$4 -> 1 | K11: =H11*$F$4 -> 196335
C12: Ser&Arr | D12: un | E12: Ensayo Densidad In Situ | F12: =3/F4 -> 0.39259308 | G12: =(0.41+4.4/3)*UF -> 73691.07 | H12: =ROUND(F12*G12,3) -> 28930.604 | J12: =F12*$F$4 -> 3 | K12: =H12*$F$4 -> 221073.21
E13: Total APU 8.3 | F13: =$F$4 -> 7.6415 | G13: =SUM(H5:H12) -> 84110.441 | H13: =ROUND(F13*G13,3) -> 642729.94 | K13: =SUM(K5:K12) -> 642729.93

Sheet 8.4
B1: 02.- Presupuesto'!A1
B3: Código | C3: Recurso | D3: Unidad | E3: Descripción | F3: Cantidad | G3: Precio Unitario | H3: Total | M3: Mat | N3: MO | O3: SC | P3: Arr
B4: 8.4 | C4: Partida | D4: ='01.- Presupuesto'!F62 -> m3 | E4: ='01.- Presupuesto'!C62 -> Excavación maquinaría local y traslado a botadero, hasta 20 Km | F4: ='01.- Presupuesto'!G62 -> 15.283 | G4: =G9 -> 25500 | H4: =H9 -> 389716.5 | J4: Cantidad | K4: Costo | M4: =SUMIF(C5:C21,"Material",K5:K21) -> 0 | N4: =SUMIF(C5:C21,"Mano de Obra",K5:K21) -> 0 | O4: =SUMIF(C5:C21,"Subcontrato",K5:K21) -> 0 | P4: =SUMIF(C5:C21,"Ser&Arr",K5:K21) -> 389716.5 | Q4: =SUM(M4:P4) -> 389716.5
C5: Ser&Arr | D5: hm | E5: Excavadora | F5: =1/20 -> 0.05 | G5: =Excavadora -> 50000 | H5: =ROUND(F5*G5,3) -> 2500 | J5: =F5*$F$4 -> 0.76415 | K5: =H5*$F$4 -> 38207.5
C6: Ser&Arr | D6: hm | E6: Retroexcavadora | F6: =1/20 -> 0.05 | G6: =Retroexcavadora -> 32000 | H6: =ROUND(F6*G6,3) -> 1600 | J6: =F6*$F$4 -> 0.76415 | K6: =H6*$F$4 -> 24452.8
C7: Ser&Arr | D7: hm | E7: Camión Tolva | F7: =1/20 -> 0.05 | G7: =Tolva -> 38000 | H7: =ROUND(F7*G7,3) -> 1900 | J7: =F7*$F$4 -> 0.76415 | K7: =H7*$F$4 -> 29037.7
C8: Ser&Arr | D8: m3 | E8: Carga y Retiro de Escombros | F8: 1.3 | G8: 15000 | H8: =ROUND(F8*G8,3) -> 19500 | J8: =F8*$F$4 -> 19.8679 | K8: =H8*$F$4 -> 298018.5
E9: Total APU 8.4 | F9: =$F$4 -> 15.283 | G9: =SUM(H5:H8) -> 25500 | H9: =ROUND(F9*G9,3) -> 389716.5 | K9: =SUM(K5:K8) -> 389716.5

Sheet 8.5
B1: 02.- Presupuesto'!A1
B3: Código | C3: Recurso | D3: Unidad | E3: Descripción | F3: Cantidad | G3: Precio Unitario | H3: Total | M3: Mat | N3: MO | O3: SC | P3: Arr
B4: 8.5 | C4: Partida | D4: ='01.- Presupuesto'!F63 -> m2 | E4: ='01.- Presupuesto'!C63 -> Suministro y construcción moldajes de madera o metálicos | F4: ='01.- Presupuesto'!G63 -> 26.16 | G4: =G12 -> 16475.796 | H4: =H12 -> 431006.82 | J4: Cantidad | K4: Costo | M4: =SUMIF(C5:C24,"Material",K5:K24) -> 309624.42 | N4: =SUMIF(C5:C24,"Mano de Obra",K5:K24) -> 101152.01 | O4: =SUMIF(C5:C24,"Subcontrato",K5:K24) -> 0 | P4: =SUMIF(C5:C24,"Ser&Arr",K5:K24) -> 20230.391 | Q4: =SUM(M4:P4) -> 431006.82
C5: Material | D5: uni | E5: Pino Verde 2x3" 3,2m | F5: =1/0.48 -> 2.0833333 | G5: 2400 | H5: =ROUND(F5*G5,3) -> 5000 | J5: =F5*$F$4 -> 54.5 | K5: =H5*$F$4 -> 130800
C6: Material | D6: uni | E6: Terciado Estructural 1,22x2,44m 15 mm | F6: =1.05*1/(1.22*2.44) -> 0.35272776 | G6: 16966 | H6: =ROUND(F6*G6,3) -> 5984.379 | J6: =F6*$F$4 -> 9.2273582 | K6: =H6*$F$4 -> 156551.35
C7: Material | D7: kg | E7: Clavos CTE 1 1/2" | F7: =1/4 -> 0.25 | G7: 1184 | H7: =ROUND(F7*G7,3) -> 296 | J7: =F7*$F$4 -> 6.54 | K7: =H7*$F$4 -> 7743.36
C8: Material | D8: uni | E8: Alambre Negro Recocido #14 25 Kg | F8: =1/72 -> 0.013888889 | G8: 39990 | H8: =ROUND(F8*G8,3) -> 555.417 | J8: =F8*$F$4 -> 0.36333333 | K8: =H8*$F$4 -> 14529.709
C9: Mano de Obra | D9: hh | E9: Maestro | F9: =0.3 -> 0.3 | G9: =Maestro -> 7250 | H9: =ROUND(F9*G9,3) -> 2175 | J9: =F9*$F$4 -> 7.848 | K9: =H9*$F$4 -> 56898
C10: Mano de Obra | D10: hh | E10: Ayudante | F10: =0.3 -> 0.3 | G10: =Ayudante -> 5638.8889 | H10: =ROUND(F10*G10,3) -> 1691.667 | J10: =F10*$F$4 -> 7.848 | K10: =H10*$F$4 -> 44254.009
C11: Ser&Arr | D11: % | E11: Desgaste de Herramientas | F11: 0.2 | G11: =SUM(H9:H10) -> 3866.667 | H11: =ROUND(F11*G11,3) -> 773.333 | J11: =F11*$F$4 -> 5.232 | K11: =H11*$F$4 -> 20230.391
E12: Total APU 8.5 | F12: =$F$4 -> 26.16 | G12: =SUM(H5:H11) -> 16475.796 | H12: =ROUND(F12*G12,3) -> 431006.82 | K12: =SUM(K5:K11) -> 431006.82

Sheet 8.6
B1: 02.- Presupuesto'!A1
B3: Código | C3: Recurso | D3: Unidad | E3: Descripción | F3: Cantidad | G3: Precio Unitario | H3: Total | M3: Mat | N3: MO | O3: SC | P3: Arr
B4: 8.6 | C4: Partida | D4: ='01.- Presupuesto'!F64 -> kg | E4: ='01.- Presupuesto'!C64 -> Suministro e instalación armadura A630-420H, diámetro 12mm | F4: ='01.- Presupuesto'!G64 -> 392 | G4: =G8 -> 1644.333 | H4: =H8 -> 644578.54 | J4: Cantidad | K4: Costo | M4: =SUMIF(C5:C20,"Material",K5:K20) -> 409378.54 | N4: =SUMIF(C5:C20,"Mano de Obra",K5:K20) -> 0 | O4: =SUMIF(C5:C20,"Subcontrato",K5:K20) -> 235200 | P4: =SUMIF(C5:C20,"Ser&Arr",K5:K20) -> 0 | Q4: =SUM(M4:P4) -> 644578.54
C5: Material | D5: Kg | E5: Acero A630-420H | F5: 1.1 | G5: 900 | H5: =ROUND(F5*G5,3) -> 990 | J5: =F5*$F$4 -> 431.2 | K5: =H5*$F$4 -> 388080
C6: Material | D6: Kg | E6: Alambre Negro Recocido #18 | F6: =1/30 -> 0.033333333 | G6: 1630 | H6: =ROUND(F6*G6,3) -> 54.333 | J6: =F6*$F$4 -> 13.066667 | K6: =H6*$F$4 -> 21298.536
C7: Subcontrato | D7: Kg | E7: Enfierrador | F7: 1 | G7: =Enf -> 600 | H7: =ROUND(F7*G7,3) -> 600 | J7: =F7*$F$4 -> 392 | K7: =H7*$F$4 -> 235200
E8: Total APU 8.6 | F8: =$F$4 -> 392 | G8: =SUM(H5:H7) -> 1644.333 | H8: =ROUND(F8*G8,3) -> 644578.54 | K8: =SUM(K5:K7) -> 644578.54

Sheet 8.7
B1: 02.- Presupuesto'!A1
B3: Código | C3: Recurso | D3: Unidad | E3: Descripción | F3: Cantidad | G3: Precio Unitario | H3: Total | M3: Mat | N3: MO | O3: SC | P3: Arr
B4: 8.7 | C4: Partida | D4: ='01.- Presupuesto'!F65 -> un | E4: ='01.- Presupuesto'!C65 -> Suministro e instalación de pernos de anclaje químico | F4: ='01.- Presupuesto'!G65 -> 64 | G4: =G9 -> 11342.214 | H4: =H9 -> 725901.7 | J4: Cantidad | K4: Costo | M4: =SUMIF(C5:C21,"Material",K5:K21) -> 633101.7 | N4: =SUMIF(C5:C21,"Mano de Obra",K5:K21) -> 77333.312 | O4: =SUMIF(C5:C21,"Subcontrato",K5:K21) -> 0 | P4: =SUMIF(C5:C21,"Ser&Arr",K5:K21) -> 15466.688 | Q4: =SUM(M4:P4) -> 725901.7
C5: Material | D5: uni | E5: Perno Anclaje 3/4" | F5: 1 | G5: 9600 | H5: =ROUND(F5*G5,3) -> 9600 | J5: =F5*$F$4 -> 64 | K5: =H5*$F$4 -> 614400
C6: Material | D6: uni | E6: Adhesivo Anclaje Químico | F6: =1.1*1/49 -> 0.02244898 | G6: =15490/1.19 -> 13016.807 | H6: =ROUND(F6*G6,3) -> 292.214 | J6: =F6*$F$4 -> 1.4367347 | K6: =H6*$F$4 -> 18701.696
C7: Mano de Obra | D7: hh | E7: Maestro | F7: =1/6 -> 0.16666667 | G7: =Maestro -> 7250 | H7: =ROUND(F7*G7,3) -> 1208.333 | J7: =F7*$F$4 -> 10.666667 | K7: =H7*$F$4 -> 77333.312
C8: Ser&Arr | D8: % | E8: Desgaste de Herramientas | F8: 0.2 | G8: =SUM(H7:H7) -> 1208.333 | H8: =ROUND(F8*G8,3) -> 241.667 | J8: =F8*$F$4 -> 12.8 | K8: =H8*$F$4 -> 15466.688
E9: Total APU 8.7 | F9: =$F$4 -> 64 | G9: =SUM(H5:H8) -> 11342.214 | H9: =ROUND(F9*G9,3) -> 725901.7 | K9: =SUM(K5:K8) -> 725901.7

Sheet 9.1
B1: 02.- Presupuesto'!A1
B3: Código | C3: Recurso | D3: Unidad | E3: Descripción | F3: Cantidad | G3: Precio Unitario | H3: Total | M3: Mat | N3: MO | O3: SC | P3: Arr
B4: 9.1 | C4: Partida | D4: ='01.- Presupuesto'!F67 -> m3 | E4: ='01.- Presupuesto'!C67 -> Suministro e Instalación Hormigón G15, con aditivo impermeabilizante, igol denso. | F4: ='01.- Presupuesto'!G67 -> 2.112 | G4: =G16 -> 222362.55 | H4: =H16 -> 469629.71 | J4: Cantidad | K4: Costo | M4: =SUMIF(C5:C28,"Material",K5:K28) -> 331218.62 | N4: =SUMIF(C5:C28,"Mano de Obra",K5:K28) -> 105369.24 | O4: =SUMIF(C5:C28,"Subcontrato",K5:K28) -> 0 | P4: =SUMIF(C5:C28,"Ser&Arr",K5:K28) -> 33041.847 | Q4: =SUM(M4:P4) -> 469629.71
C5: Material | D5: m3 | E5: Hormigón G15(10)20-8 | F5: 1.1 | G5: =HormG15 -> 104842.89 | H5: =ROUND(F5*G5,3) -> 115327.18 | J5: =F5*$F$4 -> 2.3232 | K5: =H5*$F$4 -> 243571
C6: Material | D6: m3 | E6: Carga Incompleta | F6: =0.1 -> 0.1 | G6: 12000 | H6: =ROUND(F6*G6,3) -> 1200 | J6: =F6*$F$4 -> 0.2112 | K6: =H6*$F$4 -> 2534.4
C7: Material | D7: m3 | E7: Aditivo Impermeabilizante | F7: 1.1 | G7: =0.07*UF -> 2748.69 | H7: =ROUND(F7*G7,3) -> 3023.559 | J7: =F7*$F$4 -> 2.3232 | K7: =H7*$F$4 -> 6385.7566
C8: Material | D8: un | E8: Tineta Igol Denso 16 Lt | F8: =10*2*0.3/16 -> 0.375 | G8: =118290/1.19 -> 99403.361 | H8: =ROUND(F8*G8,3) -> 37276.261 | J8: =F8*$F$4 -> 0.792 | K8: =H8*$F$4 -> 78727.463
C9: Mano de Obra | D9: hh | E9: Maestro | F9: =1/3 -> 0.33333333 | G9: =Maestro -> 7250 | H9: =ROUND(F9*G9,3) -> 2416.667 | J9: =F9*$F$4 -> 0.704 | K9: =H9*$F$4 -> 5104.0007
C10: Mano de Obra | D10: hh | E10: Jornal | F10: =4*(1/3) -> 1.3333333 | G10: =Jornal -> 5397.2222 | H10: =ROUND(F10*G10,3) -> 7196.296 | J10: =F10*$F$4 -> 2.816 | K10: =H10*$F$4 -> 15198.577
C11: Mano de Obra | D11: hh | E11: Pintor | F11: =10/2 -> 5 | G11: =Pintor -> 8055.5556 | H11: =ROUND(F11*G11,3) -> 40277.778 | J11: =F11*$F$4 -> 10.56 | K11: =H11*$F$4 -> 85066.667
C12: Ser&Arr | D12: % | E12: Desgaste de Herramientas | F12: 0.2 | G12: =SUM(H9:H11) -> 49890.741 | H12: =ROUND(F12*G12,3) -> 9978.148 | J12: =F12*$F$4 -> 0.4224 | K12: =H12*$F$4 -> 21073.849
C13: Ser&Arr | D13: día | E13: Sonda Vibradora + Motor Bencinero | F13: =1/3 -> 0.33333333 | G13: =3500+3500 -> 7000 | H13: =ROUND(F13*G13,3) -> 2333.333 | J13: =F13*$F$4 -> 0.704 | K13: =H13*$F$4 -> 4927.9993
C14: Ser&Arr | D14: día | E14: Sonda Vibradora + Motor Electrico | F14: =1/3 -> 0.33333333 | G14: =3500+3500 -> 7000 | H14: =ROUND(F14*G14,3) -> 2333.333 | J14: =F14*$F$4 -> 0.704 | K14: =H14*$F$4 -> 4927.9993
C15: Ser&Arr | D15: un | E15: Compresión Probetas Cilindricas | F15: =1/50 -> 0.02 | G15: 50000 | H15: =ROUND(F15*G15,3) -> 1000 | J15: =F15*$F$4 -> 0.04224 | K15: =H15*$F$4 -> 2112
E16: Total APU 9.1 | F16: =$F$4 -> 2.112 | G16: =SUM(H5:H15) -> 222362.55 | H16: =ROUND(F16*G16,3) -> 469629.71 | K16: =SUM(K5:K15) -> 469629.71

Sheet 9.2
B1: 02.- Presupuesto'!A1
B3: Código | C3: Recurso | D3: Unidad | E3: Descripción | F3: Cantidad | G3: Precio Unitario | H3: Total | M3: Mat | N3: MO | O3: SC | P3: Arr
B4: 9.2 | C4: Partida | D4: ='01.- Presupuesto'!F68 -> m3 | E4: ='01.- Presupuesto'!C68 -> Suministro e instalación emplantillado hormigón G5 | F4: ='01.- Presupuesto'!G68 -> 0.1805 | G4: =G10 -> 120719.81 | H4: =H10 -> 21789.925 | J4: Cantidad | K4: Costo | M4: =SUMIF(C5:C22,"Material",K5:K22) -> 19707.757 | N4: =SUMIF(C5:C22,"Mano de Obra",K5:K22) -> 1735.1398 | O4: =SUMIF(C5:C22,"Subcontrato",K5:K22) -> 0 | P4: =SUMIF(C5:C22,"Ser&Arr",K5:K22) -> 347.02804 | Q4: =SUM(M4:P4) -> 21789.925
C5: Material | D5: m3 | E5: Hormigón G5 | F5: 1.1 | G5: =HormG5 -> 98167.5 | H5: =ROUND(F5*G5,3) -> 107984.25 | J5: =F5*$F$4 -> 0.19855 | K5: =H5*$F$4 -> 19491.157
C6: Material | D6: m3 | E6: Carga Incompleta | F6: =0.1 -> 0.1 | G6: 12000 | H6: =ROUND(F6*G6,3) -> 1200 | J6: =F6*$F$4 -> 0.01805 | K6: =H6*$F$4 -> 216.6
C7: Mano de Obra | D7: hh | E7: Maestro | F7: =1/3 -> 0.33333333 | G7: =Maestro -> 7250 | H7: =ROUND(F7*G7,3) -> 2416.667 | J7: =F7*$F$4 -> 0.060166667 | K7: =H7*$F$4 -> 436.20839
C8: Mano de Obra | D8: hh | E8: Jornal | F8: =4*(1/3) -> 1.3333333 | G8: =Jornal -> 5397.2222 | H8: =ROUND(F8*G8,3) -> 7196.296 | J8: =F8*$F$4 -> 0.24066667 | K8: =H8*$F$4 -> 1298.9314
C9: Ser&Arr | D9: % | E9: Desgaste de Herramientas | F9: 0.2 | G9: =SUM(H7:H8) -> 9612.963 | H9: =ROUND(F9*G9,3) -> 1922.593 | J9: =F9*$F$4 -> 0.0361 | K9: =H9*$F$4 -> 347.02804
E10: Total APU 9.2 | F10: =$F$4 -> 0.1805 | G10: =SUM(H5:H9) -> 120719.81 | H10: =ROUND(F10*G10,3) -> 21789.925 | K10: =SUM(K5:K9) -> 21789.925

Sheet 9.3
B1: 02.- Presupuesto'!A1
B3: Código | C3: Recurso | D3: Unidad | E3: Descripción | F3: Cantidad | G3: Precio Unitario | H3: Total | M3: Mat | N3: MO | O3: SC | P3: Arr
B4: 9.3 | C4: Partida | D4: ='01.- Presupuesto'!F69 -> kg | E4: ='01.- Presupuesto'!C69 -> Suministro e instalación enfierradura malla acma C-188 | F4: ='01.- Presupuesto'!G69 -> 66 | G4: =G9 -> 2586.773 | H4: =H9 -> 170727.02 | J4: Cantidad | K4: Costo | M4: =SUMIF(C5:C21,"Material",K5:K21) -> 94592.322 | N4: =SUMIF(C5:C21,"Mano de Obra",K5:K21) -> 63445.602 | O4: =SUMIF(C5:C21,"Subcontrato",K5:K21) -> 0 | P4: =SUMIF(C5:C21,"Ser&Arr",K5:K21) -> 12689.094 | Q4: =SUM(M4:P4) -> 170727.02
C5: Material | D5: uni | E5: Malla Acma C-188 | F5: =1.05*1/30.03 -> 0.034965035 | G5: 40990 | H5: =ROUND(F5*G5,3) -> 1433.217 | J5: =F5*$F$4 -> 2.3076923 | K5: =H5*$F$4 -> 94592.322
C6: Mano de Obra | D6: hh | E6: Maestro | F6: =1/30 -> 0.033333333 | G6: =Maestro -> 7250 | H6: =ROUND(F6*G6,3) -> 241.667 | J6: =F6*$F$4 -> 2.2 | K6: =H6*$F$4 -> 15950.022
C7: Mano de Obra | D7: hh | E7: Jornal | F7: =4/30 -> 0.13333333 | G7: =Jornal -> 5397.2222 | H7: =ROUND(F7*G7,3) -> 719.63 | J7: =F7*$F$4 -> 8.8 | K7: =H7*$F$4 -> 47495.58
C8: Ser&Arr | D8: % | E8: Desgaste de Herramientas | F8: 0.2 | G8: =SUM(H6:H7) -> 961.297 | H8: =ROUND(F8*G8,3) -> 192.259 | J8: =F8*$F$4 -> 13.2 | K8: =H8*$F$4 -> 12689.094
E9: Total APU 9.3 | F9: =$F$4 -> 66 | G9: =SUM(H5:H8) -> 2586.773 | H9: =ROUND(F9*G9,3) -> 170727.02 | K9: =SUM(K5:K8) -> 170727.02

Sheet 9.4
B1: 02.- Presupuesto'!A1
B3: Código | C3: Recurso | D3: Unidad | E3: Descripción | F3: Cantidad | G3: Precio Unitario | H3: Total | M3: Mat | N3: MO | O3: SC | P3: Arr
B4: 9.4 | C4: Partida | D4: ='01.- Presupuesto'!F70 -> m3 | E4: ='01.- Presupuesto'!C70 -> Excavación maquinaría local y traslado a botadero, hasta 20 Km | F4: ='01.- Presupuesto'!G70 -> 6.137 | G4: =G9 -> 25500 | H4: =H9 -> 156493.5 | J4: Cantidad | K4: Costo | M4: =SUMIF(C5:C21,"Material",K5:K21) -> 0 | N4: =SUMIF(C5:C21,"Mano de Obra",K5:K21) -> 0 | O4: =SUMIF(C5:C21,"Subcontrato",K5:K21) -> 0 | P4: =SUMIF(C5:C21,"Ser&Arr",K5:K21) -> 156493.5 | Q4: =SUM(M4:P4) -> 156493.5
C5: Ser&Arr | D5: hm | E5: Excavadora | F5: =1/20 -> 0.05 | G5: =Excavadora -> 50000 | H5: =ROUND(F5*G5,3) -> 2500 | J5: =F5*$F$4 -> 0.30685 | K5: =H5*$F$4 -> 15342.5
C6: Ser&Arr | D6: hm | E6: Retroexcavadora | F6: =1/20 -> 0.05 | G6: =Retroexcavadora -> 32000 | H6: =ROUND(F6*G6,3) -> 1600 | J6: =F6*$F$4 -> 0.30685 | K6: =H6*$F$4 -> 9819.2
C7: Ser&Arr | D7: hm | E7: Camión Tolva | F7: =1/20 -> 0.05 | G7: =Tolva -> 38000 | H7: =ROUND(F7*G7,3) -> 1900 | J7: =F7*$F$4 -> 0.30685 | K7: =H7*$F$4 -> 11660.3
C8: Ser&Arr | D8: m3 | E8: Carga y Retiro de Escombros | F8: 1.3 | G8: 15000 | H8: =ROUND(F8*G8,3) -> 19500 | J8: =F8*$F$4 -> 7.9781 | K8: =H8*$F$4 -> 119671.5
E9: Total APU 9.4 | F9: =$F$4 -> 6.137 | G9: =SUM(H5:H8) -> 25500 | H9: =ROUND(F9*G9,3) -> 156493.5 | K9: =SUM(K5:K8) -> 156493.5

Sheet 9.5
B1: 02.- Presupuesto'!A1
B3: Código | C3: Recurso | D3: Unidad | E3: Descripción | F3: Cantidad | G3: Precio Unitario | H3: Total | M3: Mat | N3: MO | O3: SC | P3: Arr
B4: 9.5 | C4: Partida | D4: ='01.- Presupuesto'!F71 -> m2 | E4: ='01.- Presupuesto'!C71 -> Suministro y construcción moldajes de madera o metálicos | F4: ='01.- Presupuesto'!G71 -> 21.12 | G4: =G12 -> 16475.796 | H4: =H12 -> 347968.81 | J4: Cantidad | K4: Costo | M4: =SUMIF(C5:C24,"Material",K5:K24) -> 249972.01 | N4: =SUMIF(C5:C24,"Mano de Obra",K5:K24) -> 81664.007 | O4: =SUMIF(C5:C24,"Subcontrato",K5:K24) -> 0 | P4: =SUMIF(C5:C24,"Ser&Arr",K5:K24) -> 16332.793 | Q4: =SUM(M4:P4) -> 347968.81
C5: Material | D5: uni | E5: Pino Verde 2x3" 3,2m | F5: =1/0.48 -> 2.0833333 | G5: 2400 | H5: =ROUND(F5*G5,3) -> 5000 | J5: =F5*$F$4 -> 44 | K5: =H5*$F$4 -> 105600
C6: Material | D6: uni | E6: Terciado Estructural 1,22x2,44m 15 mm | F6: =1.05*1/(1.22*2.44) -> 0.35272776 | G6: 16966 | H6: =ROUND(F6*G6,3) -> 5984.379 | J6: =F6*$F$4 -> 7.4496103 | K6: =H6*$F$4 -> 126390.08
C7: Material | D7: kg | E7: Clavos CTE 1 1/2" | F7: =1/4 -> 0.25 | G7: 1184 | H7: =ROUND(F7*G7,3) -> 296 | J7: =F7*$F$4 -> 5.28 | K7: =H7*$F$4 -> 6251.52
C8: Material | D8: uni | E8: Alambre Negro Recocido #14 25 Kg | F8: =1/72 -> 0.013888889 | G8: 39990 | H8: =ROUND(F8*G8,3) -> 555.417 | J8: =F8*$F$4 -> 0.29333333 | K8: =H8*$F$4 -> 11730.407
C9: Mano de Obra | D9: hh | E9: Maestro | F9: =0.3 -> 0.3 | G9: =Maestro -> 7250 | H9: =ROUND(F9*G9,3) -> 2175 | J9: =F9*$F$4 -> 6.336 | K9: =H9*$F$4 -> 45936
C10: Mano de Obra | D10: hh | E10: Ayudante | F10: =0.3 -> 0.3 | G10: =Ayudante -> 5638.8889 | H10: =ROUND(F10*G10,3) -> 1691.667 | J10: =F10*$F$4 -> 6.336 | K10: =H10*$F$4 -> 35728.007
C11: Ser&Arr | D11: % | E11: Desgaste de Herramientas | F11: 0.2 | G11: =SUM(H9:H10) -> 3866.667 | H11: =ROUND(F11*G11,3) -> 773.333 | J11: =F11*$F$4 -> 4.224 | K11: =H11*$F$4 -> 16332.793
E12: Total APU 9.5 | F12: =$F$4 -> 21.12 | G12: =SUM(H5:H11) -> 16475.796 | H12: =ROUND(F12*G12,3) -> 347968.81 | K12: =SUM(K5:K11) -> 347968.81

Sheet 9.6
B1: 02.- Presupuesto'!A1
B3: Código | C3: Recurso | D3: Unidad | E3: Descripción | F3: Cantidad | G3: Precio Unitario | H3: Total | M3: Mat | N3: MO | O3: SC | P3: Arr
B4: 9.6 | C4: Partida | D4: ='01.- Presupuesto'!F72 -> un | E4: ='01.- Presupuesto'!C72 -> Tapa en losa de hormigón G15, incluye armadura acma 188, aditivo imperm. | F4: ='01.- Presupuesto'!G72 -> 1 | G4: =G17 -> 136004.35 | H4: =H17 -> 136004.35 | J4: Cantidad | K4: Costo | M4: =SUMIF(C5:C29,"Material",K5:K29) -> 88379.347 | N4: =SUMIF(C5:C29,"Mano de Obra",K5:K29) -> 27187.5 | O4: =SUMIF(C5:C29,"Subcontrato",K5:K29) -> 0 | P4: =SUMIF(C5:C29,"Ser&Arr",K5:K29) -> 20437.5 | Q4: =SUM(M4:P4) -> 136004.35
C5: Material | D5: m3 | E5: Hormigón G15(10)20-8 | F5: =1.1*1.9*1.9*0.1 -> 0.3971 | G5: =HormG15 -> 104842.89 | H5: =ROUND(F5*G5,3) -> 41633.112 | J5: =F5*$F$4 -> 0.3971 | K5: =H5*$F$4 -> 41633.112
C6: Material | D6: m3 | E6: Carga Incompleta | F6: 2 | G6: 12000 | H6: =ROUND(F6*G6,3) -> 24000 | J6: =F6*$F$4 -> 2 | K6: =H6*$F$4 -> 24000
C7: Material | D7: m3 | E7: Aditivo Impermeabilizante | F7: =F5 -> 0.3971 | G7: =0.07*UF -> 2748.69 | H7: =ROUND(F7*G7,3) -> 1091.505 | J7: =F7*$F$4 -> 0.3971 | K7: =H7*$F$4 -> 1091.505
C8: Material | D8: un | E8: Tineta Igol Denso 16 Lt | F8: =1.9*1.9*2*0.3/16 -> 0.135375 | G8: =118290/1.19 -> 99403.361 | H8: =ROUND(F8*G8,3) -> 13456.73 | J8: =F8*$F$4 -> 0.135375 | K8: =H8*$F$4 -> 13456.73
C9: Material | D9: uni | E9: Malla Acma C-188 | F9: =1/5 -> 0.2 | G9: 40990 | H9: =ROUND(F9*G9,3) -> 8198 | J9: =F9*$F$4 -> 0.2 | K9: =H9*$F$4 -> 8198
C10: Mano de Obra | D10: hh | E10: Maestro | F10: 1 | G10: =Maestro -> 7250 | H10: =ROUND(F10*G10,3) -> 7250 | J10: =F10*$F$4 -> 1 | K10: =H10*$F$4 -> 7250
C11: Mano de Obra | D11: hh | E11: Jornal | F11: 1 | G11: =Jornal -> 5397.2222 | H11: =ROUND(F11*G11,3) -> 5397.222 | J11: =F11*$F$4 -> 1 | K11: =H11*$F$4 -> 5397.222
C12: Mano de Obra | D12: hh | E12: Pintor | F12: =1.9*1.9/2 -> 1.805 | G12: =Pintor -> 8055.5556 | H12: =ROUND(F12*G12,3) -> 14540.278 | J12: =F12*$F$4 -> 1.805 | K12: =H12*$F$4 -> 14540.278
C13: Ser&Arr | D13: % | E13: Desgaste de Herramientas | F13: 0.2 | G13: =SUM(H10:H12) -> 27187.5 | H13: =ROUND(F13*G13,3) -> 5437.5 | J13: =F13*$F$4 -> 0.2 | K13: =H13*$F$4 -> 5437.5
C14: Ser&Arr | D14: día | E14: Sonda Vibradora + Motor Bencinero | F14: 1 | G14: =3500+3500 -> 7000 | H14: =ROUND(F14*G14,3) -> 7000 | J14: =F14*$F$4 -> 1 | K14: =H14*$F$4 -> 7000
C15: Ser&Arr | D15: día | E15: Sonda Vibradora + Motor Electrico | F15: 1 | G15: =3500+3500 -> 7000 | H15: =ROUND(F15*G15,3) -> 7000 | J15: =F15*$F$4 -> 1 | K15: =H15*$F$4 -> 7000
C16: Ser&Arr | D16: un | E16: Compresión Probetas Cilindricas | F16: =1/50 -> 0.02 | G16: 50000 | H16: =ROUND(F16*G16,3) -> 1000 | J16: =F16*$F$4 -> 0.02 | K16: =H16*$F$4 -> 1000
E17: Total APU 9.6 | F17: =$F$4 -> 1 | G17: =SUM(H5:H16) -> 136004.35 | H17: =ROUND(F17*G17,3) -> 136004.35 | K17: =SUM(K5:K16) -> 136004.35

Sheet 10.1
B1: 02.- Presupuesto'!A1
B3: Código | C3: Recurso | D3: Unidad | E3: Descripción | F3: Cantidad | G3: Precio Unitario | H3: Total | M3: Mat | N3: MO | O3: SC | P3: Arr
B4: 10.1 | C4: Partida | D4: ='01.- Presupuesto'!F74 -> m3 | E4: ='01.- Presupuesto'!C74 -> Suministro e instalación de hormigón G-15 con aditivo imp, igol denso, pintura, junta poliuretano | F4: ='01.- Presupuesto'!G74 -> 4.4486 | G4: =G16 -> 222362.55 | H4: =H16 -> 989202.06 | J4: Cantidad | K4: Costo | M4: =SUMIF(C5:C28,"Material",K5:K28) -> 697660.59 | N4: =SUMIF(C5:C28,"Mano de Obra",K5:K28) -> 221943.95 | O4: =SUMIF(C5:C28,"Subcontrato",K5:K28) -> 0 | P4: =SUMIF(C5:C28,"Ser&Arr",K5:K28) -> 69597.52 | Q4: =SUM(M4:P4) -> 989202.06
C5: Material | D5: m3 | E5: Hormigón G15(10)20-8 | F5: 1.1 | G5: =HormG15 -> 104842.89 | H5: =ROUND(F5*G5,3) -> 115327.18 | J5: =F5*$F$4 -> 4.89346 | K5: =H5*$F$4 -> 513044.49
C6: Material | D6: m3 | E6: Carga Incompleta | F6: =0.1 -> 0.1 | G6: 12000 | H6: =ROUND(F6*G6,3) -> 1200 | J6: =F6*$F$4 -> 0.44486 | K6: =H6*$F$4 -> 5338.32
C7: Material | D7: m3 | E7: Aditivo Impermeabilizante | F7: 1.1 | G7: =0.07*UF -> 2748.69 | H7: =ROUND(F7*G7,3) -> 3023.559 | J7: =F7*$F$4 -> 4.89346 | K7: =H7*$F$4 -> 13450.605
C8: Material | D8: un | E8: Tineta Igol Denso 16 Lt | F8: =10*2*0.3/16 -> 0.375 | G8: =118290/1.19 -> 99403.361 | H8: =ROUND(F8*G8,3) -> 37276.261 | J8: =F8*$F$4 -> 1.668225 | K8: =H8*$F$4 -> 165827.17
C9: Mano de Obra | D9: hh | E9: Maestro | F9: =1/3 -> 0.33333333 | G9: =Maestro -> 7250 | H9: =ROUND(F9*G9,3) -> 2416.667 | J9: =F9*$F$4 -> 1.4828667 | K9: =H9*$F$4 -> 10750.785
C10: Mano de Obra | D10: hh | E10: Jornal | F10: =4*(1/3) -> 1.3333333 | G10: =Jornal -> 5397.2222 | H10: =ROUND(F10*G10,3) -> 7196.296 | J10: =F10*$F$4 -> 5.9314667 | K10: =H10*$F$4 -> 32013.442
C11: Mano de Obra | D11: hh | E11: Pintor | F11: =10/2 -> 5 | G11: =Pintor -> 8055.5556 | H11: =ROUND(F11*G11,3) -> 40277.778 | J11: =F11*$F$4 -> 22.243 | K11: =H11*$F$4 -> 179179.72
C12: Ser&Arr | D12: % | E12: Desgaste de Herramientas | F12: 0.2 | G12: =SUM(H9:H11) -> 49890.741 | H12: =ROUND(F12*G12,3) -> 9978.148 | J12: =F12*$F$4 -> 0.88972 | K12: =H12*$F$4 -> 44388.789
C13: Ser&Arr | D13: día | E13: Sonda Vibradora + Motor Bencinero | F13: =1/3 -> 0.33333333 | G13: =3500+3500 -> 7000 | H13: =ROUND(F13*G13,3) -> 2333.333 | J13: =F13*$F$4 -> 1.4828667 | K13: =H13*$F$4 -> 10380.065
C14: Ser&Arr | D14: día | E14: Sonda Vibradora + Motor Electrico | F14: =1/3 -> 0.33333333 | G14: =3500+3500 -> 7000 | H14: =ROUND(F14*G14,3) -> 2333.333 | J14: =F14*$F$4 -> 1.4828667 | K14: =H14*$F$4 -> 10380.065
C15: Ser&Arr | D15: un | E15: Compresión Probetas Cilindricas | F15: =1/50 -> 0.02 | G15: 50000 | H15: =ROUND(F15*G15,3) -> 1000 | J15: =F15*$F$4 -> 0.088972 | K15: =H15*$F$4 -> 4448.6
E16: Total APU 10.1 | F16: =$F$4 -> 4.4486 | G16: =SUM(H5:H15) -> 222362.55 | H16: =ROUND(F16*G16,3) -> 989202.06 | K16: =SUM(K5:K15) -> 989202.06

Sheet 10.2
B1: 02.- Presupuesto'!A1
B3: Código | C3: Recurso | D3: Unidad | E3: Descripción | F3: Cantidad | G3: Precio Unitario | H3: Total | M3: Mat | N3: MO | O3: SC | P3: Arr
B4: 10.2 | C4: Partida | D4: ='01.- Presupuesto'!F75 -> m3 | E4: ='01.- Presupuesto'!C75 -> Suministro e instalación emplantillado hormigón G5 | F4: ='01.- Presupuesto'!G75 -> 1.11215 | G4: =G10 -> 120719.81 | H4: =H10 -> 134258.53 | J4: Cantidad | K4: Costo | M4: =SUMIF(C5:C22,"Material",K5:K22) -> 121429.26 | N4: =SUMIF(C5:C22,"Mano de Obra",K5:K22) -> 10691.057 | O4: =SUMIF(C5:C22,"Subcontrato",K5:K22) -> 0 | P4: =SUMIF(C5:C22,"Ser&Arr",K5:K22) -> 2138.2118 | Q4: =SUM(M4:P4) -> 134258.53
C5: Material | D5: m3 | E5: Hormigón G5 | F5: 1.1 | G5: =HormG5 -> 98167.5 | H5: =ROUND(F5*G5,3) -> 107984.25 | J5: =F5*$F$4 -> 1.223365 | K5: =H5*$F$4 -> 120094.68
C6: Material | D6: m3 | E6: Carga Incompleta | F6: =0.1 -> 0.1 | G6: 12000 | H6: =ROUND(F6*G6,3) -> 1200 | J6: =F6*$F$4 -> 0.111215 | K6: =H6*$F$4 -> 1334.58
C7: Mano de Obra | D7: hh | E7: Maestro | F7: =1/3 -> 0.33333333 | G7: =Maestro -> 7250 | H7: =ROUND(F7*G7,3) -> 2416.667 | J7: =F7*$F$4 -> 0.37071667 | K7: =H7*$F$4 -> 2687.6962
C8: Mano de Obra | D8: hh | E8: Jornal | F8: =4*(1/3) -> 1.3333333 | G8: =Jornal -> 5397.2222 | H8: =ROUND(F8*G8,3) -> 7196.296 | J8: =F8*$F$4 -> 1.4828667 | K8: =H8*$F$4 -> 8003.3606
C9: Ser&Arr | D9: % | E9: Desgaste de Herramientas | F9: 0.2 | G9: =SUM(H7:H8) -> 9612.963 | H9: =ROUND(F9*G9,3) -> 1922.593 | J9: =F9*$F$4 -> 0.22243 | K9: =H9*$F$4 -> 2138.2118
E10: Total APU 10.2 | F10: =$F$4 -> 1.11215 | G10: =SUM(H5:H9) -> 120719.81 | H10: =ROUND(F10*G10,3) -> 134258.53 | K10: =SUM(K5:K9) -> 134258.53

Sheet 10.3
B1: 02.- Presupuesto'!A1
B3: Código | C3: Recurso | D3: Unidad | E3: Descripción | F3: Cantidad | G3: Precio Unitario | H3: Total | M3: Mat | N3: MO | O3: SC | P3: Arr
B4: 10.3 | C4: Partida | D4: ='01.- Presupuesto'!F76 -> m3 | E4: ='01.- Presupuesto'!C76 -> Suministro e Instalación relleno estructural compactado al 95% DMSC | F4: ='01.- Presupuesto'!G76 -> 16 | G4: =G13 -> 55574.597 | H4: =H13 -> 889193.55 | J4: Cantidad | K4: Costo | M4: =SUMIF(C5:C25,"Material",K5:K25) -> 416000 | N4: =SUMIF(C5:C25,"Mano de Obra",K5:K25) -> 23071.104 | O4: =SUMIF(C5:C25,"Subcontrato",K5:K25) -> 0 | P4: =SUMIF(C5:C25,"Ser&Arr",K5:K25) -> 450122.45 | Q4: =SUM(M4:P4) -> 889193.55
C5: Material | D5: m3 | E5: Base Granular CBR >50% | F5: 1.3 | G5: =Base50 -> 20000 | H5: =ROUND(F5*G5,3) -> 26000 | J5: =F5*$F$4 -> 20.8 | K5: =H5*$F$4 -> 416000
C6: Mano de Obra | D6: hh | E6: Maestro | F6: =1/20 -> 0.05 | G6: =Maestro -> 7250 | H6: =ROUND(F6*G6,3) -> 362.5 | J6: =F6*$F$4 -> 0.8 | K6: =H6*$F$4 -> 5800
C7: Mano de Obra | D7: hh | E7: Jornal | F7: =4*1/20 -> 0.2 | G7: =Jornal -> 5397.2222 | H7: =ROUND(F7*G7,3) -> 1079.444 | J7: =F7*$F$4 -> 3.2 | K7: =H7*$F$4 -> 17271.104
C8: Ser&Arr | D8: % | E8: Desgaste de Herramientas | F8: 0.2 | G8: =SUM(H6:H7) -> 1441.944 | H8: =ROUND(F8*G8,3) -> 288.389 | J8: =F8*$F$4 -> 3.2 | K8: =H8*$F$4 -> 4614.224
C9: Ser&Arr | D9: hm | E9: Retroexcavadora | F9: =1/20 -> 0.05 | G9: =Retroexcavadora -> 32000 | H9: =ROUND(F9*G9,3) -> 1600 | J9: =F9*$F$4 -> 0.8 | K9: =H9*$F$4 -> 25600
C10: Ser&Arr | D10: día | E10: Placa Compactadora | F10: =1/20/8 -> 0.00625 | G10: 25000 | H10: =ROUND(F10*G10,3) -> 156.25 | J10: =F10*$F$4 -> 0.1 | K10: =H10*$F$4 -> 2500
C11: Ser&Arr | D11: un | E11: Ensayo Granulometría | F11: =1/F4 -> 0.0625 | G11: =(0.6+4.4)*UF -> 196335 | H11: =ROUND(F11*G11,3) -> 12270.938 | J11: =F11*$F$4 -> 1 | K11: =H11*$F$4 -> 196335.01
C12: Ser&Arr | D12: un | E12: Ensayo Densidad In Situ | F12: =3/F4 -> 0.1875 | G12: =(0.41+4.4/3)*UF -> 73691.07 | H12: =ROUND(F12*G12,3) -> 13817.076 | J12: =F12*$F$4 -> 3 | K12: =H12*$F$4 -> 221073.22
E13: Total APU 10.3 | F13: =$F$4 -> 16 | G13: =SUM(H5:H12) -> 55574.597 | H13: =ROUND(F13*G13,3) -> 889193.55 | K13: =SUM(K5:K12) -> 889193.55

Sheet 10.4
B1: 02.- Presupuesto'!A1
B3: Código | C3: Recurso | D3: Unidad | E3: Descripción | F3: Cantidad | G3: Precio Unitario | H3: Total | M3: Mat | N3: MO | O3: SC | P3: Arr
B4: 10.4 | C4: Partida | D4: ='01.- Presupuesto'!F77 -> m3 | E4: ='01.- Presupuesto'!C77 -> Excavación maquinaría local y traslado a botadero, hasta 20 Km | F4: ='01.- Presupuesto'!G77 -> 7.78505 | G4: =G9 -> 25500 | H4: =H9 -> 198518.77 | J4: Cantidad | K4: Costo | M4: =SUMIF(C5:C21,"Material",K5:K21) -> 0 | N4: =SUMIF(C5:C21,"Mano de Obra",K5:K21) -> 0 | O4: =SUMIF(C5:C21,"Subcontrato",K5:K21) -> 0 | P4: =SUMIF(C5:C21,"Ser&Arr",K5:K21) -> 198518.78 | Q4: =SUM(M4:P4) -> 198518.78
C5: Ser&Arr | D5: hm | E5: Excavadora | F5: =1/20 -> 0.05 | G5: =Excavadora -> 50000 | H5: =ROUND(F5*G5,3) -> 2500 | J5: =F5*$F$4 -> 0.3892525 | K5: =H5*$F$4 -> 19462.625
C6: Ser&Arr | D6: hm | E6: Retroexcavadora | F6: =1/20 -> 0.05 | G6: =Retroexcavadora -> 32000 | H6: =ROUND(F6*G6,3) -> 1600 | J6: =F6*$F$4 -> 0.3892525 | K6: =H6*$F$4 -> 12456.08
C7: Ser&Arr | D7: hm | E7: Camión Tolva | F7: =1/20 -> 0.05 | G7: =Tolva -> 38000 | H7: =ROUND(F7*G7,3) -> 1900 | J7: =F7*$F$4 -> 0.3892525 | K7: =H7*$F$4 -> 14791.595
C8: Ser&Arr | D8: m3 | E8: Carga y Retiro de Escombros | F8: 1.3 | G8: 15000 | H8: =ROUND(F8*G8,3) -> 19500 | J8: =F8*$F$4 -> 10.120565 | K8: =H8*$F$4 -> 151808.48
E9: Total APU 10.4 | F9: =$F$4 -> 7.78505 | G9: =SUM(H5:H8) -> 25500 | H9: =ROUND(F9*G9,3) -> 198518.77 | K9: =SUM(K5:K8) -> 198518.78

Sheet 10.5
B1: 02.- Presupuesto'!A1
B3: Código | C3: Recurso | D3: Unidad | E3: Descripción | F3: Cantidad | G3: Precio Unitario | H3: Total | M3: Mat | N3: MO | O3: SC | P3: Arr
B4: 10.5 | C4: Partida | D4: ='01.- Presupuesto'!F78 -> m2 | E4: ='01.- Presupuesto'!C78 -> Suministro y construcción moldajes de madera o metálicos | F4: ='01.- Presupuesto'!G78 -> 4.196 | G4: =G12 -> 16475.796 | H4: =H12 -> 69132.44 | J4: Cantidad | K4: Costo | M4: =SUMIF(C5:C24,"Material",K5:K24) -> 49663 | N4: =SUMIF(C5:C24,"Mano de Obra",K5:K24) -> 16224.535 | O4: =SUMIF(C5:C24,"Subcontrato",K5:K24) -> 0 | P4: =SUMIF(C5:C24,"Ser&Arr",K5:K24) -> 3244.9053 | Q4: =SUM(M4:P4) -> 69132.44
C5: Material | D5: uni | E5: Pino Verde 2x3" 3,2m | F5: =1/0.48 -> 2.0833333 | G5: 2400 | H5: =ROUND(F5*G5,3) -> 5000 | J5: =F5*$F$4 -> 8.7416667 | K5: =H5*$F$4 -> 20980
C6: Material | D6: uni | E6: Terciado Estructural 1,22x2,44m 15 mm | F6: =1.05*1/(1.22*2.44) -> 0.35272776 | G6: 16966 | H6: =ROUND(F6*G6,3) -> 5984.379 | J6: =F6*$F$4 -> 1.4800457 | K6: =H6*$F$4 -> 25110.454
C7: Material | D7: kg | E7: Clavos CTE 1 1/2" | F7: =1/4 -> 0.25 | G7: 1184 | H7: =ROUND(F7*G7,3) -> 296 | J7: =F7*$F$4 -> 1.049 | K7: =H7*$F$4 -> 1242.016
C8: Material | D8: uni | E8: Alambre Negro Recocido #14 25 Kg | F8: =1/72 -> 0.013888889 | G8: 39990 | H8: =ROUND(F8*G8,3) -> 555.417 | J8: =F8*$F$4 -> 0.058277778 | K8: =H8*$F$4 -> 2330.5297
C9: Mano de Obra | D9: hh | E9: Maestro | F9: =0.3 -> 0.3 | G9: =Maestro -> 7250 | H9: =ROUND(F9*G9,3) -> 2175 | J9: =F9*$F$4 -> 1.2588 | K9: =H9*$F$4 -> 9126.3
C10: Mano de Obra | D10: hh | E10: Ayudante | F10: =0.3 -> 0.3 | G10: =Ayudante -> 5638.8889 | H10: =ROUND(F10*G10,3) -> 1691.667 | J10: =F10*$F$4 -> 1.2588 | K10: =H10*$F$4 -> 7098.2347
C11: Ser&Arr | D11: % | E11: Desgaste de Herramientas | F11: 0.2 | G11: =SUM(H9:H10) -> 3866.667 | H11: =ROUND(F11*G11,3) -> 773.333 | J11: =F11*$F$4 -> 0.8392 | K11: =H11*$F$4 -> 3244.9053
E12: Total APU 10.5 | F12: =$F$4 -> 4.196 | G12: =SUM(H5:H11) -> 16475.796 | H12: =ROUND(F12*G12,3) -> 69132.44 | K12: =SUM(K5:K11) -> 69132.44

Sheet 10.6
B1: 02.- Presupuesto'!A1
B3: Código | C3: Recurso | D3: Unidad | E3: Descripción | F3: Cantidad | G3: Precio Unitario | H3: Total | M3: Mat | N3: MO | O3: SC | P3: Arr
B4: 10.6 | C4: Partida | D4: ='01.- Presupuesto'!F79 -> un | E4: ='01.- Presupuesto'!C79 -> Suministro e instalación de pernos de anclaje químico | F4: ='01.- Presupuesto'!G79 -> 10 | G4: =G9 -> 11342.214 | H4: =H9 -> 113422.14 | J4: Cantidad | K4: Costo | M4: =SUMIF(C5:C21,"Material",K5:K21) -> 98922.14 | N4: =SUMIF(C5:C21,"Mano de Obra",K5:K21) -> 12083.33 | O4: =SUMIF(C5:C21,"Subcontrato",K5:K21) -> 0 | P4: =SUMIF(C5:C21,"Ser&Arr",K5:K21) -> 2416.67 | Q4: =SUM(M4:P4) -> 113422.14
C5: Material | D5: uni | E5: Perno Anclaje 3/4" | F5: 1 | G5: 9600 | H5: =ROUND(F5*G5,3) -> 9600 | J5: =F5*$F$4 -> 10 | K5: =H5*$F$4 -> 96000
C6: Material | D6: uni | E6: Adhesivo Anclaje Químico | F6: =1.1*1/49 -> 0.02244898 | G6: =15490/1.19 -> 13016.807 | H6: =ROUND(F6*G6,3) -> 292.214 | J6: =F6*$F$4 -> 0.2244898 | K6: =H6*$F$4 -> 2922.14
C7: Mano de Obra | D7: hh | E7: Maestro | F7: =1/6 -> 0.16666667 | G7: =Maestro -> 7250 | H7: =ROUND(F7*G7,3) -> 1208.333 | J7: =F7*$F$4 -> 1.6666667 | K7: =H7*$F$4 -> 12083.33
C8: Ser&Arr | D8: % | E8: Desgaste de Herramientas | F8: 0.2 | G8: =SUM(H7:H7) -> 1208.333 | H8: =ROUND(F8*G8,3) -> 241.667 | J8: =F8*$F$4 -> 2 | K8: =H8*$F$4 -> 2416.67
E9: Total APU 10.6 | F9: =$F$4 -> 10 | G9: =SUM(H5:H8) -> 11342.214 | H9: =ROUND(F9*G9,3) -> 113422.14 | K9: =SUM(K5:K8) -> 113422.14

Sheet 10.7
B1: 02.- Presupuesto'!A1
B3: Código | C3: Recurso | D3: Unidad | E3: Descripción | F3: Cantidad | G3: Precio Unitario | H3: Total | M3: Mat | N3: MO | O3: SC | P3: Arr
B4: 10.7 | C4: Partida | D4: ='01.- Presupuesto'!F80 -> un | E4: ='01.- Presupuesto'!C80 -> Suministro e instalación rejilla galvanizada nervada | F4: ='01.- Presupuesto'!G80 -> 21 | G4: =G9 -> 25620.333 | H4: =H9 -> 538026.99 | J4: Cantidad | K4: Costo | M4: =SUMIF(C5:C21,"Material",K5:K21) -> 501690 | N4: =SUMIF(C5:C21,"Mano de Obra",K5:K21) -> 30280.824 | O4: =SUMIF(C5:C21,"Subcontrato",K5:K21) -> 0 | P4: =SUMIF(C5:C21,"Ser&Arr",K5:K21) -> 6056.169 | Q4: =SUM(M4:P4) -> 538026.99
C5: Material | D5: uni | E5: Rejilla Galvanizada Nervada | F5: 1 | G5: 23890 | H5: =ROUND(F5*G5,3) -> 23890 | J5: =F5*$F$4 -> 21 | K5: =H5*$F$4 -> 501690
C6: Mano de Obra | D6: hh | E6: Maestro | F6: =1/20 -> 0.05 | G6: =Maestro -> 7250 | H6: =ROUND(F6*G6,3) -> 362.5 | J6: =F6*$F$4 -> 1.05 | K6: =H6*$F$4 -> 7612.5
C7: Mano de Obra | D7: hh | E7: Jornal | F7: =4/20 -> 0.2 | G7: =Jornal -> 5397.2222 | H7: =ROUND(F7*G7,3) -> 1079.444 | J7: =F7*$F$4 -> 4.2 | K7: =H7*$F$4 -> 22668.324
C8: Ser&Arr | D8: % | E8: Desgaste de Herramientas | F8: 0.2 | G8: =SUM(H6:H7) -> 1441.944 | H8: =ROUND(F8*G8,3) -> 288.389 | J8: =F8*$F$4 -> 4.2 | K8: =H8*$F$4 -> 6056.169
E9: Total APU 10.7 | F9: =$F$4 -> 21 | G9: =SUM(H5:H8) -> 25620.333 | H9: =ROUND(F9*G9,3) -> 538026.99 | K9: =SUM(K5:K8) -> 538026.99

Sheet 10.8
B1: 02.- Presupuesto'!A1
B3: Código | C3: Recurso | D3: Unidad | E3: Descripción | F3: Cantidad | G3: Precio Unitario | H3: Total | M3: Mat | N3: MO | O3: SC | P3: Arr
B4: 10.8 | C4: Partida | D4: ='01.- Presupuesto'!F81 -> kg | E4: ='01.- Presupuesto'!C81 -> Suministro e instalación armadura A630-420H, diámetro 12mm | F4: ='01.- Presupuesto'!G81 -> 149.916 | G4: =G8 -> 1644.333 | H4: =H8 -> 246511.83 | J4: Cantidad | K4: Costo | M4: =SUMIF(C5:C20,"Material",K5:K20) -> 156562.23 | N4: =SUMIF(C5:C20,"Mano de Obra",K5:K20) -> 0 | O4: =SUMIF(C5:C20,"Subcontrato",K5:K20) -> 89949.6 | P4: =SUMIF(C5:C20,"Ser&Arr",K5:K20) -> 0 | Q4: =SUM(M4:P4) -> 246511.83
C5: Material | D5: Kg | E5: Acero A630-420H | F5: 1.1 | G5: 900 | H5: =ROUND(F5*G5,3) -> 990 | J5: =F5*$F$4 -> 164.9076 | K5: =H5*$F$4 -> 148416.84
C6: Material | D6: Kg | E6: Alambre Negro Recocido #18 | F6: =1/30 -> 0.033333333 | G6: 1630 | H6: =ROUND(F6*G6,3) -> 54.333 | J6: =F6*$F$4 -> 4.9972 | K6: =H6*$F$4 -> 8145.386
C7: Subcontrato | D7: Kg | E7: Enfierrador | F7: 1 | G7: =Enf -> 600 | H7: =ROUND(F7*G7,3) -> 600 | J7: =F7*$F$4 -> 149.916 | K7: =H7*$F$4 -> 89949.6
E8: Total APU 10.8 | F8: =$F$4 -> 149.916 | G8: =SUM(H5:H7) -> 1644.333 | H8: =ROUND(F8*G8,3) -> 246511.83 | K8: =SUM(K5:K7) -> 246511.83

Sheet 11.1
B1: 02.- Presupuesto'!A1
B3: Código | C3: Recurso | D3: Unidad | E3: Descripción | F3: Cantidad | G3: Precio Unitario | H3: Total | M3: Mat | N3: MO | O3: SC | P3: Arr
B4: 11.1 | C4: Partida | D4: ='01.- Presupuesto'!F83 -> un | E4: ='01.- Presupuesto'!C83 -> Suministro e Instalación Cámara separadora de hidrocarburos de 230 litros Infraplast | F4: ='01.- Presupuesto'!G83 -> 1 | G4: =G21 -> 2168971.7 | H4: =H21 -> 2168971.7 | J4: Cantidad | K4: Costo | M4: =SUMIF(C5:C24,"Material",K5:K24) -> 1754158.6 | N4: =SUMIF(C5:C24,"Mano de Obra",K5:K24) -> 310300 | O4: =SUMIF(C5:C24,"Subcontrato",K5:K24) -> 27453.102 | P4: =SUMIF(C5:C24,"Ser&Arr",K5:K24) -> 77060 | Q4: =SUM(M4:P4) -> 2168971.7
C5: Material | D5: m3 | E5: Hormigón G20(10)20-8 | F5: =((4*1.2*1.8)+(1.8*1.8)+(2*1.4*1.2)*0.2) -> 12.552 | G5: =HormG20 -> 108376.92 | H5: =ROUND(F5*G5,3) -> 1360347.1 | J5: =F5*$F$4 -> 12.552 | K5: =H5*$F$4 -> 1360347.1
C6: Material | D6: m3 | E6: Carga Incompleta | F6: 0 | G6: 12000 | H6: =ROUND(F6*G6,3) -> 0 | J6: =F6*$F$4 -> 0 | K6: =H6*$F$4 -> 0
C7: Material | D7: Kg | E7: Acero A630-420H | F7: =((4*1.2*1.8)+(1.8*1.8)+(2*1.4*1.2))*39.03/(2.6*5) -> 45.755169 | G7: 900 | H7: =ROUND(F7*G7,3) -> 41179.652 | J7: =F7*$F$4 -> 45.755169 | K7: =H7*$F$4 -> 41179.652
C8: Material | D8: Kg | E8: Alambre Negro Recocido #18 | F8: =1/30*F7 -> 1.5251723 | G8: 1630 | H8: =ROUND(F8*G8,3) -> 2486.031 | J8: =F8*$F$4 -> 1.5251723 | K8: =H8*$F$4 -> 2486.031
C9: Material | D9: un | E9: Tapa diamantada galvanizada | F9: 1 | G9: 130000 | H9: =ROUND(F9*G9,3) -> 130000 | J9: =F9*$F$4 -> 1 | K9: =H9*$F$4 -> 130000
C10: Material | D10: uni | E10: Pino Verde 2x3" 3,2m | F10: =1/0.48*((4*1.2*1.8)+(1.8*1.8)+2*(2*1.4*1.2)) -> 38.75 | G10: 2400 | H10: =ROUND(F10*G10,3) -> 93000 | J10: =F10*$F$4 -> 38.75 | K10: =H10*$F$4 -> 93000
C11: Material | D11: uni | E11: Terciado Estructural 1,22x2,44m 15 mm | F11: =1.05*1/(1.22*2.44)*((4*1.2*1.8)+(1.8*1.8)+2*(2*1.4*1.2)) -> 6.5607364 | G11: 16966 | H11: =ROUND(F11*G11,3) -> 111309.45 | J11: =F11*$F$4 -> 6.5607364 | K11: =H11*$F$4 -> 111309.45
C12: Material | D12: kg | E12: Clavos CTE 1 1/2" | F12: =1/4*((4*1.2*1.8)+(1.8*1.8)+2*(2*1.4*1.2)) -> 4.65 | G12: 1184 | H12: =ROUND(F12*G12,3) -> 5505.6 | J12: =F12*$F$4 -> 4.65 | K12: =H12*$F$4 -> 5505.6
C13: Material | D13: uni | E13: Alambre Negro Recocido #14 25 Kg | F13: =1/72*((4*1.2*1.8)+(1.8*1.8)+2*(2*1.4*1.2)) -> 0.25833333 | G13: 39990 | H13: =ROUND(F13*G13,3) -> 10330.75 | J13: =F13*$F$4 -> 0.25833333 | K13: =H13*$F$4 -> 10330.75
C14: Mano de Obra | D14: hh | E14: Maestro | F14: 16 | G14: =Maestro -> 7250 | H14: =ROUND(F14*G14,3) -> 116000 | J14: =F14*$F$4 -> 16 | K14: =H14*$F$4 -> 116000
C15: Mano de Obra | D15: hh | E15: Jornal | F15: 36 | G15: =Jornal -> 5397.2222 | H15: =ROUND(F15*G15,3) -> 194300 | J15: =F15*$F$4 -> 36 | K15: =H15*$F$4 -> 194300
C16: Ser&Arr | D16: % | E16: Desgaste de Herramientas | F16: 0.2 | G16: =SUM(H14:H15) -> 310300 | H16: =ROUND(F16*G16,3) -> 62060 | J16: =F16*$F$4 -> 0.2 | K16: =H16*$F$4 -> 62060
C17: Subcontrato | D17: kg | E17: Enfierrador | F17: =F7 -> 45.755169 | G17: =Enf -> 600 | H17: =ROUND(F17*G17,3) -> 27453.102 | J17: =F17*$F$4 -> 45.755169 | K17: =H17*$F$4 -> 27453.102
C18: Ser&Arr | D18: día | E18: Sonda Vibradora + Motor Bencinero | F18: 1 | G18: =3500+3500 -> 7000 | H18: =ROUND(F18*G18,3) -> 7000 | J18: =F18*$F$4 -> 1 | K18: =H18*$F$4 -> 7000
C19: Ser&Arr | D19: día | E19: Sonda Vibradora + Motor Electrico | F19: 1 | G19: =3500+3500 -> 7000 | H19: =ROUND(F19*G19,3) -> 7000 | J19: =F19*$F$4 -> 1 | K19: =H19*$F$4 -> 7000
C20: Ser&Arr | D20: un | E20: Compresión Probetas Cilindricas | F20: =1/50 -> 0.02 | G20: 50000 | H20: =ROUND(F20*G20,3) -> 1000 | J20: =F20*$F$4 -> 0.02 | K20: =H20*$F$4 -> 1000
E21: Total APU 11.1 | F21: =$F$4 -> 1 | G21: =SUM(H5:H20) -> 2168971.7 | H21: =ROUND(F21*G21,3) -> 2168971.7 | K21: =SUM(K5:K20) -> 2168971.7

Sheet 11.2
B1: 02.- Presupuesto'!A1
B3: Código | C3: Recurso | D3: Unidad | E3: Descripción | F3: Cantidad | G3: Precio Unitario | H3: Total | M3: Mat | N3: MO | O3: SC | P3: Arr
B4: 11.2 | C4: Partida | D4: ='01.- Presupuesto'!F84 -> m | E4: ='01.- Presupuesto'!C84 -> Suministro e instalación ducto PVC hidra Ø=110 mm flexodren | F4: ='01.- Presupuesto'!G84 -> 3 | G4: =G7 -> 20083.494 | H4: =H7 -> 60250.482 | J4: Cantidad | K4: Costo | M4: =SUMIF(C5:C19,"Material",K5:K19) -> 9250.482 | N4: =SUMIF(C5:C19,"Mano de Obra",K5:K19) -> 0 | O4: =SUMIF(C5:C19,"Subcontrato",K5:K19) -> 51000 | P4: =SUMIF(C5:C19,"Ser&Arr",K5:K19) -> 0 | Q4: =SUM(M4:P4) -> 60250.482
C5: Material | D5: uni | E5: Tubería Flexodren 110 | F5: =1.1*1/50 -> 0.022 | G5: =166789/1.19 -> 140158.82 | H5: =ROUND(F5*G5,3) -> 3083.494 | J5: =F5*$F$4 -> 0.066 | K5: =H5*$F$4 -> 9250.482
C6: Subcontrato | D6: m | E6: SC Instalación Tuberías PVC | F6: 1 | G6: =SCSan -> 17000 | H6: =ROUND(F6*G6,3) -> 17000 | J6: =F6*$F$4 -> 3 | K6: =H6*$F$4 -> 51000
E7: Total APU 11.2 | F7: =$F$4 -> 3 | G7: =SUM(H5:H6) -> 20083.494 | H7: =ROUND(F7*G7,3) -> 60250.482 | K7: =SUM(K5:K6) -> 60250.482

Sheet 11.3
B1: 02.- Presupuesto'!A1
B3: Código | C3: Recurso | D3: Unidad | E3: Descripción | F3: Cantidad | G3: Precio Unitario | H3: Total | M3: Mat | N3: MO | O3: SC | P3: Arr
B4: 11.3 | C4: Partida | D4: ='01.- Presupuesto'!F85 -> m3 | E4: ='01.- Presupuesto'!C85 -> Suministro e instalación arena compactada | F4: ='01.- Presupuesto'!G85 -> 1.8 | G4: =G11 -> 34686.583 | H4: =H11 -> 62435.849 | J4: Cantidad | K4: Costo | M4: =SUMIF(C5:C23,"Material",K5:K23) -> 56160 | N4: =SUMIF(C5:C23,"Mano de Obra",K5:K23) -> 2595.4992 | O4: =SUMIF(C5:C23,"Subcontrato",K5:K23) -> 0 | P4: =SUMIF(C5:C23,"Ser&Arr",K5:K23) -> 3680.3502 | Q4: =SUM(M4:P4) -> 62435.849
C5: Material | D5: m3 | E5: Arena | F5: 1.3 | G5: =Arena -> 24000 | H5: =ROUND(F5*G5,3) -> 31200 | J5: =F5*$F$4 -> 2.34 | K5: =H5*$F$4 -> 56160
C6: Mano de Obra | D6: hh | E6: Maestro | F6: =1/20 -> 0.05 | G6: =Maestro -> 7250 | H6: =ROUND(F6*G6,3) -> 362.5 | J6: =F6*$F$4 -> 0.09 | K6: =H6*$F$4 -> 652.5
C7: Mano de Obra | D7: hh | E7: Jornal | F7: =4*1/20 -> 0.2 | G7: =Jornal -> 5397.2222 | H7: =ROUND(F7*G7,3) -> 1079.444 | J7: =F7*$F$4 -> 0.36 | K7: =H7*$F$4 -> 1942.9992
C8: Ser&Arr | D8: % | E8: Desgaste de Herramientas | F8: 0.2 | G8: =SUM(H6:H7) -> 1441.944 | H8: =ROUND(F8*G8,3) -> 288.389 | J8: =F8*$F$4 -> 0.36 | K8: =H8*$F$4 -> 519.1002
C9: Ser&Arr | D9: hm | E9: Retroexcavadora | F9: =1/20 -> 0.05 | G9: =Retroexcavadora -> 32000 | H9: =ROUND(F9*G9,3) -> 1600 | J9: =F9*$F$4 -> 0.09 | K9: =H9*$F$4 -> 2880
C10: Ser&Arr | D10: día | E10: Placa Compactadora | F10: =1/20/8 -> 0.00625 | G10: 25000 | H10: =ROUND(F10*G10,3) -> 156.25 | J10: =F10*$F$4 -> 0.01125 | K10: =H10*$F$4 -> 281.25
E11: Total APU 11.3 | F11: =$F$4 -> 1.8 | G11: =SUM(H5:H10) -> 34686.583 | H11: =ROUND(F11*G11,3) -> 62435.849 | K11: =SUM(K5:K10) -> 62435.849

Sheet 11.4
B1: 02.- Presupuesto'!A1
B3: Código | C3: Recurso | D3: Unidad | E3: Descripción | F3: Cantidad | G3: Precio Unitario | H3: Total | M3: Mat | N3: MO | O3: SC | P3: Arr
B4: 11.4 | C4: Partida | D4: ='01.- Presupuesto'!F86 -> m3 | E4: ='01.- Presupuesto'!C86 -> Excavación, carguío sobre camión y traslado a botadero | F4: ='01.- Presupuesto'!G86 -> 3.2 | G4: =G9 -> 25500 | H4: =H9 -> 81600 | J4: Cantidad | K4: Costo | M4: =SUMIF(C5:C21,"Material",K5:K21) -> 0 | N4: =SUMIF(C5:C21,"Mano de Obra",K5:K21) -> 0 | O4: =SUMIF(C5:C21,"Subcontrato",K5:K21) -> 0 | P4: =SUMIF(C5:C21,"Ser&Arr",K5:K21) -> 81600 | Q4: =SUM(M4:P4) -> 81600
C5: Ser&Arr | D5: hm | E5: Excavadora | F5: =1/20 -> 0.05 | G5: =Excavadora -> 50000 | H5: =ROUND(F5*G5,3) -> 2500 | J5: =F5*$F$4 -> 0.16 | K5: =H5*$F$4 -> 8000
C6: Ser&Arr | D6: hm | E6: Retroexcavadora | F6: =1/20 -> 0.05 | G6: =Retroexcavadora -> 32000 | H6: =ROUND(F6*G6,3) -> 1600 | J6: =F6*$F$4 -> 0.16 | K6: =H6*$F$4 -> 5120
C7: Ser&Arr | D7: hm | E7: Camión Tolva | F7: =1/20 -> 0.05 | G7: =Tolva -> 38000 | H7: =ROUND(F7*G7,3) -> 1900 | J7: =F7*$F$4 -> 0.16 | K7: =H7*$F$4 -> 6080
C8: Ser&Arr | D8: m3 | E8: Carga y Retiro de Escombros | F8: 1.3 | G8: 15000 | H8: =ROUND(F8*G8,3) -> 19500 | J8: =F8*$F$4 -> 4.16 | K8: =H8*$F$4 -> 62400
E9: Total APU 11.4 | F9: =$F$4 -> 3.2 | G9: =SUM(H5:H8) -> 25500 | H9: =ROUND(F9*G9,3) -> 81600 | K9: =SUM(K5:K8) -> 81600

Sheet 12.1
B1: 02.- Presupuesto'!A1
B3: Código | C3: Recurso | D3: Unidad | E3: Descripción | F3: Cantidad | G3: Precio Unitario | H3: Total | M3: Mat | N3: MO | O3: SC | P3: Arr
B4: 12.1 | C4: Partida | D4: ='01.- Presupuesto'!F88 -> m3 | E4: ='01.- Presupuesto'!C88 -> Suministro e Instalación Hormigón G15, con aditivo impermeabilizante, igol denso. | F4: ='01.- Presupuesto'!G88 -> 1.2 | G4: =G16 -> 222362.55 | H4: =H16 -> 266835.07 | J4: Cantidad | K4: Costo | M4: =SUMIF(C5:C28,"Material",K5:K28) -> 188192.4 | N4: =SUMIF(C5:C28,"Mano de Obra",K5:K28) -> 59868.889 | O4: =SUMIF(C5:C28,"Subcontrato",K5:K28) -> 0 | P4: =SUMIF(C5:C28,"Ser&Arr",K5:K28) -> 18773.777 | Q4: =SUM(M4:P4) -> 266835.06
C5: Material | D5: m3 | E5: Hormigón G15(10)20-8 | F5: 1.1 | G5: =HormG15 -> 104842.89 | H5: =ROUND(F5*G5,3) -> 115327.18 | J5: =F5*$F$4 -> 1.32 | K5: =H5*$F$4 -> 138392.61
C6: Material | D6: m3 | E6: Carga Incompleta | F6: =0.1 -> 0.1 | G6: 12000 | H6: =ROUND(F6*G6,3) -> 1200 | J6: =F6*$F$4 -> 0.12 | K6: =H6*$F$4 -> 1440
C7: Material | D7: m3 | E7: Aditivo Impermeabilizante | F7: 1.1 | G7: =0.07*UF -> 2748.69 | H7: =ROUND(F7*G7,3) -> 3023.559 | J7: =F7*$F$4 -> 1.32 | K7: =H7*$F$4 -> 3628.2708
C8: Material | D8: un | E8: Tineta Igol Denso 16 Lt | F8: =10*2*0.3/16 -> 0.375 | G8: =118290/1.19 -> 99403.361 | H8: =ROUND(F8*G8,3) -> 37276.261 | J8: =F8*$F$4 -> 0.45 | K8: =H8*$F$4 -> 44731.513
C9: Mano de Obra | D9: hh | E9: Maestro | F9: =1/3 -> 0.33333333 | G9: =Maestro -> 7250 | H9: =ROUND(F9*G9,3) -> 2416.667 | J9: =F9*$F$4 -> 0.4 | K9: =H9*$F$4 -> 2900.0004
C10: Mano de Obra | D10: hh | E10: Jornal | F10: =4*(1/3) -> 1.3333333 | G10: =Jornal -> 5397.2222 | H10: =ROUND(F10*G10,3) -> 7196.296 | J10: =F10*$F$4 -> 1.6 | K10: =H10*$F$4 -> 8635.5552
C11: Mano de Obra | D11: hh | E11: Pintor | F11: =10/2 -> 5 | G11: =Pintor -> 8055.5556 | H11: =ROUND(F11*G11,3) -> 40277.778 | J11: =F11*$F$4 -> 6 | K11: =H11*$F$4 -> 48333.334
C12: Ser&Arr | D12: % | E12: Desgaste de Herramientas | F12: 0.2 | G12: =SUM(H9:H11) -> 49890.741 | H12: =ROUND(F12*G12,3) -> 9978.148 | J12: =F12*$F$4 -> 0.24 | K12: =H12*$F$4 -> 11973.778
C13: Ser&Arr | D13: día | E13: Sonda Vibradora + Motor Bencinero | F13: =1/3 -> 0.33333333 | G13: =3500+3500 -> 7000 | H13: =ROUND(F13*G13,3) -> 2333.333 | J13: =F13*$F$4 -> 0.4 | K13: =H13*$F$4 -> 2799.9996
C14: Ser&Arr | D14: día | E14: Sonda Vibradora + Motor Electrico | F14: =1/3 -> 0.33333333 | G14: =3500+3500 -> 7000 | H14: =ROUND(F14*G14,3) -> 2333.333 | J14: =F14*$F$4 -> 0.4 | K14: =H14*$F$4 -> 2799.9996
C15: Ser&Arr | D15: un | E15: Compresión Probetas Cilindricas | F15: =1/50 -> 0.02 | G15: 50000 | H15: =ROUND(F15*G15,3) -> 1000 | J15: =F15*$F$4 -> 0.024 | K15: =H15*$F$4 -> 1200
E16: Total APU 12.1 | F16: =$F$4 -> 1.2 | G16: =SUM(H5:H15) -> 222362.55 | H16: =ROUND(F16*G16,3) -> 266835.07 | K16: =SUM(K5:K15) -> 266835.06

Sheet 12.2
B1: 02.- Presupuesto'!A1
B3: Código | C3: Recurso | D3: Unidad | E3: Descripción | F3: Cantidad | G3: Precio Unitario | H3: Total | M3: Mat | N3: MO | O3: SC | P3: Arr
B4: 12.2 | C4: Partida | D4: ='01.- Presupuesto'!F89 -> m3 | E4: ='01.- Presupuesto'!C89 -> Suministro e instalación emplantillado hormigón G5 | F4: ='01.- Presupuesto'!G89 -> 0.1 | G4: =G10 -> 120719.81 | H4: =H10 -> 12071.981 | J4: Cantidad | K4: Costo | M4: =SUMIF(C5:C22,"Material",K5:K22) -> 10918.425 | N4: =SUMIF(C5:C22,"Mano de Obra",K5:K22) -> 961.2963 | O4: =SUMIF(C5:C22,"Subcontrato",K5:K22) -> 0 | P4: =SUMIF(C5:C22,"Ser&Arr",K5:K22) -> 192.2593 | Q4: =SUM(M4:P4) -> 12071.981
C5: Material | D5: m3 | E5: Hormigón G5 | F5: 1.1 | G5: =HormG5 -> 98167.5 | H5: =ROUND(F5*G5,3) -> 107984.25 | J5: =F5*$F$4 -> 0.11 | K5: =H5*$F$4 -> 10798.425
C6: Material | D6: m3 | E6: Carga Incompleta | F6: =0.1 -> 0.1 | G6: 12000 | H6: =ROUND(F6*G6,3) -> 1200 | J6: =F6*$F$4 -> 0.01 | K6: =H6*$F$4 -> 120
C7: Mano de Obra | D7: hh | E7: Maestro | F7: =1/3 -> 0.33333333 | G7: =Maestro -> 7250 | H7: =ROUND(F7*G7,3) -> 2416.667 | J7: =F7*$F$4 -> 0.033333333 | K7: =H7*$F$4 -> 241.6667
C8: Mano de Obra | D8: hh | E8: Jornal | F8: =4*(1/3) -> 1.3333333 | G8: =Jornal -> 5397.2222 | H8: =ROUND(F8*G8,3) -> 7196.296 | J8: =F8*$F$4 -> 0.13333333 | K8: =H8*$F$4 -> 719.6296
C9: Ser&Arr | D9: % | E9: Desgaste de Herramientas | F9: 0.2 | G9: =SUM(H7:H8) -> 9612.963 | H9: =ROUND(F9*G9,3) -> 1922.593 | J9: =F9*$F$4 -> 0.02 | K9: =H9*$F$4 -> 192.2593
E10: Total APU 12.2 | F10: =$F$4 -> 0.1 | G10: =SUM(H5:H9) -> 120719.81 | H10: =ROUND(F10*G10,3) -> 12071.981 | K10: =SUM(K5:K9) -> 12071.981

Sheet 12.3
B1: 02.- Presupuesto'!A1
B3: Código | C3: Recurso | D3: Unidad | E3: Descripción | F3: Cantidad | G3: Precio Unitario | H3: Total | M3: Mat | N3: MO | O3: SC | P3: Arr
B4: 12.3 | C4: Partida | D4: ='01.- Presupuesto'!F90 -> m3 | E4: ='01.- Presupuesto'!C90 -> Excavación maquinaría local y traslado a botadero, hasta 20 Km | F4: ='01.- Presupuesto'!G90 -> 1.3 | G4: =G9 -> 25500 | H4: =H9 -> 33150 | J4: Cantidad | K4: Costo | M4: =SUMIF(C5:C21,"Material",K5:K21) -> 0 | N4: =SUMIF(C5:C21,"Mano de Obra",K5:K21) -> 0 | O4: =SUMIF(C5:C21,"Subcontrato",K5:K21) -> 0 | P4: =SUMIF(C5:C21,"Ser&Arr",K5:K21) -> 33150 | Q4: =SUM(M4:P4) -> 33150
C5: Ser&Arr | D5: hm | E5: Excavadora | F5: =1/20 -> 0.05 | G5: =Excavadora -> 50000 | H5: =ROUND(F5*G5,3) -> 2500 | J5: =F5*$F$4 -> 0.065 | K5: =H5*$F$4 -> 3250
C6: Ser&Arr | D6: hm | E6: Retroexcavadora | F6: =1/20 -> 0.05 | G6: =Retroexcavadora -> 32000 | H6: =ROUND(F6*G6,3) -> 1600 | J6: =F6*$F$4 -> 0.065 | K6: =H6*$F$4 -> 2080
C7: Ser&Arr | D7: hm | E7: Camión Tolva | F7: =1/20 -> 0.05 | G7: =Tolva -> 38000 | H7: =ROUND(F7*G7,3) -> 1900 | J7: =F7*$F$4 -> 0.065 | K7: =H7*$F$4 -> 2470
C8: Ser&Arr | D8: m3 | E8: Carga y Retiro de Escombros | F8: 1.3 | G8: 15000 | H8: =ROUND(F8*G8,3) -> 19500 | J8: =F8*$F$4 -> 1.69 | K8: =H8*$F$4 -> 25350
E9: Total APU 12.3 | F9: =$F$4 -> 1.3 | G9: =SUM(H5:H8) -> 25500 | H9: =ROUND(F9*G9,3) -> 33150 | K9: =SUM(K5:K8) -> 33150

Sheet 12.4
B1: 02.- Presupuesto'!A1
B3: Código | C3: Recurso | D3: Unidad | E3: Descripción | F3: Cantidad | G3: Precio Unitario | H3: Total | M3: Mat | N3: MO | O3: SC | P3: Arr
B4: 12.4 | C4: Partida | D4: ='01.- Presupuesto'!F91 -> m2 | E4: ='01.- Presupuesto'!C91 -> Suministro y construcción moldajes de madera o metálicos | F4: ='01.- Presupuesto'!G91 -> 17.3 | G4: =G12 -> 16475.796 | H4: =H12 -> 285031.27 | J4: Cantidad | K4: Costo | M4: =SUMIF(C5:C24,"Material",K5:K24) -> 204759.27 | N4: =SUMIF(C5:C24,"Mano de Obra",K5:K24) -> 66893.339 | O4: =SUMIF(C5:C24,"Subcontrato",K5:K24) -> 0 | P4: =SUMIF(C5:C24,"Ser&Arr",K5:K24) -> 13378.661 | Q4: =SUM(M4:P4) -> 285031.27
C5: Material | D5: uni | E5: Pino Verde 2x3" 3,2m | F5: =1/0.48 -> 2.0833333 | G5: 2400 | H5: =ROUND(F5*G5,3) -> 5000 | J5: =F5*$F$4 -> 36.041667 | K5: =H5*$F$4 -> 86500
C6: Material | D6: uni | E6: Terciado Estructural 1,22x2,44m 15 mm | F6: =1.05*1/(1.22*2.44) -> 0.35272776 | G6: 16966 | H6: =ROUND(F6*G6,3) -> 5984.379 | J6: =F6*$F$4 -> 6.1021903 | K6: =H6*$F$4 -> 103529.76
C7: Material | D7: kg | E7: Clavos CTE 1 1/2" | F7: =1/4 -> 0.25 | G7: 1184 | H7: =ROUND(F7*G7,3) -> 296 | J7: =F7*$F$4 -> 4.325 | K7: =H7*$F$4 -> 5120.8
C8: Material | D8: uni | E8: Alambre Negro Recocido #14 25 Kg | F8: =1/72 -> 0.013888889 | G8: 39990 | H8: =ROUND(F8*G8,3) -> 555.417 | J8: =F8*$F$4 -> 0.24027778 | K8: =H8*$F$4 -> 9608.7141
C9: Mano de Obra | D9: hh | E9: Maestro | F9: =0.3 -> 0.3 | G9: =Maestro -> 7250 | H9: =ROUND(F9*G9,3) -> 2175 | J9: =F9*$F$4 -> 5.19 | K9: =H9*$F$4 -> 37627.5
C10: Mano de Obra | D10: hh | E10: Ayudante | F10: =0.3 -> 0.3 | G10: =Ayudante -> 5638.8889 | H10: =ROUND(F10*G10,3) -> 1691.667 | J10: =F10*$F$4 -> 5.19 | K10: =H10*$F$4 -> 29265.839
C11: Ser&Arr | D11: % | E11: Desgaste de Herramientas | F11: 0.2 | G11: =SUM(H9:H10) -> 3866.667 | H11: =ROUND(F11*G11,3) -> 773.333 | J11: =F11*$F$4 -> 3.46 | K11: =H11*$F$4 -> 13378.661
E12: Total APU 12.4 | F12: =$F$4 -> 17.3 | G12: =SUM(H5:H11) -> 16475.796 | H12: =ROUND(F12*G12,3) -> 285031.27 | K12: =SUM(K5:K11) -> 285031.27

Sheet 12.5
B1: 02.- Presupuesto'!A1
B3: Código | C3: Recurso | D3: Unidad | E3: Descripción | F3: Cantidad | G3: Precio Unitario | H3: Total | M3: Mat | N3: MO | O3: SC | P3: Arr
B4: 12.5 | C4: Partida | D4: ='01.- Presupuesto'!F92 -> kg | E4: ='01.- Presupuesto'!C92 -> Suministro e instalación enfierradura malla acma C-188 | F4: ='01.- Presupuesto'!G92 -> 35 | G4: =G9 -> 2586.773 | H4: =H9 -> 90537.055 | J4: Cantidad | K4: Costo | M4: =SUMIF(C5:C21,"Material",K5:K21) -> 50162.595 | N4: =SUMIF(C5:C21,"Mano de Obra",K5:K21) -> 33645.395 | O4: =SUMIF(C5:C21,"Subcontrato",K5:K21) -> 0 | P4: =SUMIF(C5:C21,"Ser&Arr",K5:K21) -> 6729.065 | Q4: =SUM(M4:P4) -> 90537.055
C5: Material | D5: uni | E5: Malla Acma C-188 | F5: =1.05*1/30.03 -> 0.034965035 | G5: 40990 | H5: =ROUND(F5*G5,3) -> 1433.217 | J5: =F5*$F$4 -> 1.2237762 | K5: =H5*$F$4 -> 50162.595
C6: Mano de Obra | D6: hh | E6: Maestro | F6: =1/30 -> 0.033333333 | G6: =Maestro -> 7250 | H6: =ROUND(F6*G6,3) -> 241.667 | J6: =F6*$F$4 -> 1.1666667 | K6: =H6*$F$4 -> 8458.345
C7: Mano de Obra | D7: hh | E7: Jornal | F7: =4/30 -> 0.13333333 | G7: =Jornal -> 5397.2222 | H7: =ROUND(F7*G7,3) -> 719.63 | J7: =F7*$F$4 -> 4.6666667 | K7: =H7*$F$4 -> 25187.05
C8: Ser&Arr | D8: % | E8: Desgaste de Herramientas | F8: 0.2 | G8: =SUM(H6:H7) -> 961.297 | H8: =ROUND(F8*G8,3) -> 192.259 | J8: =F8*$F$4 -> 7 | K8: =H8*$F$4 -> 6729.065
E9: Total APU 12.5 | F9: =$F$4 -> 35 | G9: =SUM(H5:H8) -> 2586.773 | H9: =ROUND(F9*G9,3) -> 90537.055 | K9: =SUM(K5:K8) -> 90537.055

Sheet 12.6
B1: 02.- Presupuesto'!A1
B3: Código | C3: Recurso | D3: Unidad | E3: Descripción | F3: Cantidad | G3: Precio Unitario | H3: Total | M3: Mat | N3: MO | O3: SC | P3: Arr
B4: 12.6 | C4: Partida | D4: ='01.- Presupuesto'!F93 -> m | E4: ='01.- Presupuesto'!C93 -> Ducto PVC 110mm, considera salida desde pretiles de transformador a cámara separadora | F4: ='01.- Presupuesto'!G93 -> 32 | G4: =G7 -> 19571.289 | H4: =H7 -> 626281.25 | J4: Cantidad | K4: Costo | M4: =SUMIF(C5:C8,"Material",K5:K8) -> 82281.248 | N4: =SUMIF(C5:C8,"Mano de Obra",K5:K8) -> 0 | O4: =SUMIF(C5:C8,"Subcontrato",K5:K8) -> 544000 | P4: =SUMIF(C5:C8,"Ser&Arr",K5:K8) -> 0 | Q4: =SUM(M4:P4) -> 626281.25
C5: Material | D5: uni | E5: Tubería PVC 110 mm Sanitario | F5: =1.1*1/6 -> 0.18333333 | G5: =16690/1.19 -> 14025.21 | H5: =ROUND(F5*G5,3) -> 2571.289 | J5: =F5*$F$4 -> 5.8666667 | K5: =H5*$F$4 -> 82281.248
C6: Subcontrato | D6: m | E6: SC Instalación Tuberías PVC | F6: 1 | G6: =SCSan -> 17000 | H6: =ROUND(F6*G6,3) -> 17000 | J6: =F6*$F$4 -> 32 | K6: =H6*$F$4 -> 544000
E7: Total APU 12.6 | F7: =$F$4 -> 32 | G7: =SUM(H5:H6) -> 19571.289 | H7: =ROUND(F7*G7,3) -> 626281.25 | K7: =SUM(K5:K6) -> 626281.25

Sheet 13.1
B1: 02.- Presupuesto'!A1
B3: Código | C3: Recurso | D3: Unidad | E3: Descripción | F3: Cantidad | G3: Precio Unitario | H3: Total | M3: Mat | N3: MO | O3: SC | P3: Arr
B4: 13.1 | C4: Partida | D4: ='01.- Presupuesto'!F95 -> m3 | E4: ='01.- Presupuesto'!C95 -> Suministro y colocación arena limpia compactada | F4: ='01.- Presupuesto'!G95 -> 14.4 | G4: =G11 -> 34686.583 | H4: =H11 -> 499486.79 | J4: Cantidad | K4: Costo | M4: =SUMIF(C5:C23,"Material",K5:K23) -> 449280 | N4: =SUMIF(C5:C23,"Mano de Obra",K5:K23) -> 20763.994 | O4: =SUMIF(C5:C23,"Subcontrato",K5:K23) -> 0 | P4: =SUMIF(C5:C23,"Ser&Arr",K5:K23) -> 29442.802 | Q4: =SUM(M4:P4) -> 499486.8
C5: Material | D5: m3 | E5: Arena | F5: 1.3 | G5: =Arena -> 24000 | H5: =ROUND(F5*G5,3) -> 31200 | J5: =F5*$F$4 -> 18.72 | K5: =H5*$F$4 -> 449280
C6: Mano de Obra | D6: hh | E6: Maestro | F6: =1/20 -> 0.05 | G6: =Maestro -> 7250 | H6: =ROUND(F6*G6,3) -> 362.5 | J6: =F6*$F$4 -> 0.72 | K6: =H6*$F$4 -> 5220
C7: Mano de Obra | D7: hh | E7: Jornal | F7: =4*1/20 -> 0.2 | G7: =Jornal -> 5397.2222 | H7: =ROUND(F7*G7,3) -> 1079.444 | J7: =F7*$F$4 -> 2.88 | K7: =H7*$F$4 -> 15543.994
C8: Ser&Arr | D8: % | E8: Desgaste de Herramientas | F8: 0.2 | G8: =SUM(H6:H7) -> 1441.944 | H8: =ROUND(F8*G8,3) -> 288.389 | J8: =F8*$F$4 -> 2.88 | K8: =H8*$F$4 -> 4152.8016
C9: Ser&Arr | D9: hm | E9: Retroexcavadora | F9: =1/20 -> 0.05 | G9: =Retroexcavadora -> 32000 | H9: =ROUND(F9*G9,3) -> 1600 | J9: =F9*$F$4 -> 0.72 | K9: =H9*$F$4 -> 23040
C10: Ser&Arr | D10: día | E10: Placa Compactadora | F10: =1/20/8 -> 0.00625 | G10: 25000 | H10: =ROUND(F10*G10,3) -> 156.25 | J10: =F10*$F$4 -> 0.09 | K10: =H10*$F$4 -> 2250
E11: Total APU 13.1 | F11: =$F$4 -> 14.4 | G11: =SUM(H5:H10) -> 34686.583 | H11: =ROUND(F11*G11,3) -> 499486.79 | K11: =SUM(K5:K10) -> 499486.8

Sheet 13.2
B1: 02.- Presupuesto'!A1
B3: Código | C3: Recurso | D3: Unidad | E3: Descripción | F3: Cantidad | G3: Precio Unitario | H3: Total | M3: Mat | N3: MO | O3: SC | P3: Arr
B4: 13.2 | C4: Partida | D4: ='01.- Presupuesto'!F96 -> m3 | E4: ='01.- Presupuesto'!C96 -> Suministro y colocación gravilla (bajo tamiz 1") | F4: ='01.- Presupuesto'!G96 -> 2.5 | G4: =G11 -> 37286.583 | H4: =H11 -> 93216.458 | J4: Cantidad | K4: Costo | M4: =SUMIF(C5:C23,"Material",K5:K23) -> 84500 | N4: =SUMIF(C5:C23,"Mano de Obra",K5:K23) -> 3604.86 | O4: =SUMIF(C5:C23,"Subcontrato",K5:K23) -> 0 | P4: =SUMIF(C5:C23,"Ser&Arr",K5:K23) -> 5111.5975 | Q4: =SUM(M4:P4) -> 93216.458
C5: Material | D5: m3 | E5: Gravilla | F5: 1.3 | G5: =Gravilla -> 26000 | H5: =ROUND(F5*G5,3) -> 33800 | J5: =F5*$F$4 -> 3.25 | K5: =H5*$F$4 -> 84500
C6: Mano de Obra | D6: hh | E6: Maestro | F6: =1/20 -> 0.05 | G6: =Maestro -> 7250 | H6: =ROUND(F6*G6,3) -> 362.5 | J6: =F6*$F$4 -> 0.125 | K6: =H6*$F$4 -> 906.25
C7: Mano de Obra | D7: hh | E7: Jornal | F7: =4*1/20 -> 0.2 | G7: =Jornal -> 5397.2222 | H7: =ROUND(F7*G7,3) -> 1079.444 | J7: =F7*$F$4 -> 0.5 | K7: =H7*$F$4 -> 2698.61
C8: Ser&Arr | D8: % | E8: Desgaste de Herramientas | F8: 0.2 | G8: =SUM(H6:H7) -> 1441.944 | H8: =ROUND(F8*G8,3) -> 288.389 | J8: =F8*$F$4 -> 0.5 | K8: =H8*$F$4 -> 720.9725
C9: Ser&Arr | D9: hm | E9: Retroexcavadora | F9: =1/20 -> 0.05 | G9: =Retroexcavadora -> 32000 | H9: =ROUND(F9*G9,3) -> 1600 | J9: =F9*$F$4 -> 0.125 | K9: =H9*$F$4 -> 4000
C10: Ser&Arr | D10: día | E10: Placa Compactadora | F10: =1/20/8 -> 0.00625 | G10: 25000 | H10: =ROUND(F10*G10,3) -> 156.25 | J10: =F10*$F$4 -> 0.015625 | K10: =H10*$F$4 -> 390.625
E11: Total APU 13.2 | F11: =$F$4 -> 2.5 | G11: =SUM(H5:H10) -> 37286.583 | H11: =ROUND(F11*G11,3) -> 93216.458 | K11: =SUM(K5:K10) -> 93216.458

Sheet 13.3
B1: 02.- Presupuesto'!A1
B3: Código | C3: Recurso | D3: Unidad | E3: Descripción | F3: Cantidad | G3: Precio Unitario | H3: Total | M3: Mat | N3: MO | O3: SC | P3: Arr
B4: 13.3 | C4: Partida | D4: ='01.- Presupuesto'!F97 -> un | E4: ='01.- Presupuesto'!C97 -> Suministro e instalación Cubos dren 26 t/m2 | F4: ='01.- Presupuesto'!G97 -> 48 | G4: =G8 -> 18599.722 | H4: =H8 -> 892786.66 | J4: Cantidad | K4: Costo | M4: =SUMIF(C5:C10,"Material",K5:K10) -> 546720 | N4: =SUMIF(C5:C10,"Mano de Obra",K5:K10) -> 346066.66 | O4: =SUMIF(C5:C10,"Subcontrato",K5:K10) -> 0 | P4: =SUMIF(C5:C10,"Ser&Arr",K5:K10) -> 0 | Q4: =SUM(M4:P4) -> 892786.66
C5: Material | D5: uni | E5: Cubo Drenaje INSYTEC Serie 3000 16/26T 0,425 x 0,38 x 0,79 m | F5: 1 | G5: =CuboDren -> 11390 | H5: =ROUND(F5*G5,3) -> 11390 | J5: =F5*$F$4 -> 48 | K5: =H5*$F$4 -> 546720
C6: Mano de Obra | D6: hh | E6: Maestro | F6: =1/4 -> 0.25 | G6: =Maestro -> 7250 | H6: =ROUND(F6*G6,3) -> 1812.5 | J6: =F6*$F$4 -> 12 | K6: =H6*$F$4 -> 87000
C7: Mano de Obra | D7: hh | E7: Jornal | F7: 1 | G7: =Jornal -> 5397.2222 | H7: =ROUND(F7*G7,3) -> 5397.222 | J7: =F7*$F$4 -> 48 | K7: =H7*$F$4 -> 259066.66
E8: Total APU 13.3 | F8: =$F$4 -> 48 | G8: =SUM(H5:H7) -> 18599.722 | H8: =ROUND(F8*G8,3) -> 892786.66 | K8: =SUM(K5:K7) -> 892786.66

Sheet 13.4
B1: 02.- Presupuesto'!A1
B3: Código | C3: Recurso | D3: Unidad | E3: Descripción | F3: Cantidad | G3: Precio Unitario | H3: Total | M3: Mat | N3: MO | O3: SC | P3: Arr
B4: 13.4 | C4: Partida | D4: ='01.- Presupuesto'!F98 -> m3 | E4: ='01.- Presupuesto'!C98 -> Excavación máquinaria local, traslado a botadero hasta 20km (geométrica, sin esponajamiento) | F4: ='01.- Presupuesto'!G98 -> 15 | G4: =G9 -> 25500 | H4: =H9 -> 382500 | J4: Cantidad | K4: Costo | M4: =SUMIF(C5:C21,"Material",K5:K21) -> 0 | N4: =SUMIF(C5:C21,"Mano de Obra",K5:K21) -> 0 | O4: =SUMIF(C5:C21,"Subcontrato",K5:K21) -> 0 | P4: =SUMIF(C5:C21,"Ser&Arr",K5:K21) -> 382500 | Q4: =SUM(M4:P4) -> 382500
C5: Ser&Arr | D5: hm | E5: Excavadora | F5: =1/20 -> 0.05 | G5: =Excavadora -> 50000 | H5: =ROUND(F5*G5,3) -> 2500 | J5: =F5*$F$4 -> 0.75 | K5: =H5*$F$4 -> 37500
C6: Ser&Arr | D6: hm | E6: Retroexcavadora | F6: =1/20 -> 0.05 | G6: =Retroexcavadora -> 32000 | H6: =ROUND(F6*G6,3) -> 1600 | J6: =F6*$F$4 -> 0.75 | K6: =H6*$F$4 -> 24000
C7: Ser&Arr | D7: hm | E7: Camión Tolva | F7: =1/20 -> 0.05 | G7: =Tolva -> 38000 | H7: =ROUND(F7*G7,3) -> 1900 | J7: =F7*$F$4 -> 0.75 | K7: =H7*$F$4 -> 28500
C8: Ser&Arr | D8: m3 | E8: Carga y Retiro de Escombros | F8: 1.3 | G8: 15000 | H8: =ROUND(F8*G8,3) -> 19500 | J8: =F8*$F$4 -> 19.5 | K8: =H8*$F$4 -> 292500
E9: Total APU 13.4 | F9: =$F$4 -> 15 | G9: =SUM(H5:H8) -> 25500 | H9: =ROUND(F9*G9,3) -> 382500 | K9: =SUM(K5:K8) -> 382500

Sheet 13.5
B1: 02.- Presupuesto'!A1
B3: Código | C3: Recurso | D3: Unidad | E3: Descripción | F3: Cantidad | G3: Precio Unitario | H3: Total | M3: Mat | N3: MO | O3: SC | P3: Arr
B4: 13.5 | C4: Partida | D4: ='01.- Presupuesto'!F99 -> m | E4: ='01.- Presupuesto'!C99 -> Suministro e instalación PVC 110mm | F4: ='01.- Presupuesto'!G99 -> 36 | G4: =G7 -> 19571.289 | H4: =H7 -> 704566.4 | J4: Cantidad | K4: Costo | M4: =SUMIF(C5:C19,"Material",K5:K19) -> 92566.404 | N4: =SUMIF(C5:C19,"Mano de Obra",K5:K19) -> 0 | O4: =SUMIF(C5:C19,"Subcontrato",K5:K19) -> 612000 | P4: =SUMIF(C5:C19,"Ser&Arr",K5:K19) -> 0 | Q4: =SUM(M4:P4) -> 704566.4
C5: Material | D5: uni | E5: Tubería PVC 110 mm Sanitario | F5: =1.1*1/6 -> 0.18333333 | G5: =16690/1.19 -> 14025.21 | H5: =ROUND(F5*G5,3) -> 2571.289 | J5: =F5*$F$4 -> 6.6 | K5: =H5*$F$4 -> 92566.404
C6: Subcontrato | D6: m | E6: SC Instalación Tuberías PVC | F6: 1 | G6: =SCSan -> 17000 | H6: =ROUND(F6*G6,3) -> 17000 | J6: =F6*$F$4 -> 36 | K6: =H6*$F$4 -> 612000
E7: Total APU 13.5 | F7: =$F$4 -> 36 | G7: =SUM(H5:H6) -> 19571.289 | H7: =ROUND(F7*G7,3) -> 704566.4 | K7: =SUM(K5:K6) -> 704566.4

Sheet 13.6
B1: 02.- Presupuesto'!A1
B3: Código | C3: Recurso | D3: Unidad | E3: Descripción | F3: Cantidad | G3: Precio Unitario | H3: Total | M3: Mat | N3: MO | O3: SC | P3: Arr
B4: 13.6 | C4: Partida | D4: ='01.- Presupuesto'!F100 -> un | E4: ='01.- Presupuesto'!C100 -> Suministro e instalación códo de PVC 110mm | F4: ='01.- Presupuesto'!G100 -> 5 | G4: =G7 -> 2698.506 | H4: =H7 -> 13492.53 | J4: Cantidad | K4: Costo | M4: =SUMIF(C5:C19,"Material",K5:K19) -> 1686.975 | N4: =SUMIF(C5:C19,"Mano de Obra",K5:K19) -> 0 | O4: =SUMIF(C5:C19,"Subcontrato",K5:K19) -> 11805.555 | P4: =SUMIF(C5:C19,"Ser&Arr",K5:K19) -> 0 | Q4: =SUM(M4:P4) -> 13492.53
C5: Material | D5: uni | E5: Codo PVC 110 mm Sanitario | F5: =1.1*1/6 -> 0.18333333 | G5: =2190/1.19 -> 1840.3361 | H5: =ROUND(F5*G5,3) -> 337.395 | J5: =F5*$F$4 -> 0.91666667 | K5: =H5*$F$4 -> 1686.975
C6: Subcontrato | D6: m | E6: SC Instalación Tuberías PVC | F6: =F4/'13.5'!F4 -> 0.13888889 | G6: =SCSan -> 17000 | H6: =ROUND(F6*G6,3) -> 2361.111 | J6: =F6*$F$4 -> 0.69444444 | K6: =H6*$F$4 -> 11805.555
E7: Total APU 13.6 | F7: =$F$4 -> 5 | G7: =SUM(H5:H6) -> 2698.506 | H7: =ROUND(F7*G7,3) -> 13492.53 | K7: =SUM(K5:K6) -> 13492.53

Sheet 13.7
B1: 02.- Presupuesto'!A1
B3: Código | C3: Recurso | D3: Unidad | E3: Descripción | F3: Cantidad | G3: Precio Unitario | H3: Total | M3: Mat | N3: MO | O3: SC | P3: Arr
B4: 13.7 | C4: Partida | D4: ='01.- Presupuesto'!F101 -> m2 | E4: ='01.- Presupuesto'!C101 -> Suministro e instalación de Geotextil | F4: ='01.- Presupuesto'!G101 -> 29 | G4: =G9 -> 1623.533 | H4: =H9 -> 47082.457 | J4: Cantidad | K4: Costo | M4: =SUMIF(C5:C21,"Material",K5:K21) -> 38280 | N4: =SUMIF(C5:C21,"Mano de Obra",K5:K21) -> 7335.376 | O4: =SUMIF(C5:C21,"Subcontrato",K5:K21) -> 0 | P4: =SUMIF(C5:C21,"Ser&Arr",K5:K21) -> 1467.081 | Q4: =SUM(M4:P4) -> 47082.457
C5: Material | D5: uni | E5: Malla Geotextil 2x50 | F5: =1/(2*50)*1.1 -> 0.011 | G5: 120000 | H5: =ROUND(F5*G5,3) -> 1320 | J5: =F5*$F$4 -> 0.319 | K5: =H5*$F$4 -> 38280
C6: Mano de Obra | D6: hh | E6: Maestro | F6: =1/50 -> 0.02 | G6: =Maestro -> 7250 | H6: =ROUND(F6*G6,3) -> 145 | J6: =F6*$F$4 -> 0.58 | K6: =H6*$F$4 -> 4205
C7: Mano de Obra | D7: hh | E7: Jornal | F7: =1/50 -> 0.02 | G7: =Jornal -> 5397.2222 | H7: =ROUND(F7*G7,3) -> 107.944 | J7: =F7*$F$4 -> 0.58 | K7: =H7*$F$4 -> 3130.376
C8: Ser&Arr | D8: % | E8: Desgaste de Herramientas | F8: 0.2 | G8: =SUM(H6:H7) -> 252.944 | H8: =ROUND(F8*G8,3) -> 50.589 | J8: =F8*$F$4 -> 5.8 | K8: =H8*$F$4 -> 1467.081
E9: Total APU 13.7 | F9: =$F$4 -> 29 | G9: =SUM(H5:H8) -> 1623.533 | H9: =ROUND(F9*G9,3) -> 47082.457 | K9: =SUM(K5:K8) -> 47082.457

Sheet 13.8
B1: 02.- Presupuesto'!A1
B3: Código | C3: Recurso | D3: Unidad | E3: Descripción | F3: Cantidad | G3: Precio Unitario | H3: Total | M3: Mat | N3: MO | O3: SC | P3: Arr
B4: 13.8 | C4: Partida | D4: ='01.- Presupuesto'!F102 -> m | E4: ='01.- Presupuesto'!C102 -> Suministro e instalación PVC110 mm ranurado | F4: ='01.- Presupuesto'!G102 -> 6 | G4: =G7 -> 20083.494 | H4: =H7 -> 120500.96 | J4: Cantidad | K4: Costo | M4: =SUMIF(C5:C19,"Material",K5:K19) -> 18500.964 | N4: =SUMIF(C5:C19,"Mano de Obra",K5:K19) -> 0 | O4: =SUMIF(C5:C19,"Subcontrato",K5:K19) -> 102000 | P4: =SUMIF(C5:C19,"Ser&Arr",K5:K19) -> 0 | Q4: =SUM(M4:P4) -> 120500.96
C5: Material | D5: uni | E5: Tubería Flexodren 110 | F5: =1.1*1/50 -> 0.022 | G5: =166789/1.19 -> 140158.82 | H5: =ROUND(F5*G5,3) -> 3083.494 | J5: =F5*$F$4 -> 0.132 | K5: =H5*$F$4 -> 18500.964
C6: Subcontrato | D6: m | E6: SC Instalación Tuberías PVC | F6: 1 | G6: =SCSan -> 17000 | H6: =ROUND(F6*G6,3) -> 17000 | J6: =F6*$F$4 -> 6 | K6: =H6*$F$4 -> 102000
E7: Total APU 13.8 | F7: =$F$4 -> 6 | G7: =SUM(H5:H6) -> 20083.494 | H7: =ROUND(F7*G7,3) -> 120500.96 | K7: =SUM(K5:K6) -> 120500.96

Sheet 14.1
B1: 02.- Presupuesto'!A1
B3: Código | C3: Recurso | D3: Unidad | E3: Descripción | F3: Cantidad | G3: Precio Unitario | H3: Total | M3: Mat | N3: MO | O3: SC | P3: Arr
B4: 14.1 | C4: Partida | D4: ='01.- Presupuesto'!F104 -> m3 | E4: ='01.- Presupuesto'!C104 -> Suministro e Instalación Hormigón G20(10)20-8 | F4: ='01.- Presupuesto'!G104 -> 2.94 | G4: =G13 -> 137616.83 | H4: =H13 -> 404593.49 | J4: Cantidad | K4: Costo | M4: =SUMIF(C5:C25,"Material",K5:K25) -> 354018.96 | N4: =SUMIF(C5:C25,"Mano de Obra",K5:K25) -> 28262.111 | O4: =SUMIF(C5:C25,"Subcontrato",K5:K25) -> 0 | P4: =SUMIF(C5:C25,"Ser&Arr",K5:K25) -> 22312.421 | Q4: =SUM(M4:P4) -> 404593.49
C5: Material | D5: m3 | E5: Hormigón G20(10)20-8 | F5: 1.1 | G5: =HormG20 -> 108376.92 | H5: =ROUND(F5*G5,3) -> 119214.61 | J5: =F5*$F$4 -> 3.234 | K5: =H5*$F$4 -> 350490.96
